Workbook
Name AC_gross_in: '[1]Programme Trajectory Input'!$D$101:$K$101
Name AC_net: '[1]Programme Trajectory Input'!$D$105:$K$105
Name Agri_Res_gross_in: '[1]Programme Trajectory Input'!$D$60:$K$60
Name BTR_gross_cum_in: '[1]Programme Trajectory Input'!$D$42
Name Demo_rebuild_PDR_gross_in: '[1]Programme Trajectory Input'!$D$61:$K$61
Name Ebbsfleet_additionality_factor_in: '[1]Programme Trajectory Input'!$C$90
Name Ebbsfleet_net: '[1]Programme Trajectory Input'!$D$91:$K$91
Name GBB_gross_cum_in: '[1]Programme Trajectory Input'!$D$43
Name HD_gross_in: '[1]Programme Trajectory Input'!$D$59:$K$59
Name House_price_growth: '[1]Private Baseline Calculation'!$AB$11
Name HtB_additionality_factor_in: '[1]Programme Trajectory Input'!$C$78
Name HtB_gross_in: '[1]Programme Trajectory Input'!$D$76:$K$76
Name Interbank_rate_prev3_q: '[1]Private Baseline Calculation'!$AB$10
Name Lag: '[1]Private Baseline Calculation'!$AB$18
Name Legacy_additionality_factor_in: '[1]Programme Trajectory Input'!$C$48
Name Legacy_dist_in: '[1]Programme Trajectory Input'!$D$44:$K$44
Name Legacy_gross: '[1]Programme Trajectory Input'!$D$45:$K$45
Name Legacy_net: '[1]Programme Trajectory Input'!$D$50:$K$50
Name LTF_additionality_factor: '[1]Programme Trajectory Input'!$C$34
Name LTF_dist_in: '[1]Programme Trajectory Input'!$D$30:$K$30
Name LTF_gross: '[1]Programme Trajectory Input'!$D$31:$K$31
Name LTF_gross_in: '[1]Programme Trajectory Input'!$D$29
Name LTF_net: '[1]Programme Trajectory Input'!$D$36:$K$36
Name Planning_additonality_factor_in: '[1]Programme Trajectory Input'!$C$65
Name Planning_gross: '[1]Programme Trajectory Input'!$D$63:$K$63
Name Planning_net: '[1]Programme Trajectory Input'!$D$67:$K$67
Name Pro_rata_factor: '[1]Programme Trajectory Input'!$D$18
Name Q1_: '[1]Private Baseline Calculation'!$AB$7
Name Q2_: '[1]Private Baseline Calculation'!$AB$8
Name Q3_: '[1]Private Baseline Calculation'!$AB$9
Name STIF_addiitonality_factor: '[1]Programme Trajectory Input'!$C$21
Name STIF_AF: '[1]Programme Trajectory Input'!$C$21
Name STIF_cs_in: '[1]Programme Trajectory Input'!$D$11:$K$11
Name STIF_fs_in: '[1]Programme Trajectory Input'!$D$12:$K$12
Name STIF_gross: '[1]Programme Trajectory Input'!$D$14:$K$14
Name STIF_gross_cum_total_in: '[1]Programme Trajectory Input'!$D$16
Name STIF_gross_cum_total_update_in: '[1]Programme Trajectory Input'!$D$17
Name STIF_net: '[1]Programme Trajectory Input'!$D$23:$K$23

Sheet LIVE LDS Data
A1: DO NOT EDIT
A2: ONSCODE | B2: Unique VLS code [only to be used where there is more than one plan] | C2: Local Planning Authority | D2: Title of Emerging Development Plan Document | E2: LDF Number | F2: Plan Period Start (YYYY) | G2: Plan Period End (YYYY) | H2: Aligned Plan (Y/N) | I2: Joint Plan (Y/N) | J2: Current Plan Adopted | K2: Previous Plan Adopted | L2: Delay | M2: Reason for delay | N2: Support Given | O2: Early Review? | P2: Emerging Plan Published | Q2: Emerging Plan Submitted | R2: Emerging Found Sound | S2: Emerging Plan found not legally compliant/unsound | T2: Emerging Plan Withdrawn / Work Stopped | U2: Self Review Date | V2: Decision | W2: LIVE Timetable or LIVE Reg 18? | X2: Timetable published? | Y2: Type of Timetable | Z2: IF no LDS or Timetable, has Reg 18 (or later) commenced? | AA2: URL of page including link to LDS | AB2: URL of LDS PDF | AC2: LDS Screenshot link | AD2: Date of LDS or website timetable (MMM-YYYY) | AE2: Scheduled date of first Regulation 18 consultation (as stated in LDS) | AF2: Title of consultation (if applicable) | AG2: Scheduled date of first Regulation 18 consultation (MMM-YYYY) | AH2: Actual Start date of First Regulation 18 Consultation | AI2: Actual End date of First Regulation 18 Consultation | AJ2: URL of First Reg 18 | AK2: Screenshot of First Reg 18 | AL2: Scheduled date of second Regulation 18 consultation (as stated in LDS) | AM2: Title of consultation (if applicable)- | AN2: Scheduled date of second Regulation 18 consultation (MMM-YYYY) | AO2: Actual Start date of Second Regulation 18 Consultation | AP2: Actual End date of Second Regulation 18 Consultation | AQ2: URL of Second Reg 18 | AR2: Screenshot of Second Reg 18 | AS2: Scheduled date of third Regulation 18 consultation (as stated in LDS) | AT2: Title of consultation (if applicable)-2 | AU2: Scheduled date of third Regulation 18 consultation (MMM-YYYY) | AV2: Actual Start date of Third Regulation 18 Consultation | AW2: Actual End date of Third Regulation 18 Consultation | AX2: URL of Third Reg 18 | AY2: Screenshot of Third Reg 18 | AZ2: Scheduled date of fourth Regulation 18 consultation (as stated in LDS) | BA2: Title of consultation (if applicable)-- | BB2: Scheduled date of fourth Regulation 18 consultation (MMM-YYYY) | BC2: Actual Start date of Fourth Regulation 18 Consultation | BD2: Actual End date of Fourth Regulation 18 Consultation | BE2: URL of Fourth Reg 18 | BF2: Screenshot of Fourth Reg 18 | BG2: Scheduled date of publication (as stated in LDS) | BH2: Scheduled date of publication (MMM-YYYY) | BI2: Actual Date of Publication | BJ2: Scheduled date of submission (as stated in LDS) | BK2: Scheduled date of submission (MMM-YYYY) | BL2: Actual Date of submission | BM2: Scheduled date of adoption (as stated in LDS) | BN2: Scheduled date of adoption (MMM-YYYY) | BO2: Actual Date of Adoption | BP2: Source of intel/comments/notes | BQ2: Any further notes - not for summary table | BR2: Emerging Joint Plan Summary Position (if applicable, for summary) | BS2: Date LDS checked (no change) | BT2: Date LDS updated (with changes) | BU2: Date Consultation Timetable checked (no change) | BV2: Date Consultation Timetable updated (with changes) | BW2: Intel updated (if applicable) | BX2: STAGE ** | BY2: Current Delay (months) | BZ2: Monitoring ('Alpha') | CA2: Change detected | CB2: Change omitted | CC2: Change omitted - Notes | CD2: PINS Intel Received? (Y/N)
A3: E07000223 | C3: Adur | D3: Adur Local Plan | E3: 2342 | F3: 2024 | G3: 2039 | H3: N | I3: N | J3: 43083 | L3: YES | U3: 2021 | V3: Decided it is necessary to update the Plan (source: November 2021 newsletter). | W3: =IF(OR(X3="Yes", Y3="Web-page timetable", Z3="YES"), "Yes") -> Yes | X3: Yes | Y3: LDS Document | AA3: https://www.adur-worthing.gov.uk/adur-local-plan-update/#adur-lds | AB3: https://www.adur-worthing.gov.uk/media/Media,98763,smxx.pdf | AD3: 45717 | AE3: Summer 2024 | AF3: Reg 18 consultation | AG3: 45474 | AH3: 45622 | AI3: 46027 | AJ3: https://www.adur-worthing.gov.uk/alp-key-issues-consultation/ | AL3: 46327 | AM3: Reg 18 | AN3: 46327 | BG3: 46600 | BH3: 46600 | BJ3: 46722 | BK3: 46722 | BM3: 46905 | BN3: 46905 | BP3: Draft LDS Mar 2025 | BS3: 45562 | BT3: 45743 | BU3: 45562 | BV3: 45743 | BW3: 45743 | BX3: new plan to be prepared under new system | BZ3: VisualPing | CA3: x
A4: E07000026 | C4: Allerdale (now part of Cumberland) | D4: Allerdale Local Plan Review | J4: 41836 | L4: YES | M4: Nutrient neutrality (March 2022); | W4: =IF(OR(X4="Yes", Y4="Web-page timetable", Z4="YES"), "Yes") -> FALSE | X4: Yes, but refers to something else | Y4: LDS Document | AA4: https://www.allerdale.gov.uk/en/planning-building-control/planning-policy/local-development-scheme/ | AB4: https://www-cloudfront.allerdale.gov.uk/media/filer_public/a8/7d/a87d1a25-6deb-4a2d-bf14-1d77a25a173c/lds_march_2022.pdf | AD4: 44621 | BG4: 45170 | BH4: 45170 | BJ4: 45261 | BK4: 45261 | BM4: TBC | BN4: TBC | BS4: 45061 | BT4: 44659 | BV4: 44796 | BW4: 44796 | BX4: DEFUNCT LPA [new unitary authority to prepare plan] | BZ4: VisualPing
A5: E07000032 | C5: Amber Valley | D5: Amber Valley Borough Local Plan | E5: 2191 | F5: 2022 | G5: 2040 | H5: N | I5: N | J5: none | L5: Yes | M5: Previous emerging plan withdrawn May 2019 DtC - 2023 (with Derby over meeting their unmet need) | P5: 45338 | Q5: 45502 | W5: =IF(OR(X5="Yes", Y5="Web-page timetable", Z5="YES"), "Yes") -> Yes | X5: Yes | Y5: LDS Document | AA5: https://www.ambervalley.gov.uk/planning/planning-policy/local-development-scheme/ | AB5: https://info.ambervalley.gov.uk/docarc/docviewer.aspx?docguid=d8d0717dd04d40f993ce3dfd0c84fb07 | AD5: 45689 | AE5: July - Sep 2021 | AF5: Alternative Spatial Strategy Options | AG5: 44378 | AH5: 44378 | AI5: 44440 | AJ5: https://www.ambervalley.gov.uk/planning/planning-policy/local-plan/alternative-spatial-strategy-options-for-housing-and-economic-growth/ | AL5: July - Aug 2022 | AM5: Preferred Spatial Strategy and draft policies | AN5: 44743 | AO5: 44757 | AP5: 44806 | AQ5: https://www.ambervalley.gov.uk/planning/planning-policy/local-plan/ | BG5: 45292 | BH5: 45292 | BI5: 45338 | BJ5: 45383 | BK5: Apr-2024 | BL5: 45502 | BM5: 46082 | BN5: 46082 | BP5: Feb 2025 LDS | BQ5: March-2024 (was TBC, Sep-2023) pins est. 29/04/24 | BS5: 45960 | BT5: 45743 | BV5: 45743 | BW5: 46027 | BX5: Submitted July 2024 | BZ5: VisualPing
A6: E07000224 | C6: Arun | D6: Arun Local Plan Update 2023 - 2041 | E6: 2328 | F6: 2023 | G6: 2041 | H6: N | I6: N | J6: 43299 | L6: YES | M6: Expected changes to Planning Bill | W6: =IF(OR(X6="Yes", Y6="Web-page timetable", Z6="YES"), "Yes") -> Yes | X6: Yes | Y6: LDS Document | AA6: https://www.arun.gov.uk/local-development-scheme-lds | AB6: https://www.arun.gov.uk/arun-district-council-local-development-scheme | AD6: 45717 | AE6: Spring/Summer 2024 | AF6: Issues and Options | AG6: 45383 | AH6: 45376 | AI6: 45536 | AJ6: https://www.arun.gov.uk/arun-local-plan-update-2023-2041/ | AL6: April - Sept 2026 | AM6: Draft DPD consultation | AN6: 46113 | BG6: April - Sept 2027 | BH6: 46478 | BJ6: 46753 | BK6: 46753 | BM6: Summer 2028 | BN6: 46935 | BP6: LDS Updates - Mar 2025 (draft LDS) | BQ6: consulted on the first document to inform production of the Local Plan update from 25 March until 13 May 2024 | BS6: 45576 | BT6: 45743 | BU6: 45576 | BV6: 45743 | BW6: 45302 | BX6: new plan to be prepared under new system
A7: E07000170 | C7: Ashfield | D7: Local Plan 2023-2040 | E7: 2131 | F7: 2023 | G7: 2040 | H7: N | I7: N | J7: none | L7: YES | M7: change of political control LHN | P7: 45261 | Q7: 45411 | W7: =IF(OR(X7="Yes", Y7="Web-page timetable", Z7="YES"), "Yes") -> Yes | X7: Yes | Y7: LDS Document | AA7: https://www.ashfield.gov.uk/planning-and-building-control/emerging-local-plan/ | AB7: https://www.ashfield.gov.uk/media/fcrpp1b4/local-development-scheme-january-2025.docx | AD7: 45658 | AE7: January/February 2020 | AF7: Draft Plan | AG7: 43831 | AH7: 44473 | AI7: 44516 | AJ7: https://www.ashfield.gov.uk/planning-building-control/local-plan/emerging-local-plan/ | BG7: Nov 2023-Feb 2024 | BH7: 45231 | BI7: 45261 | BJ7: 45413 | BK7: 45413 | BL7: 45411 | BM7: 46203 | BN7: 46174 | BP7: LDS Updates - Mar 2025 | BQ7: Ashfield had a change of policital control in 2018 (to independents) and subsequently decided to withdraw their plan from examination in September 2018. Ashfield then started work on a new Local Plan. | BS7: 45960 | BT7: 45743 | BU7: 44825 | BV7: 45743 | BW7: 45868 | BX7: Submitted April 2024 [plan paused] | BZ7: Published - Dec 2023 Visualping
A8: E07000105 | C8: Ashford | D8: Ashford Local Plan 2042 | E8: 2354 | F8: 2024 | G8: 2042 | H8: N | I8: N | J8: 43517 | L8: YES | M8: Nutrient neutrality (since 2018) | W8: =IF(OR(X8="Yes", Y8="Web-page timetable", Z8="YES"), "Yes") -> Yes | X8: Yes | Y8: LDS Document | AA8: https://www.ashford.gov.uk/planning-and-development/our-planning-policies/planning-policy-consultations-current-historic/local-development-scheme/ | AB8: https://www.ashford.gov.uk/media/zegd5h5p/lds-2024-1-use.pdf | AD8: 45474 | AE8: Qtr 2 2025 | AF8: Reg 18 consultation | AG8: 45748 | AH8: 45887 | AI8: 45943 | AJ8: https://haveyoursay.ashford.gov.uk/draft-lp42-consultation | BG8: Q1 2026 | BH8: 46054 | BJ8: Q3 2026 | BK8: 46266 | BM8: Q3 2027 | BN8: 46478 | BP8: LDS Updates - Mar 2025 | BS8: 46024 | BT8: 45743 | BU8: 45856 | BV8: 45918 | BW8: 45743 | BX8: Reg 18 completed | BZ8: VisualPing
A9: E07000004 | C9: Aylesbury Vale (defunct) | D9: The Vale of Aylesbury Local Plan (VALP) | J9: 44454 | K9: none [Sep 2021 adopted plan is first post-2004 Act Plan] | P9: 43041 | Q9: 43159 | R9: 44427 | W9: =IF(OR(X9="Yes", Y9="Web-page timetable", Z9="YES"), "Yes") -> Yes | X9: Yes | Y9: LDS Document | AA9: https://www.aylesburyvaledc.gov.uk/section/vale-aylesbury-local-plan-valp-2013-2033 | AB9: https://www.aylesburyvaledc.gov.uk/sites/default/files/page_downloads/2018%20%28Jan%29%20LDS%20FINAL_0.pdf | AC9: https://teams.microsoft.com/_#/png/viewer/teams/https:~2F~2Fmhclg.sharepoint.com~2Fsites~2FDevelopmentPlans~2FShared%2520Documents~2FData%2520and%2520Analysis~2FPlanning%2520Data%2520Unit~2FData%2520Project~2FShort-term%2520Solution~2FLDS%2520Approach~2FLDS%2520screen%2520captures~2FAYL18%2520-%2520Aylesbury%2520Vale%2520LDS%25202018.PNG?threadId=19:02cfc1d922c64c5584e5731b4a607ece@thread.skype&fileId=4A363F8A-D4AC-4A42-99AE-01F460EE805E&ctx=files&viewerAction=view | AD9: 43101 | AE9: October-December 2015 | AG9: 42309 | AL9: July to September 2016 | AN9: 42583 | BG9: November/December 2017 | BH9: 43040 | BI9: =P9 -> 43041 | BJ9: 43132 | BK9: 43132 | BL9: =Q9 -> 43159 | BM9: 43466 | BN9: 43466 | BO9: 44440 | BS9: 43676 | BW9: 44461 | BX9: DEFUNCT LPA [new unitary authority to prepare plan]
A10: E07000200 | C10: Babergh | D10: Babergh & Mid Suffolk Joint Local Plan | E10: TBA | H10: N | I10: Y | J10: 45251 | K10: 41695 | W10: =IF(OR(X10="Yes", Y10="Web-page timetable", Z10="YES"), "Yes") -> Yes | X10: Yes | Y10: LDS Document | AA10: https://www.babergh.gov.uk/joint-local-plan | AB10: https://www.babergh.gov.uk/documents/d/asset-library-54706/babergh-and-mid-suffolk-joint-local-development-scheme-2025-2029 | AD10: 45717 | AE10: Aug 2026 - Mar 2027 | AF10: First Public Consultation | AG10: 46235 | BG10: Jan - June 2028 | BH10: 46753 | BJ10: 46905 | BK10: 46905 | BM10: 47209 | BN10: 47209 | BP10: LDS Updates - Mar 2025 (joint Feb 2025 LDS). Website (02/10/2025) | BS10: 45960 | BT10: 45743 | BV10: 45743 | BW10: 45932 | BX10: new plan to be prepared under new system | BZ10: Babergh adopted 21 Nov 2023 | CD10: Yes
A11: E09000002 | C11: Barking & Dagenham | D11: New Local Plan | H11: N | I11: N | J11: 45553 | K11: 40380 | L11: YES | M11: OTHER | W11: =IF(OR(X11="Yes", Y11="Web-page timetable", Z11="YES"), "Yes") -> Yes | X11: Yes | Y11: LDS Document | AA11: https://www.lbbd.gov.uk/planning-building-control-and-local-land-charges/planning-guidance-and-policies/local-plan | AB11: https://www.lbbd.gov.uk/sites/default/files/2025-02/LDS%20February%202025%20Update.pdf | AD11: 45689 | AE11: 2028 | AF11: Reg 18 equivalent | AG11: 2028 | BG11: 46935 | BH11: 46935 | BJ11: 47119 | BK11: 47119 | BM11: 47453 | BN11: 47453 | BP11: LDS Updates - Mar 2025 | BS11: 45961 | BT11: 45743 | BU11: 44267 | BV11: 45743 | BW11: 45700 | BX11: new plan to be prepared under new system | BZ11: Submitted Dec 2021
A12: E09000003 | C12: Barnet | D12: New Local Plan for Barnet | H12: N | I12: N | J12: 45720 | K12: 41163 | W12: =IF(OR(X12="Yes", Y12="Web-page timetable", Z12="YES"), "Yes") -> Yes | X12: Yes | Y12: LDS Document | AA12: https://www.barnet.gov.uk/planning-and-building/planning-policies/local-plan-review | AB12: https://www.barnet.gov.uk/sites/default/files/appendix_g_-_local_development_scheme.pdf | AC12: https://mhclg.sharepoint.com/sites/DevelopmentPlans/Shared%20Documents/Data%20and%20Analysis/Planning%20Data%20Unit/LDS%20&%20Reg%2018%20Monitoring/LDS%20Screenshots/BAR20%20-%20Barnet%20LDS%20Jan%202020.PNG | AD12: 45689 | AE12: 46174 | AF12: Reg 18 equivalent | AG12: 46174 | AL12: 46388 | AM12: Reg 18 equivalent | AN12: 46388 | BG12: 46569 | BH12: 46569 | BJ12: 46874 | BK12: 46874 | BM12: 47058 | BN12: 47058 | BP12: LDS (Feb 2025) | BS12: 45961 | BT12: 45744 | BU12: 44463 | BV12: 45744 | BW12: 45744 | BX12: new plan to be prepared under new system | BZ12: Submitted Nov 2021
A13: E08000016 | C13: Barnsley | D13: new system | E13: n/a | J13: 43468 | U13: 44889 | V13: No need to update local plan. Further review in 2027 | W13: =IF(OR(X13="Yes", Y13="Web-page timetable", Z13="YES"), "Yes") -> FALSE | X13: No | Y13: None | BP13: LPA's website | BQ13: The Local Plan review was endorsed at a meeting of Full Council on 24 November 2022. The review concluded that the Local plan remains fit for purpose and is adequately delivering its objectives. This means no updates to the Local Plan, in whole or in part, are to be carried out ahead of a further review. A further review will take place in 2027 or earlier if circumstances, including fundamental changes to the Local Plan system, require it. | BS13: 23/08/2023 [none found] | BW13: 44648 | BX13: new plan to be prepared under new system
A14: E07000027 | C14: Barrow-in-Furness (unitarised in 2023, now Westmorland and Furness) | D14: Barrow Borough Council Local Plan | J14: 43620 | W14: =IF(OR(X14="Yes", Y14="Web-page timetable", Z14="YES"), "Yes") -> FALSE | X14: Yes, but TT refers to adopted Plan | Y14: LDS Document | AA14: https://www.barrowbc.gov.uk/residents/planning/planning-policy/examination-of-local-plan/examination-library/supporting-documents/ | AB14: https://www.barrowbc.gov.uk/residents/planning/planning-policy/examination-of-local-plan/examination-library/supporting-documents/?entryid1=5956 | AC14: https://teams.microsoft.com/_#/png/viewer/teams/https:~2F~2Fmhclg.sharepoint.com~2Fsites~2FDevelopmentPlans~2FShared%20Documents~2FData%20and%20Analysis~2FPlanning%20Data%20Unit~2FData%20Project~2FShort-term%20Solution~2FLDS%20Approach~2FLDS%20screen%20captures~2FBAR16%20-%20Barrow-in-Furness%20LDS%202016.PNG?threadId=19:02cfc1d922c64c5584e5731b4a607ece@thread.skype&baseUrl=https:~2F~2Fmhclg.sharepoint.com~2Fsites~2FDevelopmentPlans&fileId=5FA8388F-9974-45E1-BC07-1BC0787AC89F&ctx=files&viewerAction=view | AD14: 43497 | BS14: 45013 | BU14: 45013 | BX14: DEFUNCT LPA [new unitary authority to prepare plan]
A15: E07000066 | C15: Basildon | D15: New Local Plan (previous emerging plan withdrawn from examination) | E15: 2299 | F15: 2023 | G15: 2043 | H15: N | I15: N | J15: none | L15: Yes | M15: Previous emerging plan withdrawn from examination | W15: =IF(OR(X15="Yes", Y15="Web-page timetable", Z15="YES"), "Yes") -> Yes | X15: Yes | Y15: LDS Document | AA15: https://www.basildon.gov.uk/article/2012/Timetable-and-Consultation-Standards | AB15: https://www.basildon.gov.uk/media/12610/Basildon-Borough-Council-Local-Development-Scheme-2025-2026/pdf/Basildon_Borough_Council_Local_Development_Scheme_2025-2026.pdf?m=1761645190953 | AD15: 45931 | AE15: Q2 2023 | AF15: Issues and Options Consultation | AG15: 45047 | AH15: 45104 | AI15: 45174 | AJ15: https://www.basildon.gov.uk/article/9107/Local-Plan-Latest-news-and-updates | AK15: https://basildonlocalplan.commonplace.is/timeline | AL15: Winter 2024 (Q1) | AM15: First Draft Local Plan Consultation (Reg 18) | AN15: 45658 | AO15: 45597 | AP15: 45658 | AQ15: https://www.basildon.gov.uk/article/9107/Local-Plan-Latest-news-and-updates | AS15: 45689 | AT15: Second Focused Draft Local Plan consultation | AU15: 45748 | AV15: 45719 | AW15: 45761 | AX15: https://basildonlocalplan.commonplace.is/timeline | AZ15: Nov 2025 - Jan 2026 | BA15: Third Draft Plan consultation | BB15: 45962 | BC15: 45989 | BD15: 46038 | BE15: https://www.basildon.gov.uk/article/9107/Local-Plan-Latest-news-and-updates | BG15: Q1 2026 winter | BH15: 46023 | BJ15: Q2 2026 Spring | BK15: 46113 | BM15: Q4 2026 autumn | BN15: 46296 | BP15: Oct 2025 LDS & LPA website (Dec 2025) | BS15: 46024 | BT15: 45960 | BU15: 45121 | BV15: 45996 | BW15: 45996 | BX15: Reg 18 ongoing | BZ15: VisualPing
A16: E07000084 | C16: Basingstoke and Deane | D16: Local Plan | E16: 2327 | F16: 2021 | G16: 2040 | H16: N | I16: N | J16: 42516 | L16: YES | M16: Nutrient neutrality (since 2018) | W16: =IF(OR(X16="Yes", Y16="Web-page timetable", Z16="YES"), "Yes") -> Yes | X16: Yes | Y16: Web-page timetable | AA16: https://www.basingstoke.gov.uk/LDS | AB16: https://www.basingstoke.gov.uk/LDS | AD16: 45689 | AE16: Winter 2023/24 | AF16: Draft Plan (Reg 18) | AG16: 45292 | AH16: 45313 | AI16: 45355 | AJ16: https://www.basingstoke.gov.uk/LPU-reg18-consultation | AL16: Autumn/Winter 2025 | AM16: Additional consultation on draft plan | AN16: 45931 | BG16: Summer 2026 | BH16: 46204 | BJ16: Winter 2026 | BK16: 46357 | BM16: Winter 2027 | BN16: 46753 | BP16: LDS (Feb 2025) | BR16: 45589 | BS16: 46297 | BT16: 45743 | BU16: 45298 | BV16: 45743 | BW16: 45744 | BX16: Reg 18 ongoing | BZ16: VisualPing
A17: E07000171 | C17: Bassetlaw | D17: Bassetlaw Local Plan 2028-2043 | E17: TBC | F17: 2028 | G17: 2043 | H17: N | I17: N | J17: 45441 | K17: 40899 | W17: =IF(OR(X17="Yes", Y17="Web-page timetable", Z17="YES"), "Yes") -> Yes | X17: Yes | Y17: LDS Document | AA17: https://www.bassetlaw.gov.uk/planning-and-building/planning-services/planning-policy/local-development-scheme/ | AB17: https://www.bassetlaw.gov.uk/media/zeffmlis/local-development-scheme-2025.pdf | AD17: 45717 | BG17: TBC | BH17: TBC | BJ17: 46997 | BK17: 46997 | BM17: April - May 2029 | BN17: 47209 | BP17: LDS (March 2025) | BQ17: Draft Bassetlaw Plan (Nov 2020) consulted on Nov 2020 - Jan 2021. A further Reg 18 consultation (Draft Bassetlaw Local Plan Focussed Consultation) closed 21 July 2021, but not recorded on our timeline here. | BS17: 45071 | BT17: 45744 | BV17: 45744 | BW17: 45744 | BX17: new plan to be prepared under new system | BZ17: FS 21 Feb 2024
B18: E06000022-03 | C18: Bath & North East Somerset | D18: Bath and North East Somerset Local Plan (Core Strategy and Placemaking Plan incorporating the Local Plan Partial Update) [not strategic in terms of housing requirement] | E18: 2103 | F18: 2011 | G18: 2029 | H18: N | I18: N | J18: 10 July 2014 (as amended by partial update on 19 Jan 2023) | P18: 44435 | Q18: 44547 | R18: 44908 | W18: =IF(OR(X18="Yes", Y18="Web-page timetable", Z18="YES"), "Yes") -> Yes | X18: Yes | Y18: LDS Document | AA18: https://beta.bathnes.gov.uk/planning-consultation-local-plan-partial-update-and-statement-community-involvement | AB18: https://beta.bathnes.gov.uk/sites/default/files/2021-08/LDS%20July%202021%20Final%20-%20accessible.pdf | AD18: 2022 | AE18: April - June 2020 | AF18: Planning consultation: Local Plan partial update and Statement of Community Involvement | AG18: 43922 | AH18: 43927 | AI18: 43983 | AJ18: https://beta.bathnes.gov.uk/sites/default/files/2020-04/LP%20Commencement%20April%202020v5%20%28FINAL%29.pdf | AL18: Nov/Dec 2020 | AM18: Options Consultation | AN18: 44136 | AO18: 44203 | AP18: 44245 | AQ18: https://beta.bathnes.gov.uk/local-plan-partial-update-options-consultation | BM18: 44927 | BN18: 44927 | BO18: 44927 | BR18: Statutory consultation on draft plan scheduled for Spring 2022 but missed. Work halted due to lack of agreement by South Gloucestershire (who want to commence work on their own plan). | BS18: 44736 | BT18: 44629 | BU18: 44656 | BV18: 44629 | BW18: 44629 | BX18: partial update adopted Jan-2023 | BZ18: Adopted 19 Jan 2023
B19: E06000022-02 | C19: Bath & North East Somerset | D19: WECA Spatial Development Strategy (SDS) | F19: 2022 | G19: 2042 | H19: N | I19: SDS | J19: 10 July 2014 (as amended by partial update on 19 Jan 2023) | L19: YES | M19: lack of agreement | W19: =IF(OR(X19="Yes", Y19="Web-page timetable", Z19="YES"), "Yes") -> Yes | X19: Yes | Y19: LDS Document | AA19: https://www.westofengland-ca.gov.uk/what-we-do/planning-housing/spatial-development-strategy/ | AB19: https://beta.bathnes.gov.uk/sites/default/files/2021-08/LDS%20July%202021%20Final%20-%20accessible.pdf | AD19: 2021 | AE19: Second Half of 2021 | AF19: Draft SDS Public consultation | AG19: 44378 | BG19: Spring 2022 | BH19: 44652 | BJ19: Spring 2023 | BK19: 45017 | BM19: TBC | BN19: TBC | BR19: Statutory consultation on draft plan scheduled for Spring 2022 but missed. Work halted due to lack of agreement by South Gloucestershire (who want to progress work on their own plan). | BS19: 44628 | BU19: 44628 | BW19: 44740 | BX19: work stopped | BZ19: VisualPing
A20: E06000022 | C20: Bath & North East Somerset | D20: Bath and North East Somerset Council New Local Plan (2022-2042) | E20: 2290 | F20: 2022 | G20: 2042 | H20: N | I20: N | J20: 10 July 2014 (as amended by partial update on 19 Jan 2023) | W20: Yes | X20: Yes | Y20: LDS Document | AA20: https://beta.bathnes.gov.uk/policy-and-documents-library/local-development-scheme | AB20: https://www.bathnes.gov.uk/policy-and-documents-library/local-development-scheme | AD20: 45748 | AE20: 44835 | AF20: Options Consultation | AG20: 44835 | AH20: 44838 | AI20: 44880 | AJ20: https://beta.bathnes.gov.uk/local-plan-launch-document-consultation | AL20: Oct - Dec 2023 | AM20: Options | AN20: 45200 | AO20: 45334 | AP20: 45390 | AQ20: https://beta.bathnes.gov.uk/local-plan-2022-2042-development-timeline | AS20: Aug - Sep 2025 | AT20: Options | AU20: 45870 | AV20: 45931 | AW20: 45962 | AX20: https://bathnesplaces.co.uk/localplan/ | BG20: May - July 2026 | BH20: 46143 | BJ20: 46296 | BK20: 46296 | BM20: Sept/Oct 2027 | BN20: 46631 | BP20: April 2025 LDS revision | BS20: 46024 | BT20: 46031 | BV20: 46031 | BW20: 46031 | BX20: Reg 18 completed | BZ20: VisualPing
A21: E06000055 | C21: Bedford | D21: Local Plan 2040 | E21: 2183 | F21: 2020 | G21: 2040 | H21: N | I21: N | J21: 43845 | O21: YES | P21: 44727 | Q21: 44938 | T21: 45938 | W21: =IF(OR(X21="Yes", Y21="Web-page timetable", Z21="YES"), "Yes") -> Yes | X21: Yes | Y21: LDS Document | AA21: https://www.bedford.gov.uk/planning-and-building-control/planning-policy/local-development-scheme | AB21: https://www.bedford.gov.uk/media/4027/download?inline | AD21: 44562 | AE21: July - Sept 2020 | AF21: Issues and Options | AG21: 44026 | AH21: 44013 | AI21: 44088 | AJ21: https://www.bedford.gov.uk/planning-and-building/planning-policy-its-purpose/local-plan-review/ | AL21: July - Sept 2021 | AM21: Draft Plan Consultation | AN21: 44378 | AO21: 44391 | AP21: 44443 | AQ21: https://www.bedford.gov.uk/planning-and-building/planning-policy-its-purpose/local-plan-review/ | BG21: May - June 2022 | BH21: 44682 | BI21: 44727 | BJ21: 44927 | BK21: 44927 | BL21: 44938 | BM21: 45261 | BN21: 45261 | BS21: 45961 | BT21: 44461 | BV21: 44960 | BX21: WITHDRAWN 8 Oct 2025 | BZ21: early review Submitted Jan 2023
A22: E09000004 | C22: Bexley | D22: Bexley Local Plan | E22: TBA | H22: N | I22: N | J22: 45042 | K22: 40961 | U22: 2017 | V22: Will update Plan | W22: =IF(OR(X22="Yes", Y22="Web-page timetable", Z22="YES"), "Yes") -> Yes | X22: Yes | Y22: LDS Document | AB22: https://www.bexley.gov.uk/sites/default/files/2025-03/bexley-local-development-scheme-march-2025.pdf | AD22: 45717 | AE22: 47058 | AF22: Reg 18 equivalent | AG22: 47058 | BG22: 47300 | BH22: 47300 | BJ22: 47543 | BK22: 47543 | BM22: 47757 | BN22: 47757 | BP22: March 2025 LDS | BS22: 45888 | BT22: 44320 | BU22: 45888 | BV22: 45744 | BW22: 45744 | BX22: new plan to be prepared under new system | BZ22: Adopted 26 April 2023
A23: E08000025 | C23: Birmingham | D23: Birmingham Local Plan 2042 | E23: 2300 | F23: 2020 | G23: 2042 | H23: N | I23: N | J23: 42745 | L23: YES | U23: 43983 | V23: need to update local plan | W23: =IF(OR(X23="Yes", Y23="Web-page timetable", Z23="YES"), "Yes") -> Yes | X23: Yes | Y23: LDS Document | AA23: https://www.birmingham.gov.uk/downloads/file/845/local_development_scheme_for_birmingham | AB23: https://www.birmingham.gov.uk/download/downloads/id/845/local_development_scheme_for_birmingham.pdf | AD23: 45689 | AE23: Oct - Nov 2022 | AF23: Issues & Options | AG23: 44835 | AH23: 44858 | AI23: 44900 | AJ23: https://www.birmingham.gov.uk/info/20008/planning_and_development/2477/new_local_plan_for_birmingham#:~:text=We%20are%20working%20on%20a,Local%20Plan%20has%20now%20concluded. | AL23: June-July 2024 | AM23: Preferred Options | AN23: 45444 | AO23: 45474 | AP23: 45505 | AS23: Nov/Dec 2025 | AT23: Further Preferred Options | AU23: 45992 | BG23: June/July 2026 | BH23: 46204 | BJ23: 46296 | BK23: 46296 | BM23: 46631 | BN23: 46631 | BP23: Jan/Feb 2025 LDS | BS23: 46024 | BT23: 45686 | BU23: 45960 | BV23: 45686 | BX23: Reg 18 ongoing | BZ23: VisualPing
A24: E07000129 | C24: Blaby | D24: Blaby District New Local Plan | E24: 2112 | F24: 2022 | G24: 2042 | H24: N | I24: N | J24: 41326 | L24: YES | W24: =IF(OR(X24="Yes", Y24="Web-page timetable", Z24="YES"), "Yes") -> Yes | X24: Yes | Y24: LDS Document | AA24: https://www.blaby.gov.uk/planning-and-building/local-plan/about-the-local-plan/ | AB24: https://www.blaby.gov.uk/media/i0of4qyl/blaby-district-local-plan-local-development-scheme-2025.pdf | AD24: 45717 | AE24: July/August 2019 | AF24: Issues and Options | AG24: 43647 | AH24: 43647 | AI24: 43738 | AJ24: https://www.blaby.gov.uk/planning-and-building/local-plan/new-local-plan/ | AK24: https://mhclg.sharepoint.com/sites/DevelopmentPlans/Shared%20Documents/Data%20and%20Analysis/Planning%20Data%20Unit/Reg%2018%20monitoring/Screenshots/Blaby%20Issues%20&%20Options%20June%202019.PNG | AL24: Jan/Feb 2021 | AM24: Draft Plan | AN24: 44197 | AO24: 44197 | AP24: 44256 | AQ24: https://www.blaby.gov.uk/planning-and-building/local-plan/new-local-plan/ | BG24: 46113 | BH24: 46113 | BJ24: TBC (was Dec 2025) | BK24: TBC | BM24: TBC (was Dec 2026) | BN24: TBC | BP24: March 2025 LDS & update from website (Jan 2026) | BS24: 46024 | BT24: 45763 | BU24: 45559 | BV24: 46024 | BW24: 45635 | BX24: Reg 18 completed | BZ24: Email Alert; VisualPing
A25: E06000008 | C25: Blackburn with Darwen | D25: Blackburn with Darwen Local Plan (single plan) | E25: 2104 | F25: 2021 | G25: 2037 | H25: N | I25: N | J25: 45316 | K25: 40570 | L25: YES | M25: Covid-19 | P25: 44596 | Q25: 44778 | R25: 45271 | W25: =IF(OR(X25="Yes", Y25="Web-page timetable", Z25="YES"), "Yes") -> FALSE | X25: Yes, but TT refers to adopted Plan | Y25: LDS Document | AA25: https://www.blackburn.gov.uk/planning/planning-policies-strategies-and-guides/local-development-scheme | AB25: https://democracy.blackburn.gov.uk/documents/s21585/Blackburn%20Local%20Development%20Scheme%202023%20final.pdf | AD25: 45170 | AE25: Feb - April 2019 | AF25: Issues & Options | AG25: 43525 | AH25: 43507 | AI25: 43556 | AJ25: https://www.blackburn.gov.uk/planning/planning-policies-strategies-and-guides/local-plan-review | AK25: https://mhclg.sharepoint.com/:i:/s/DevelopmentPlans/EcFCRibQgYdAkXUZhugunmMBb931QXQ7c-Dl0SiQz2Plkw?e=lWQ2RK | AL25: 44075 | AM25: Draft Local Plan Consultation (Reg 18) | AN25: 44075 | AO25: 44204 | AP25: 44246 | AQ25: http://blackburn-darwen.org.uk/wp-content/uploads/UA-Consultation-Draft-Local-Plan-1.pdf | BG25: Jan - Feb 2022 | BH25: 44562 | BI25: 44596 | BJ25: June - July 2022 | BK25: 44713 | BL25: 44778 | BM25: Summer 2023 | BN25: 45108 | BO25: 45316 | BP25: PINS updates | BS25: 45950 | BT25: 44428 | BU25: 44645 | BV25: 44428 | BX25: no work on an emerging plan [adopted Jan-2024] | BZ25: Adopted Jan 2024
A26: E06000009 | C26: Blackpool | D26: New Local Plan to 2042 | E26: 2301 | F26: 2023 | G26: 2042 | H26: N | I26: N | J26: 42389 | W26: =IF(OR(X26="Yes", Y26="Web-page timetable", Z26="YES"), "Yes") -> Yes | X26: Yes | Y26: LDS Document | AA26: https://democracy.blackpool.gov.uk/documents/s98308/PH29%20Local%20Development%20Scheme.pdf | AB26: https://democracy.blackpool.gov.uk/documents/s98308/PH29%20Local%20Development%20Scheme.pdf | AD26: 45689 | AE26: 46388 | AF26: Reg 18 equivalent | AG26: 46388 | BG26: 47209 | BH26: 47209 | BJ26: 47515 | BK26: 47515 | BM26: 47880 | BN26: 47880 | BP26: Jan 2025 LDS | BQ26: Blackpool have now reviewed the Core Strategy policies: full review of Plan required. July 2022 LDS provides timetable: Reg 18: Sept/Oct 2023; Reg 19: Sept/Oct 2024; Submission: Dec 2024; Adoption: December 2025 | BS26: 45961 | BT26: 45763 | BU26: 45594 | BV26: 44855 | BW26: 45594 | BX26: new plan to be prepared under new system | BZ26: VisualPing
A27: E07000033 | C27: Bolsover | D27: Bolsover Local Plan | H27: N | I27: N | J27: 43894 | W27: =IF(OR(X27="Yes", Y27="Web-page timetable", Z27="YES"), "Yes") -> Yes | X27: Yes | Y27: LDS Document | AA27: https://www.bolsover.gov.uk/services/p/planning-policy/local-development-scheme | AB27: https://www.bolsover.gov.uk/component/edocman/15178-local-development-scheme-no-8/download?Itemid=0 | AD27: 45748 | AE27: 46661 | AF27: Reg 18 equivalent | AG27: 46661 | BG27: 47027 | BH27: 47027 | BJ27: 47150 | BK27: 47150 | BM27: 47453 | BN27: 47453 | BP27: April 2025 LDS | BS27: 45317 | BT27: 45961 | BU27: 45961 | BV27: 45686 | BW27: 31/010/2025 | BX27: new plan to be prepared under new system
A28: E08000001 | C28: Bolton | D28: Places for Everyone (PFE) | E28: 2175 | F28: 2022 | G28: 2039 | H28: N | I28: Y | J28: 45372 | K28: 40604 | P28: 44417 | Q28: 44606 | R28: 45336 | W28: =IF(OR(X28="Yes", Y28="Web-page timetable", Z28="YES"), "Yes") -> Yes | X28: Yes | Y28: Web-page timetable | AA28: https://www.greatermanchester-ca.gov.uk/what-we-do/planning-and-housing/places-for-everyone/timeline/ | AD28: 2023 | BI28: 44417 | BJ28: early 2022 | BK28: 44562 | BL28: 44606 | BO28: 45372 | BR28: Plan Submitted 14 February 2022. Hearings likely to commence October 2022. | BV28: 44440 | BW28: 45279 | BX28: Adopted March 2024 | BZ28: FS 14 Feb 2024
B29: E08000001-01 | C29: Bolton | D29: Bolton Local Plan (non strategic) | W29: =IF(OR(X29="Yes", Y29="Web-page timetable", Z29="YES"), "Yes") -> Yes | X29: Yes | Y29: Web-page timetable | AB29: https://www.bolton.gov.uk/downloads/file/7443/local-plan-direction-of-travel-consultation-document-pdf- | AD29: 45931 | AE29: Spring 2025 | AF29: Issues and Options | AG29: 45748 | AH29: 45890 | AI29: 45902 | AJ29: https://www.bolton.gov.uk/planning-policy-strategy/local-plan/2 | AL29: Autumn 2025 | AM29: Direction of Travel (2nd Reg 18) | AN29: 45931 | AO29: 45988 | AP29: 46044 | AQ29: https://www.bolton.gov.uk/downloads/file/7443/local-plan-direction-of-travel-consultation-document-pdf- | BG29: Summer 2026 | BH29: 46204 | BJ29: Winter 2026 | BK29: 46357 | BM29: 2027 | BN29: 2027 | BP29: Direction of Travel consultation document Oct 2025 | BS29: 46034 | BU29: 46034 | BW29: 46034 | BX29: Reg 18 ongoing
A30: E07000136 | C30: Boston | D30: South East Lincolnshire Local Plan Review | E30: n/a | J30: 43532 | U30: 45474 | V30: That based on the review that has taken place, the Joint Committee conclude that there is no requirement to update the Local Plan at this time | W30: =IF(OR(X30="Yes", Y30="Web-page timetable", Z30="YES"), "Yes") -> FALSE | X30: Yes, but TT refers to adopted Plan | Y30: LDS Document | AA30: http://www.southeastlincslocalplan.org/documents/ | AB30: http://www.southeastlincslocalplan.org/wp-content/uploads/2017/06/Local-Development-Scheme-June-2017.pdf | AD30: 42887 | BS30: 45933 | BX30: self-reviewed new plan to be submitted under new system
A31: E06000028 | C31: Bournemouth (defunct - now part of Bournemouth, Christchurch & Poole) | J31: 41212 | W31: =IF(OR(X31="Yes", Y31="Web-page timetable", Z31="YES"), "Yes") -> FALSE | BX31: DEFUNCT LPA [new unitary authority to prepare plan]
A32: E06000058 | C32: Bournemouth, Christchurch and Poole ("BCP") | D32: BCP Plan | J32: new lpa | Y32: LDS Document | AA32: https://www.bcpcouncil.gov.uk/planning-and-building-control/planning-policy/bcp-local-plan-and-community-infrastructure-levy-cil/local-development-scheme | AB32: https://www.bcpcouncil.gov.uk/Assets/Planning-and-building-control/Local-plan-and-cil/Local-Development-Scheme.pdf | AD32: 45778 | AE32: Aug - Oct 2026 | AF32: Reg 18 Equivalent [consultation on options] | AG32: 46235 | BG32: Sep - Nov 2027 | BH32: 46631 | BJ32: 46813 | BK32: 46813 | BM32: 47027 | BN32: 47027 | BP32: LPA e-mail (27 Aug 2025) | BS32: 45932 | BT32: 45834 | BU32: 45945 | BV32: 45834 | BX32: new plan to be prepared under new system
B33: E06000058-01 | C33: Bournemouth, Christchurch and Poole ("BCP") | D33: BCP Plan | E33: 2143 | F33: 2023 | G33: 2038 | H33: N | I33: N | J33: new LPA | L33: YES | M33: Nutrient neutrality (since 2018) | P33: 45371 | Q33: 45470 | S33: 45719 | T33: 45811 | W33: =IF(OR(X33="Yes", Y33="Web-page timetable", Z33="YES"), "Yes") -> Yes | X33: Yes | Y33: LDS Document | AA33: https://www.bcpcouncil.gov.uk/planning-and-building-control/planning-policy/bcp-local-plan/local-development-scheme | AB33: https://www.bcpcouncil.gov.uk/documents/planning-and-building-control/Local-Development-Scheme-Feb-2024.pdf | AD33: 45292 | AE33: Oct/Nov 2019 | AF33: Issues and Call for Sites Consultation | AG33: 43739 | AH33: 43745 | AI33: 43787 | AJ33: https://www.bcpcouncil.gov.uk/Council-and-Democratic/Consultation-And-Research/Consultations/BCP-Council-Local-Plan.aspx | AL33: Sep/Oct 2020 | AM33: Issues & Options | AN33: 44075 | AO33: 44571 | AP33: 44645 | AQ33: https://haveyoursay.bcpcouncil.gov.uk/localplan | BG33: 45352 | BH33: 45352 | BI33: 45371 | BJ33: 45444 | BK33: 45444 | BL33: 45470 | BM33: Summer 2025 | BN33: 45839 | BP33: LDS - Feb 2024 | BS33: 45420 | BT33: 45377 | BU33: 45441 | BV33: 45475 | BW33: 45763 | BX33: Submitted June 2024, failed DtC 2025; withdrawn 3 June 2025 | BZ33: VisualPing; Published June 2024
A34: E06000036 | C34: Bracknell Forest | D34: Bracknell Forest Local Plan | E34: TBA | H34: N | I34: N | J34: 45370 | K34: 39485 | L34: YES | M34: Covid-19 | W34: =IF(OR(X34="Yes", Y34="Web-page timetable", Z34="YES"), "Yes") -> Yes | X34: Yes | Y34: LDS Document | AA34: https://www.bracknell-forest.gov.uk/planning-and-building-control/planning/planning-policy/about-planning-policy | AB34: https://www.bracknell-forest.gov.uk/sites/default/files/2025-03/local-development-scheme-march-2025.pdf | AD34: 45717 | AE34: Winter/Spring 2028 | AF34: Visioning and strategy development - public consultation | AG34: 46844 | BG34: Spring 2029 | BH34: 47209 | BJ34: Autumn 2029 | BK34: 47392 | BM34: Spring 2030 | BN34: 47574 | BP34: March 2025 LDS | BT34: 45888 | BU34: 44309 | BV34: 45888 | BW34: 45888 | BX34: new plan to be prepared under new system | BZ34: Adopted 19 March 2024
A35: E08000032 | C35: Bradford | D35: Bradford District Local Plan | E35: 2208 | F35: 2020 | G35: 2038 | H35: N | I35: N | J35: 42934 | L35: YES | M35: LHN and White Paper | W35: =IF(OR(X35="Yes", Y35="Web-page timetable", Z35="YES"), "Yes") -> Yes | X35: Yes | Y35: LDS Document | AA35: https://www.bradford.gov.uk/planning-and-building-control/planning-policy/local-development-scheme/ | AB35: https://www.bradford.gov.uk/media/dmidr35l/local-development-scheme-2025-2028.pdf | AD35: 45931 | AE35: 43405 | AF35: Issues & Options (Core Strategy Partial Review) | AG35: 43405 | AH35: 43476 | AI35: 43518 | AJ35: https://www.bradford.gov.uk/planning-and-building-control/planning-policy/core-strategy-dpd/?Folder=Core+Strategy+Partial+Review | AK35: https://mhclg.sharepoint.com/sites/DevelopmentPlans/Shared%20Documents/Data%20and%20Analysis/Planning%20Data%20Unit/Reg%2018%20monitoring/Screenshots/Bradford%20Jan-Feb%202019%20FIRST.PNG | AL35: 43586 | AM35: Preferred Options (Core Strategy Partial Review) | AN35: 43586 | AO35: 43676 | AP35: 43732 | AQ35: https://www.bradford.gov.uk/planning-and-building-control/planning-policy/core-strategy-dpd/?Folder=Core%20Strategy%20Partial%20Review\Preferred+Options+Report | AS35: 44228 | AT35: Draft Bradford District Local Plan - both "Call for Sites" and "Preferred Options" (Regulation 18) | AU35: 44228 | AV35: 44235 | AW35: 44279 | AX35: https://www.bradford.gov.uk/planning-and-building-control/planning-policy/bradford-district-local-plan/ | BG35: 46204 | BH35: 46204 | BJ35: 46327 | BK35: 46327 | BM35: Summer 2028 | BN35: 46935 | BP35: LDS adopted Oct 2025 | BQ35: As of mid-2020, the Council is preparing a single Local Plan which includes work undertaken to date on the Core Strategy Partial Review and land allocations. | BS35: 45497 | BT35: 46024 | BU35: 45310 | BV35: 46024 | BW35: 46024 | BX35: Reg 18 completed | BZ35: Visual Ping
A36: E07000067 | C36: Braintree | D36: Braintree Local Plan (North Essex Garden Communities) Section 1 Review | E36: TBC | H36: Y | I36: N | J36: 44249 | W36: =IF(OR(X36="Yes", Y36="Web-page timetable", Z36="YES"), "Yes") -> Yes | X36: Yes | Y36: LDS Document | AA36: https://www.braintree.gov.uk/homepage/116/local-development-scheme-download | AB36: https://www.braintree.gov.uk/downloads/file/2023/local-development-scheme | AD36: 45962 | AE36: Jan/Feb 2025 | AF36: Issues and Options (Reg 18) | AG36: 46054 | AH36: 45677 | AI36: 45723 | AJ36: https://www.braintree.gov.uk/planning-building-control/braintree-district-development-plan/2 | AL36: 46054 | AM36: Preferred Options (Reg 18) | AN36: 46054 | BG36: 46235 | BH36: 46235 | BJ36: 46327 | BK36: 46327 | BM36: 46539 | BN36: 46539 | BP36: LDS Nov 2025 | BS36: 46031 | BT36: 46024 | BU36: 46031 | BV36: 46024 | BW36: 46024 | BX36: Reg 18 ongoing
A37: E07000143 | C37: Breckland | D37: Breckland Local Plan Full Update 2024-2041 | E37: 2317 | F37: 2024 | G37: 2041 | H37: N | I37: N | J37: 28 November 2019 (as amended by the partial update of 21 Sept 2023) | L37: YES | M37: Nutrient neutrality (March 2022) | W37: Yes | X37: Yes | Y37: LDS Document | AA37: https://www.breckland.gov.uk/local-plan-review | AB37: https://democracy.breckland.gov.uk/documents/g5348/Public%20reports%20pack%2003rd-Mar-2025%2011.00%20Cabinet.pdf?T=10 | AD37: 45717 | AE37: Jan - April 2023 | AF37: Issues and Options | AG37: 44927 | AH37: 44995 | AI37: 45065 | AJ37: https://www.breckland.gov.uk/article/19942/Local-Plan-Full-Update | AL37: Oct 2023 - Jan 2024 | AM37: emerging development strategy (Reg 18) | AN37: 45200 | AO37: 45299 | AP37: 45341 | AQ37: https://www.breckland.gov.uk/article/19942/Local-Plan-Full-Update | AS37: Spring 2024 | AT37: Draft Local Plan consultation | AU37: 45383 | AV37: 45446 | AW37: 45488 | AX37: https://www.breckland.gov.uk/article/19942/Local-Plan-Full-Update-2024 | AZ37: Oct - Dec 2025 | BA37: Revised Regulation 18 Consultation | BB37: 45931 | BC37: 45931 | BD37: 46006 | BE37: https://www.breckland.gov.uk/article/25391/Regulation-18-Local-Plan-Consultation-2025 | BG37: July - Sept 2026 | BH37: 46204 | BJ37: 46357 | BK37: 46357 | BM37: 2027 TBC | BN37: 2027 TBC | BP37: March 2025 LDS (as found in cabinet minutes of 3 March 2025) | BQ37: In September 2024, Breckland Council in Norfolk paused work on its local plan update despite the strategy going out of date in two months, citing a 47% rise in its annual housing requirement under proposed changes to the National Planning Policy Framework (NPPF). | BS37: 46034 | BT37: 45950 | BU37: 46034 | BV37: 45950 | BW37: 45950 | BX37: Reg 18 completed | BZ37: NEED A NEW VISUALPING ALERT once reg 18 starts
B38: E07000143-02 | C38: Breckland | D38: Breckland Local Plan - partial review non-strategic for our purposes | E38: 2184 | F38: 2011 | G38: 2036 | H38: N | I38: N | J38: 28 November 2019 (as amended by the partial update of 21 Sept 2023) | M38: Planning White Paper; Nutrient neutrality (March 2022) | O38: YES | P38: 44784 | Q38: 44894 | R38: 45167 | W38: =IF(OR(X38="Yes", Y38="Web-page timetable", Z38="YES"), "Yes") -> Yes | X38: Yes | Y38: LDS Document | AA38: https://www.breckland.gov.uk/local-plan-review | AB38: https://democracy.breckland.gov.uk/documents/g5348/Public%20reports%20pack%2003rd-Mar-2025%2011.00%20Cabinet.pdf?T=10 | AD38: 45717 | AE38: Q1 2022 - Q2 2022 | AF38: Issues and Options | AG38: 44593 | AH38: 44784 | AI38: 44827 | BG38: 44774 | BH38: 44774 | BI38: 11/08/2022 30/09/2022 | BJ38: 44866 | BK38: 44866 | BL38: 44866 | BM38: 45047 | BN38: 45047 | BO38: 45170 | BQ38: The Partial Review updates Policy INF03 of the Breckland Local Plan by removing the requirement for a more detailed review of four policies. They relate to housing provision, accommodation for gypsies and travellers, technical housing standards and the economic strategy. The Partial Review submitted for examination seeks to update Policy INF 03 by deleting this requirement, in favour of the production of a full Local Plan due to be submitted by the end of 2024. | BS38: 44628 | BT38: 45950 | BU38: 44463 | BV38: 44846 | BW38: 44846 | BX38: Adopted [partial update] | BZ38: Submitted Nov 2022
A39: E09000005 | C39: Brent | D39: Brent Local Plan | E39: TBA | H39: N | I39: N | J39: 44616 | K39: 40371 | W39: =IF(OR(X39="Yes", Y39="Web-page timetable", Z39="YES"), "Yes") -> Yes | X39: Yes | Y39: LDS Document | AA39: https://www.brent.gov.uk/localplan | AB39: https://www.brent.gov.uk/-/media/files/resident-documents/planning-and-bc-documents/local-development-scheme.pdf?rev=87535829340143c9af2ccdadddce3d1c&hash=0AE68BB76ED56E989EDA46E99B6A031A | AD39: 45748 | AE39: 46388 | AF39: First formal consultation | AG39: 46388 | BG39: 46753 | BH39: 46753 | BJ39: 46905 | BK39: 46905 | BM39: 47119 | BN39: 47119 | BP39: April 2025 LDS | BS39: 45142 | BT39: 45888 | BV39: 45888 | BW39: 45888 | BX39: new plan to be prepared under new system | BZ39: Adopted 24 Feb 2022
A40: E07000068 | C40: Brentwood | D40: Brentwood Local Plan | E40: TBA | H40: N | I40: N | J40: 44643 | K40: none [Mar 2022 adopted plan is first post-2004 Act Plan] | O40: YES | W40: =IF(OR(X40="Yes", Y40="Web-page timetable", Z40="YES"), "Yes") -> Yes | X40: Yes | Y40: LDS Document | AA40: https://www.brentwood.gov.uk/local-development-scheme-lds | AB40: https://www.brentwood.gov.uk/media/942 | AD40: 45689 | AE40: Q2 2026 | AF40: Preferred Options (equivalent) | AG40: 46143 | BG40: Q2 2027 | BH40: 46508 | BJ40: Q1 2028 | BK40: 46784 | BM40: Q1 2029 | BN40: 47150 | BP40: Feb 2025 LDS | BS40: 45961 | BT40: 45902 | BV40: 45902 | BW40: 45902 | BX40: new plan to be prepared under new system | CD40: Yes
A41: E06000043 | C41: Brighton & Hove | D41: City Plan Part 1 Review | E41: Reg 18 yet to start | H41: N | I41: N | J41: 42453 | W41: =IF(OR(X41="Yes", Y41="Web-page timetable", Z41="YES"), "Yes") -> Yes | X41: Yes | Y41: LDS Document | AA41: https://www.brighton-hove.gov.uk/planning/planning-policy/local-development-scheme-2023-2026 | AB41: https://www.brighton-hove.gov.uk/planning/planning-policy/local-development-scheme-2025-2028 | AD41: 45717 | AE41: Spring 2024 | AF41: Scoping consultation [now "key issues"] | AG41: 45383 | AI41: 45677 | AJ41: https://www.brighton-hove.gov.uk/planning/city-plan-2041 | AL41: July - Sep 2026 | AM41: Reg 18? | AN41: 46204 | BG41: Autumn 2027 | BH41: 46661 | BJ41: Early 2028 | BK41: 46753 | BM41: Late 2028 | BN41: 47088 | BP41: LPA website updated with "key issues" consultation ending 20 Jan 2025 | BQ41: The timetable for the latter stages of the Review is subject to some uncertainty and is likely to be impacted by the forthcoming changes to the planning system. The government’s proposed timetable for introducing the changes currently indicates that the first examinations to be held under the new system will not take place until October 2026. The Local Development Scheme will be updated should the timetable change. | BS41: 45902 | BT41: 45716 | BU41: 45902 | BV41: 45716 | BW41: 45716 | BX41: new plan to be prepared under new system | BZ41: Visualping
A42: E06000023 | C42: Bristol | D42: New Bristol Local Plan | E42: 2007 | F42: 2022 | G42: 2040 | H42: N | I42: N | J42: 40715 | L42: YES | N42: PAS | P42: 45251 | Q42: 45407 | W42: =IF(OR(X42="Yes", Y42="Web-page timetable", Z42="YES"), "Yes") -> Yes | X42: Yes | Y42: LDS Document | AA42: https://www.bristol.gov.uk/residents/planning-and-building-regulations/planning-policy-and-guidance/local-plan/local-plan-review | AB42: https://www.bristol.gov.uk/files/documents/5265-local-development-scheme | AD42: 45108 | AE42: March - May 2019 | AF42: Local Plan review Consultation | AG42: 43556 | AH42: 43542 | AI42: 43609 | AJ42: https://www.bristol.gov.uk/documents/20182/34536/Bristol+Local+Plan+Review+consultation+March+2019+-+Summary+of+responses+Web.pdf/333c1eef-9387-5b1e-6890-f0577cc24468 | AL42: 44866 | AM42: Further consultation on policies and proposals | AN42: 44866 | AO42: 44893 | AP42: 44946 | AQ42: https://www.bristol.gov.uk/files/documents/5446-bristol-local-plan-review-nov-22-further-consultation/file | BG42: 45231 | BH42: 45231 | BI42: 45251 | BJ42: Spring 2024 | BK42: 45352 | BL42: 45407 | BM42: Spring 2025 | BN42: 45748 | BP42: PINS tracker | BS42: 45950 | BT42: 45154 | BU42: 45273 | BV42: 45413 | BW42: 46027 | BX42: Submitted April 2024 | BZ42: VisualPing Published Nov 2023
B43: E06000023-02 | C43: Bristol | D43: WECA Spatial Development Strategy (SDS) | F43: 2022 | G43: 2042 | H43: N | I43: SDS | J43: 40715 | L43: YES | M43: lack of agreement | W43: =IF(OR(X43="Yes", Y43="Web-page timetable", Z43="YES"), "Yes") -> Yes | X43: Yes | Y43: LDS Document | AA43: https://www.westofengland-ca.gov.uk/what-we-do/planning-housing/spatial-development-strategy/ | AB43: https://beta.bathnes.gov.uk/sites/default/files/2021-08/LDS%20July%202021%20Final%20-%20accessible.pdf | AD43: 2021 | AE43: Second Half of 2021 | AF43: Draft SDS Public consultation | AG43: 44378 | BG43: Spring 2022 | BH43: 44652 | BJ43: Spring 2023 | BK43: 45017 | BM43: TBC | BN43: TBC | BR43: Work has stopped on the SDS and is not being progressed by WECA. | BS43: 44628 | BU43: 44628 | BW43: 44740 | BX43: work stopped | BZ43: VisualPing
A44: E07000144 | C44: Broadland | D44: Greater Norwich Local Plan Review | E44: TBA | H44: N | I44: Y | J44: 45379 | K44: 41649 | L44: YES | M44: Nutrient neutrality (March 2022) | W44: =IF(OR(X44="Yes", Y44="Web-page timetable", Z44="YES"), "Yes") -> Yes | X44: Yes | Y44: LDS Document | AA44: https://www.south-norfolk.gov.uk/residents/planning-and-building/planning-policy/local-development-scheme | AB44: https://www.norwich.gov.uk/download/downloads/id/1671/local_development_scheme_lds_-_march_2025.pdf | AC44: 45717 | AD44: 45717 | AE44: Sept - Oct 2026 | AF44: Gateway 1 consultation | AG44: 46266 | BF44: 46813 | BG44: July - Aug 2027 | BH44: 46569 | BJ44: 46935 | BK44: 46935 | BM44: 47178 | BN44: 47178 | BP44: March 2025 LDS | BR44: 45779 | BS44: 44547 | BT44: 45804 | BU44: 44362 | BV44: 45804 | BW44: 45804 | BX44: new plan to be prepared under new system | BZ44: FS Feb 2024
A45: E26000007 | C45: Broads | D45: Broads Local Plan Review | E45: 2419 | F45: 2021 | G45: 2042 | H45: N | I45: N | J45: 43602 | L45: YES | P45: 45989 | W45: =IF(OR(X45="Yes", Y45="Web-page timetable", Z45="YES"), "Yes") -> Yes | X45: Yes | Y45: LDS Document | AA45: https://www.broads-authority.gov.uk/planning/planning-policies/local-plan-for-the-broads/local-plan-for-the-broads-review | AB45: https://www.broads-authority.gov.uk/__data/assets/pdf_file/0020/131852/Broads-Local-Plan-LDS-Dec-2025.pdf | AD45: 45992 | AE45: 44682 | AF45: Issues and Options | AG45: 44682 | AH45: 44837 | AI45: 44904 | AJ45: https://www.broads-authority.gov.uk/about-us/how-we-work/transparency/consultations/the-local-plan-for-the-broads-issues-and-options-consultation | AL45: 45413 | AM45: Preferred Options | AN45: 45413 | AP45: 45429 | AQ45: https://www.broads-authority.gov.uk/__data/assets/pdf_file/0032/513599/Preferred-Options-February-2024.pdf | BG45: 1. Jul-2025 2. Nov-2025 | BH45: 1. Jul-2025 2. Nov-2025 | BI45: 1. Jul-2025 2. Nov-2025 | BJ45: Feb / Mar 2026 | BK45: 46054 | BM45: TBC | BN45: TBC | BP45: Dec 2025 LDS | BS45: 45961 | BT45: 46031 | BU45: 45140 | BV45: 46031 | BW45: 46031 | BX45: Published (2nd)
A46: E09000006 | C46: Bromley | D46: Review of the Bromley Local Plan | E46: 2303 | F46: 2023 | G46: 2038 | H46: N | I46: N | J46: 43481 | W46: =IF(OR(X46="Yes", Y46="Web-page timetable", Z46="YES"), "Yes") -> Yes | X46: Yes | Y46: LDS Document | AA46: https://www.bromley.gov.uk/planning-policy/local-development-scheme | AB46: https://www.bromley.gov.uk/downloads/file/60/local-development-scheme-2025 | AD46: 45658 | AE46: Late 2021 to early 2022 | AF46: Isses and Options | AG46: 44562 | AH46: 45017 | AI46: 45078 | AJ46: https://www.bromley.gov.uk/downloads/download/484/bromley-local-plan-review-issues-and-options | AL46: Q2 2025 | AM46: Reg 18 consultation Direction of Travel Document | AN46: 45778 | AO46: 45863 | AP46: 45926 | AQ46: https://www.bromley.gov.uk/planning-policy/review-bromley-local-plan/2 | BG46: Summer 2026 | BH46: 46204 | BJ46: 46357 | BK46: 46357 | BM46: Q3 - Q4 2027 | BN46: 46600 | BP46: Jan 2025 LDS & PINS intel (Jan 2025) & LPA website (post-Reg-18 consultation, Oct 2025) | BQ46: The Council is currently reviewing the Bromley Local Plan. This review will be progressed under the current plan-making system (rather than the new-style plan_x0002_making system, of which there are no firm details at the time of writing1). The deadline for submission of plans under the current system is December 2026 | BS46: 46024 | BT46: 45681 | BU46: 45257 | BV46: 45960 | BW46: 45960 | BX46: Reg 18 completed
A47: E07000234 | C47: Bromsgrove | D47: Local Plan Review | E47: 2107 [to check] | H47: N | I47: N | J47: 42760 | L47: YES | M47: White Paper Other | W47: =IF(OR(X47="Yes", Y47="Web-page timetable", Z47="YES"), "Yes") -> Yes | X47: Yes | Y47: LDS Document | AA47: https://www.bromsgrove.gov.uk/council/policy/planning-policies-and-other-planning-information/local-development-scheme-lds/ | AB47: https://www.bromsgrove.gov.uk/media/pwonbj5u/bdc-lds-2025-version-final.pdf | AD47: 45689 | AE47: June / July 2026 | AF47: First mandatory consultation | AG47: 46174 | BG47: 46478 | BH47: 46478 | BJ47: 46722 | BK47: 46722 | BM47: 46935 | BN47: 46935 | BP47: Feb 2025 LDS & LPA website | BQ47: 20/02/24 LPA advised R19 expected April 25 with submission July 2025; they stated that whilst not officially confirmed by elected members both Bromsgrove and Redditch will be submitting under the new system | BS47: 45961 | BT47: 45764 | BU47: 45562 | BV47: 45888 | BW47: 45937 | BX47: new plan to be prepared under new system | BZ47: VisualPing
A48: E07000095 | C48: Broxbourne | D48: Broxbourne Local Plan | E48: TBA | H48: N | I48: N | J48: 44006 | AA48: https://www.broxbourne.gov.uk/planning/local-plan-2018-2033/1 | AB48: https://www.broxbourne.gov.uk/downloads/file/4632/broxbourne-local-development-scheme-february-2025 | AD48: 45931 | AE48: 46143 | AF48: "Issues and Options" | AG48: 46143 | AL48: 46508 | AM48: "Draft Local Plan" consultation | AN48: 46508 | BG48: 46753 | BH48: 46753 | BJ48: 46874 | BK48: 46874 | BM48: TBC | BN48: TBC | BP48: October 2025 LDS | BT48: 45950 | BV48: 45950 | BW48: 45950 | BX48: new plan to be prepared under new system
A49: E07000172 | C49: Broxtowe | D49: Greater Nottingham Strategic Plan 2041 | E49: 2394 | F49: 2023 | G49: 2041 | H49: N | I49: Y | J49: 41899 | P49: 1st. 4 Nov 2024 2nd. 12 Mar 2025 | Q49: 46013 | W49: =IF(OR(X49="Yes", Y49="Web-page timetable", Z49="YES"), "Yes") -> Yes | X49: Yes | Y49: LDS Document | Z49: YES | AA49: https://www.broxtowe.gov.uk/for-you/planning/planning-policy/local-development-scheme/ | AB49: https://www.broxtowe.gov.uk/media/k0jdkda1/local-development-scheme-dec-2025.pdf | AD49: 45992 | AE49: 6 July 2020 - 14 Sep 2020 | AF49: Growth Options | AG49: 44013 | AH49: 44018 | AI49: 44279 | AJ49: https://gnplan.inconsult.uk/consult.ti/gnspgo/consultationHome | AL49: Autumn 2022 | AM49: Preferred Approach | AN49: 44835 | AO49: 44929 | AP49: 44971 | AQ49: https://www.gnplan.org.uk/consultations/greater-nottingham-strategic-plan-preferred-approach/ | AR49: https://www.gnplan.org.uk/latest-news/ | AS49: 45170 | AT49: Preferred Approach number 2 | AU49: 45170 | AV49: 45170 | AW49: 45237 | BG49: 1. Autumn 2024 2. March 2025 | BH49: 1. Oct 2024 2. March 2025 | BI49: 1. Nov 2024 2. March 2025 | BJ49: 45901 | BK49: 45901 | BL49: 45992 | BM49: 46357 | BN49: 46357 | BP49: Feb 2025 LDS & GNPP website | BR49: Reg 19 exp. June 2024 | BS49: 45961 | BT49: 46024 | BU49: 45602 | BV49: 46024 | BW49: 45786 | BX49: Submitted | BZ49: VisualPing
A50: E06000060 | C50: Buckinghamshire | D50: Local Plan for Buckinghamshire | E50: 2452 | G50: 2045 | H50: N | I50: N | J50: new LPA | W50: =IF(OR(X50="Yes", Y50="Web-page timetable", Z50="YES"), "Yes") -> Yes | X50: Yes | Y50: Web-page timetable | AA50: https://www.buckinghamshire.gov.uk/planning-and-building-control/local-development-plans/local-development-scheme/plans-we-will-work-on/ | AB50: https://www.buckinghamshire.gov.uk/planning-and-building-control/local-development-plans-info/local-development-scheme/plans-we-will-work-on/ | AD50: 45748 | AE50: Sept/Oct 2025 | AF50: Reg 18 consultation on draft plan | AG50: 45901 | AH50: 45917 | AI50: 45959 | AJ50: https://www.buckinghamshire.gov.uk/planning-and-building-control/planning-policy/local-planning/buckinghamshire-local-plan/ | BG50: July/August 2026 | BH50: 46204 | BJ50: 46357 | BK50: 46357 | BM50: 46722 | BN50: 46722 | BP50: LPA web-based timetable (April 2025) & Inspector's AV (Nov 2025) | BS50: 46024 | BT50: 45757 | BU50: 46024 | BV50: 45960 | BW50: 46031 | BX50: Reg 18 completed
A51: E07000117 | C51: Burnley | D51: Burnley Local Plan | E51: TBC | J51: 43312 | U51: 45119 | V51: Not to commence an update of Burnley's Local Plan 2012-2032 at the present time. | W51: =IF(OR(X51="Yes", Y51="Web-page timetable", Z51="YES"), "Yes") -> FALSE | X51: No | Y51: LDS Document | AA51: https://www.burnley.gov.uk/residents/planning/planning-policies/burnleys-local-development-scheme-lds | AB51: https://burnley.gov.uk/wp-content/uploads/2025/03/LDS-2025-2028-6-March-2025-Final.pdf | AD51: 45717 | AE51: 46905 | AF51: First consultation | AG51: 46905 | BP51: March 2025 LDS | BS51: 45455 | BT51: 45856 | BU51: 45856 | BW51: 45856 | BX51: new plan to be prepared under new system | BZ51: adopted July 2018 self-reviewed july 2023
B52: E08000002-01 | C52: Bury | D52: Bury Local Plan (non-strategic) | W52: =IF(OR(X52="Yes", Y52="Web-page timetable", Z52="YES"), "Yes") -> Yes | X52: Yes | Y52: LDS Document | AA52: https://www.bury.gov.uk/planning-building-control/policy-and-projects/planning-policy/local-development-scheme | AB52: https://www.bury.gov.uk/asset-library/lds-update-january-20261.pdf | AD52: 46023 | AE52: 45352 | AF52: Regulation 18 Notification /Call for Sites/consultation on Integrated Appraisal scoping | AG52: March 20247 | AH52: 45352 | AL52: 45717 | AM52: Consultation on draft plan | AN52: 45717 | AO52: 45733 | AP52: 45789 | AQ52: https://www.bury.gov.uk/asset-library/draft-local-plan-v7-cabinet.pdf | BG52: March 2026 (with representations invited from May 2026) | BH52: 46082 | BJ52: 46296 | BK52: 46296 | BM52: 46661 | BN52: 46661 | BP52: Jan 2026 LDS | BS52: 46034 | BU52: 46034 | BW52: 46034 | BX52: Reg 18 completed
A53: E08000002 | C53: Bury | D53: Places for Everyone (PFE) | E53: 2175 | F53: 2022 | G53: 2039 | H53: N | I53: Y | J53: 45372 | K53: none | P53: 44417 | Q53: 44606 | R53: 45336 | W53: =IF(OR(X53="Yes", Y53="Web-page timetable", Z53="YES"), "Yes") -> Yes | X53: Yes | Y53: Web-page timetable | AA53: https://www.greatermanchester-ca.gov.uk/what-we-do/planning-and-housing/places-for-everyone/timeline/ | AD53: 2023 | BI53: 44417 | BJ53: early 2022 | BK53: 44562 | BL53: 44606 | BO53: 45372 | BR53: Plan Submitted 14 February 2022. Hearings likely to commence October 2022. | BV53: 44440 | BW53: 45279 | BX53: Adopted March 2024 | BZ53: FS 14 Feb 2024
A54: E08000033 | C54: Calderdale | D54: Calderdale Local Plan | H54: N | I54: N | J54: 45007 | K54: none [Mar 2023 adopted plan is first post-2004 Act Plan] | W54: =IF(OR(X54="Yes", Y54="Web-page timetable", Z54="YES"), "Yes") -> FALSE | X54: Yes, but refers to something else | Y54: LDS Document | AA54: https://new.calderdale.gov.uk/planning-and-building-control/planning-policy/local-plan | AB54: https://calderdale-consult.objective.co.uk/kse/event/37823 | AD54: 45231 | AE54: 46113 | AF54: First consultation | AG54: 46113 | AL54: 46388 | AM54: Further consultation | AN54: 46388 | BG54: 46569 | BH54: 46569 | BJ54: 46753 | BK54: 46753 | BM54: 47027 | BN54: 47027 | BP54: LDS exercise March 2025 | BS54: 45950 | BV54: 45908 | BW54: 45908 | BX54: new plan to be prepared under new system | BZ54: Adopted Mar 2023
A55: E07000008 | C55: Cambridge | D55: Greater Cambridge Local Plan | E55: 2139 | F55: 2024 | G55: 2045 | H55: N | I55: Y | J55: 43391 | O55: YES | W55: =IF(OR(X55="Yes", Y55="Web-page timetable", Z55="YES"), "Yes") -> Yes | X55: Yes | Y55: LDS Document | AA55: https://www.greatercambridgeplanning.org/local-and-neighbourhood-planning/emerging-plans-and-guidance/local-development-scheme | AB55: https://www.greatercambridgeplanning.org/media/4xzkjei0/greater-cambridge-local-plan-development-scheme-local-plan-timetable-nov-2025.pdf | AD55: 45962 | AE55: 43831 | AF55: Issues and Options | AG55: 43831 | AH55: 43843 | AI55: 43885 | AJ55: https://www.scambs.gov.uk/planning/local-plan-and-neighbourhood-planning/emerging-local-plans-and-guidance/emerging-greater-cambridge-local-plan/call-for-sites/ | AL55: Summer/Autumn 2021 | AM55: Preferred Options | AN55: 44378 | AO55: 44470 | AP55: 44470 | AS55: Winter 2025/2026 | AT55: Draft Plan (Reg 18) | AU55: 45962 | AV55: 45992 | AW55: 46052 | AX55: https://consultations.greatercambridgeplanning.org/draft-greater-cambridge-local-plan-consultation/document-library | BG55: Summer/Autumn 2026 | BH55: 46235 | BJ55: 46357 | BK55: 46357 | BM55: 46905 | BN55: 46905 | BP55: Nov 2025 LDS & Joint Plan website (Dec 2025) | BQ55: Submission confirmed by PINS late 2026 | BR55: First Joint Plan between Cambridge City Council and South Cambs DC. Third Reg 18 (Draft Plan): Autumn 2023; Reg 19: Autumn 2024; Submission: Summer/Autumn 2025; Adoption: TBC. | BS55: 45960 | BT55: 46024 | BU55: 45686 | BV55: 45996 | BW55: 45996 | BX55: Reg 18 ongoing | BZ55: VisualPing
A56: E09000007 | C56: Camden | D56: Local Plan Review | E56: 2436 | F56: 2023 | G56: 2038 | H56: N | I56: N | J56: 42919 | P56: 45778 | W56: =IF(OR(X56="Yes", Y56="Web-page timetable", Z56="YES"), "Yes") -> Yes | X56: Yes | Y56: LDS Document | AA56: https://www.camden.gov.uk/planning-guidance?inheritRedirect=true#aqbw | AB56: https://www.camden.gov.uk/documents/d/guest/local-development-scheme-september-2025 | AD56: 45901 | AE56: Winter 2022/2023 | AF56: First consultation | AG56: 44927 | AH56: _ | AI56: - | AJ56: - | AL56: Winter 2023/Spring 2024 | AM56: Draft Plan (Reg 18) | AN56: 45383 | AO56: 45308 | AP56: 45364 | BG56: Spring - early Summer 2025 | BH56: 45717 | BI56: 45778 | BJ56: Autumn 2025 | BK56: 45931 | BM56: Winter 2026 | BN56: 46388 | BP56: Sep 2025 LDS (no change to timetable) | BS56: 45695 | BT56: 45959 | BU56: 45959 | BV56: 45632 | BW56: 45959 | BX56: Published | BZ56: VisualPing
A57: E07000192 | C57: Cannock Chase | D57: Cannock Chase Local Plan | E57: 2047 | F57: 2018 | G57: 2040 | H57: N | I57: N | J57: 41801 | L57: YES | M57: White Paper and Covid-19 | P57: 45327 | Q57: 45625 | W57: =IF(OR(X57="Yes", Y57="Web-page timetable", Z57="YES"), "Yes") -> Yes | X57: Yes | Y57: LDS Document | AA57: https://www.cannockchasedc.gov.uk/residents/planning-and-building-control/planning-policy/local-development-scheme | AB57: https://www.cannockchasedc.gov.uk/sites/default/files/document-library/Local%20Development%20Scheme%202024.pdf | AD57: 45536 | AE57: June-July 2018 | AF57: Issues & Scope | AG57: 43497 | AH57: 43252 | AI57: 43282 | AJ57: https://www.cannockchasedc.gov.uk/residents/planning/planning-policy/cannock-chase-local-plan | AL57: May-July 2019 | AM57: Issues & Options | AN57: 43586 | AO57: 43598 | AP57: 43654 | AQ57: https://www.cannockchasedc.gov.uk/residents/planning/planning-policy/cannock-chase-local-plan | AS57: July-Aug 2020 | AT57: Preferred Options | AU57: 44013 | AV57: 44274 | AW57: 44316 | AX57: https://www.cannockchasedc.gov.uk/residents/planning/planning-policy/planning-policy-news-consultations | BG57: Winter 2023/24 | BH57: 45292 | BI57: 45327 | BJ57: Summer 2024 | BK57: 45505 | BL57: 45625 | BM57: 46054 | BN57: 46054 | BP57: Sep 2024 LDS | BS57: 45951 | BT57: 45607 | BU57: 45174 | BV57: 45607 | BW57: 45995 | BX57: Submitted Nov 2024 | BZ57: VisualPing
A58: E07000106 | C58: Canterbury | D58: New Canterbury District Local Plan (2024-2043) | E58: 2109 | F58: 2024 | G58: 2043 | H58: N | I58: N | J58: 42929 | L58: YES | M58: Nutrient neutrality (since 2018) | W58: =IF(OR(X58="Yes", Y58="Web-page timetable", Z58="YES"), "Yes") -> Yes | X58: Yes | Y58: Web-page timetable | AA58: https://haveyoursay.canterbury.gov.uk/draft-canterbury-district-local-plan-focused-consultation-2025?_gl=1*1oz7w7d*_ga*NjYxNzQ1NTgwLjE3NjEwNTk5MDU.*_ga_6MTT8J065V*czE3NjEwNTk5MDQkbzEkZzEkdDE3NjEwNTk5MjQkajQwJGwwJGgw | AB58: https://ehq-production-europe.s3.eu-west-1.amazonaws.com/f1fecf933f6cd7a4b7987ec0b3c7865fc629b554/original/1756910239/163843c5032b77d845b4f7330e4cc1dc_Local%20Development%20Scheme.pdf?X-Amz-Algorithm=AWS4-HMAC-SHA256&X-Amz-Credential=AKIA4KKNQAKIJHZMYNPA%2F20251021%2Feu-west-1%2Fs3%2Faws4_request&X-Amz-Date=20251021T151952Z&X-Amz-Expires=300&X-Amz-SignedHeaders=host&X-Amz-Signature=4c26db027efc0c95347df7a45411db49764f5a235cebedf242148a011ae509c1 | AD58: 45809 | AE58: Oct 2019 - August 2021 | AF58: Issues & Options (more than one consultation in this period) | AG58: 43739 | AH58: 44013 | AI58: 44104 | AJ58: https://districtplan.canterbury.gov.uk/ | AL58: Sep 2021 - Jan 2023 | AM58: Draft Local Plan | AN58: 44440 | AO58: 44440 | AP58: 44927 | AQ58: https://forms.canterbury.gov.uk/xfp/form/801 | AS58: 45362 | AT58: Revised Draft Local Plan Consultation | AU58: 45446 | AV58: 45362 | AW58: 45446 | AX58: https://www.canterbury.gov.uk/planning-and-building/new-local-plan-2045/local-plan-consultations | BG58: early 2026 | BH58: 46054 | BJ58: Summer 2026 | BK58: 46204 | BM58: 46722 | BN58: 46722 | BP58: June 2025 LDS & AV Note 10/12/2025 & LPA website | BS58: 46024 | BT58: 45951 | BU58: 45686 | BV58: 46024 | BW58: 46010 | BX58: Reg 18 completed | BZ58: VisualPing
A59: E07000028 | C59: Carlisle (unitarised in 2023, now Cumberland) | D59: Carlisle District Local Plan 2015-2030 Review | F59: 2015 | G59: 2030 | H59: N | I59: N | J59: 42682 | L59: YES | M59: Nutrient neutrality (March 2022) | W59: =IF(OR(X59="Yes", Y59="Web-page timetable", Z59="YES"), "Yes") -> Yes | X59: Yes | Y59: LDS Document | AA59: https://www.carlisle.gov.uk/planning-policy/Plans-In-Preparation/Local-Development-Scheme-LDS | AB59: https://www.carlisle.gov.uk/Portals/24/Documents/Local_Plan/Local%20Development%20Scheme/LDS%20Update%202019-2022.pdf?timestamp=1580736105312 | AC59: https://mhclg.sharepoint.com/sites/DevelopmentPlans/Shared%20Documents/Data%20and%20Analysis/Planning%20Data%20Unit/LDS%20&%20Reg%2018%20Monitoring/LDS%20Screenshots/CAR16%20-%20Carlisle%20LDS%202016.PNG | AD59: 43617 | BS59: 45126 | BX59: DEFUNCT LPA [new unitary authority to prepare plan] | BZ59: Visualping
B60: E07000069-02 | C60: Castle Point | D60: New Castle Point Local Plan 2018 - 2033 (WITHDRAWN 15 JUNE 2022) | E60: 2233 | F60: 2018 | G60: 2033 | H60: N | I60: N | J60: none | P60: 43815 | Q60: 44106 | R60: 44623 | T60: 44727 | W60: =IF(OR(X60="Yes", Y60="Web-page timetable", Z60="YES"), "Yes") -> Yes | X60: Yes | Y60: LDS Document | AA60: https://www.castlepoint.gov.uk/local-development-scheme | AB60: https://www.castlepoint.gov.uk/download.cfm?doc=docm93jijm4n5468.pdf&ver=8949 | AD60: 44136 | AE60: 43282 | AF60: Issues Consultation - Sustainability Appraisal scoping report | AG60: 43282 | AH60: 43285 | AI60: 43327 | AJ60: https://www.castlepoint.gov.uk/2018-local-plan-consultation/ | AK60: https://mhclg.sharepoint.com/sites/DevelopmentPlans/Shared%20Documents/Data%20and%20Analysis/Planning%20Data%20Unit/Reg%2018%20monitoring/Screenshots/Castle%20Point%20July%202018%20FIRST%20ltr.PNG | BG60: 43800 | BH60: 43800 | BI60: 43815 | BJ60: 43983 | BK60: 43983 | BL60: 44106 | BM60: Autumn 2021 | BN60: 44440 | BS60: 44658 | BW60: 44740 | BX60: withdrawn | BZ60: WITHDRAWN 15 June 2022
A61: E07000069 | C61: Castle Point | D61: Castle Point Plan | E61: 2411 | F61: 2026 | G61: 2043 | H61: N | I61: N | J61: none | L61: YES | M61: Previous emerging plan withdrawn 15 June 2022 | P61: 45870 | W61: =IF(OR(X61="Yes", Y61="Web-page timetable", Z61="YES"), "Yes") -> Yes | X61: Yes | Y61: LDS Document | AA61: https://www.castlepoint.gov.uk/castle-point-plan | AB61: https://www.castlepoint.gov.uk/download/local-development-scheme-july-2025pdf.pdf?ver=14924&doc=docm93jijm4n8873.pdf | AD61: 45839 | AE61: June 2024 - Feb 2025 | AF61: Developing the Plan (Options engagement) | AG61: 45444 | AH61: summer 2024 | AI61: summer 2024 | BG61: April - May 2025 Oct-2025 | BH61: Apr-2025 Oct-2025 | BI61: Aug-2025 Oct-2025 | BJ61: 45962 | BK61: 45962 | BM61: 46266 | BN61: 46266 | BP61: July 2025 LDS/PDT intel/LPA webiste Oct 2025) | BS61: 45317 | BT61: 45954 | BU61: 45093 | BV61: 45954 | BW61: 45954 | BX61: Published [re-published] | BZ61: VisualPing
A62: E06000056 | C62: Central Bedfordshire | D62: Central Bedfordshire Local Plan Full Review | E62: Reg 18 yet to start | H62: N | I62: N | J62: 44399 | L62: YES | M62: NPPF (March 2023) | O62: YES | W62: =IF(OR(X62="Yes", Y62="Web-page timetable", Z62="YES"), "Yes") -> Yes | X62: Yes | Y62: LDS Document | AA62: https://www.centralbedfordshire.gov.uk/info/45/planning_policy/1168/local_development_scheme_lds | AB62: https://centralbedfordshirecouncil.sharepoint.com/sites/Communications/Website%20and%20intranet/Forms/AllItems.aspx?id=%2Fsites%2FCommunications%2FWebsite%20and%20intranet%2FWebsite%20Documents%2FPlanning%2FPlanning%20Policy%2FLocal%20development%20scheme%2FLocal%20Development%20Scheme%20%28LDS%29%2Epdf&parent=%2Fsites%2FCommunications%2FWebsite%20and%20intranet%2FWebsite%20Documents%2FPlanning%2FPlanning%20Policy%2FLocal%20development%20scheme&p=true&ga=1 | AD62: 45658 | AE62: Feb - April 2026 | AF62: Draft Plan Consultation (Reg 18) | AG62: 46113 | BG62: Sep - Oct 2027 | BH62: 46631 | BJ62: 46784 | BK62: 46784 | BM62: 47088 | BN62: 47088 | BP62: Jan 2025 LDS | BQ62: Central Bedfordshire are progressing a Full Local Plan Review under the new legislation. | BS62: 45960 | BT62: 45700 | BU62: 45427 | BV62: 45700 | BW62: 45700 | BX62: new plan to be prepared under new system
A63: E07000130 | C63: Charnwood | D63: Charnwood Local Plan 2021 - 2037 | E63: 1951 | F63: 2021 | G63: 2037 | H63: N | I63: N | J63: 42317 | L63: YES | M63: Covid-19 | P63: 44389 | Q63: 44533 | W63: =IF(OR(X63="Yes", Y63="Web-page timetable", Z63="YES"), "Yes") -> Yes | X63: Yes | Y63: LDS Document | AA63: https://www.charnwood.gov.uk/pages/localdevelopmentscheme | AB63: https://www.charnwood.gov.uk/files/documents/local_development_scheme_december_2024/Local%20Development%20Scheme%20Dec%202024.pdf | AD63: 45627 | AE63: 42552 | AF63: Scope of Local Plan | AG63: 42552 | AH63: 42563 | AI63: 42605 | AJ63: https://www.charnwood.gov.uk/pages/previous_local_plan_consultations | AL63: 43191 | AM63: Issues & Options - "Towards a Local Plan for Charnwood" | AN63: 43191 | AO63: 43216 | AP63: 43258 | AQ63: https://www.charnwood.gov.uk/pages/local_plan_review | AR63: https://mhclg.sharepoint.com/sites/DevelopmentPlans/Shared%20Documents/Data%20and%20Analysis/Planning%20Data%20Unit/Reg%2018%20monitoring/Screenshots/Charnwood%20April%202018%20Reg%2018%20First.PNG | AS63: July 2019 | AT63: Preferred Options (Draft Plan) | AU63: 43647 | AV63: 43773 | AW63: 43815 | AX63: https://www.charnwood.gov.uk/pages/draft_charnwood_local_plan_2019_36 | BG63: 44378 | BH63: 44378 | BI63: 44389 | BJ63: 44470 | BK63: 44470 | BL63: 44533 | BM63: 45901 | BN63: 45901 | BP63: Dec 2024 LDS & FC report Dec 2025 | BS63: 45959 | BT63: 45680 | BU63: 45959 | BV63: 45680 | BW63: 46010 | BX63: Submitted December 2021 Fact Check Report Issued Dec 2025 | BZ63: VisualPing; Submitted Dec 2021
A64: E07000070 | C64: Chelmsford | D64: Chelmsford Local Plan | E64: 2295 | F64: 2022 | G64: 2041 | H64: N | I64: N | J64: 43978 | W64: =IF(OR(X64="Yes", Y64="Web-page timetable", Z64="YES"), "Yes") -> Yes | X64: Yes | Y64: LDS Document | AA64: https://www.chelmsford.gov.uk/planning-and-building-control/planning-policy-and-local-plan/local-plan-review-2022/ | AB64: https://www.chelmsford.gov.uk/media/ehzd1alh/chelmsford-local-development-scheme-2025-2028.pdf | AD64: 45931 | AE64: 44774 | AF64: Issues and Options | AG64: 44774 | AH64: 44784 | AI64: 44854 | AJ64: https://www.chelmsford.gov.uk/media/chehlnlq/issues-and-options-consultation-document.pdf | AL64: 45413 | AM64: Preferred Options - consultation on Draft Local Plan | AN64: 45413 | AO64: 45420 | AP64: 45462 | AQ64: https://www.chelmsford.gov.uk/media/jxuccf4z/preferred-options-local-plan-consultation-document.pdf | BG64: Q1 2025 Qtr 4 2025 / Qtr 1 2026 | BH64: Feb-2025 Nov-2025 | BI64: Feb-2025 Nov-2025 | BJ64: Quarter 2 2026 (before 12 June 2026) | BK64: 46143 | BM64: Quarter 4 2026 / Quarter 1 2027 | BN64: 46419 | BP64: Oct 2025 LDS & LPA website (21 Nov 2025) | BS64: 46034 | BT64: 45950 | BU64: 46034 | BV64: 45950 | BW64: 46034 | BX64: Published | BZ64: VisualPing
A65: E07000078 | C65: Cheltenham | D65: The Cheltenham, Gloucester and Tewkesbury Strategic and Local Plan (CGTSLP) | E65: 2142 | F65: 2021 | G65: 2036 | H65: N | I65: Y | J65: 43080 | O65: YES | W65: =IF(OR(X65="Yes", Y65="Web-page timetable", Z65="YES"), "Yes") -> Yes | X65: Yes | Y65: LDS Document | AA65: https://www.cheltenham.gov.uk/downloads/file/9720/cheltenham_borough_local_development_scheme | AB65: https://www.cheltenham.gov.uk/download/downloads/id/9720/cheltenham_borough_local_development_scheme.pdf | AD65: 45689 | AE65: 43374 | AF65: Issues & Options | AG65: 43374 | AH65: 43416 | AI65: 43476 | AJ65: https://jointcorestrategy-my.sharepoint.com/personal/website_jointcorestrategy_onmicrosoft_com/_layouts/15/onedrive.aspx?id=%2Fpersonal%2Fwebsite%5Fjointcorestrategy%5Fonmicrosoft%5Fcom%2FDocuments%2FJoint%20Core%20Strategy%20%28JCS%29%20website%2FProjects%2FJoint%20Core%20Strategy%20review%2FJCS%20Issues%20and%20Options%20Consultation%2Epdf&parent=%2Fpersonal%2Fwebsite%5Fjointcorestrategy%5Fonmicrosoft%5Fcom%2FDocuments%2FJoint%20Core%20Strategy%20%28JCS%29%20website%2FProjects%2FJoint%20Core%20Strategy%20review&originalPath=aHR0cHM6Ly9qb2ludGNvcmVzdHJhdGVneS1teS5zaGFyZXBvaW50LmNvbS86YjovZy9wZXJzb25hbC93ZWJzaXRlX2pvaW50Y29yZXN0cmF0ZWd5X29ubWljcm9zb2Z0X2NvbS9FZUN3cFkxbFJ1WkVzTDFBR2hJYk50c0JYYWRITmRCQWhkQURVTTZBSFQwLW93P3J0aW1lPWdISXNMSzY2MTBn | AL65: 45200 | AM65: Consultation on Spatial Options and Key Policy Areas (Reg 18) | AN65: 45200 | AO65: 45292 | AP65: 45352 | AQ65: https://strategiclocalplan.org/wp-content/uploads/2023/12/SLP-Consultation-Document-Reg-18-1.pdf | AS65: 45992 | AT65: Phase 2 SLP consultation | AU65: 45992 | AV65: 45992 | AW65: 46038 | AX65: https://www.punchline-gloucester.com/articles/aanews/have-your-say-on-next-phase-of-gloucestershire-plan-worth-billions | BG65: Aug - Sep 2026 | BH65: 46235 | BJ65: Oct - Nov 2026 | BK65: 46296 | BM65: 46722 | BN65: 46722 | BP65: Feb 2025 LDS & PDT data (March 2025) in relation to adoption date. SLP website | BQ65: PINS intel confirm submission April 2026 | BR65: With an additional Reg 18 stage, commencing Oct 2023, the (now) third Reg 18 (Preferred Options) is now scheduled for March 2025 (was Spring 2023); Reg 19 now Jan 2026 (was Autumn 2023); submission now April 2026 (was Spring 2024); Adoption now TBC (was Winter 2024/Spring 2025) | BS65: 46024 | BT65: 45758 | BU65: 45678 | BV65: 45996 | BW65: 45996 | BX65: Reg 18 ongoing | BZ65: VisualPing
B66: E07000177-02 | C66: Cherwell | D66: Oxfordshire Joint Plan 2050 | E66: 2085 | F66: 2020 | G66: 2050 | H66: N | I66: Y | J66: 20 July 2015 (incorporating Partial Review September 2020) | T66: 44774 | W66: =IF(OR(X66="Yes", Y66="Web-page timetable", Z66="YES"), "Yes") -> Yes | X66: Yes | Y66: LDS Document | AA66: https://www.oxford.gov.uk/downloads/file/7340/local_development_scheme_2020-25 | AB66: https://www.oxford.gov.uk/download/downloads/id/7340/local_development_scheme_2020-25.pdf | AC66: https://mhclg.sharepoint.com/sites/DevelopmentPlans/Shared%20Documents/Data%20and%20Analysis/Planning%20Data%20Unit/LDS%20&%20Reg%2018%20Monitoring/LDS%20Screenshots/OXF2020%20-%20Oxford%20City%20LDS%20July%202020.PNG | AD66: 44317 | AE66: Feb/March 2019 | AF66: First Stage - Introducing the Oxfordshire Plan | AG66: 43497 | AH66: 43507 | AI66: 43549 | AJ66: https://oxfordshireplan.inconsult.uk/consult.ti/Oxfordshire_Plan_Intro/consultationHome | AL66: Summer 2021 | AM66: Spatial Growth Options (including scale and Broad Locations of Growth) (Reg. 18 part2) | AN66: 44378 | AO66: 44407 | AP66: 44477 | AQ66: https://oxfordshireplan.inconsult.uk/Call_for_Ideas_2021/consultationHome | BG66: 45108 | BH66: 45108 | BJ66: 45292 | BK66: 45292 | BM66: TBC | BN66: TBC | BR66: work ceased on plan August 2022 | BS66: 44256 | BT66: 44483 | BU66: 44427 | BV66: 44764 | BW66: 44739 | BX66: work stopped [work stopped on joint plan August 2022] | BZ66: VisualPing
A67: E07000177 | C67: Cherwell | D67: Cherwell Local Plan 2042 | E67: 2289 | F67: 2020 | G67: 2042 | H67: N | I67: N | J67: 20 July 2015 (incorporating Partial Review September 2020) | L67: YES | M67: Local politics | P67: 45645 | Q67: 45869 | W67: =IF(OR(X67="Yes", Y67="Web-page timetable", Z67="YES"), "Yes") -> Yes | X67: Yes | Y67: LDS Document | AA67: https://www.cherwell.gov.uk/info/33/planning-policy/382/local-development-scheme | AB67: https://www.cherwell.gov.uk/download/downloads/id/17666/july-2025-final-local-development-scheme.pdf | AD67: 45839 | AE67: July - Aug 2020 | AF67: Community Involvement Paper: District Wide Issues Consultation | AG67: 44013 | AH67: 44043 | AI67: 44088 | AJ67: https://www.cherwell.gov.uk/info/83/local-plans/729/planning-for-cherwell---local-plan-review/2 | AL67: Oct-Nov 2021 | AM67: Community Involvement Paper 2: Developing Our Options | AN67: 44470 | AO67: 44468 | AP67: 44510 | AQ67: https://www.cherwell.gov.uk/info/83/local-plans/729/planning-for-cherwell---local-plan-review/3 | AS67: Sep-Oct 2023 (was Feb-March 2023) | AT67: Draft Plan (Reg 18) | AU67: Sep-2023 (was Feb-2023) | AV67: 45191 | AW67: 45233 | AX67: https://www.cherwell.gov.uk/info/83/local-plans/729/planning-for-cherwell---local-plan-review/4 | BG67: Sep-Oct 2024 | BH67: 45627 | BI67: 45645 | BJ67: 45748 | BK67: 45748 | BL67: 45869 | BM67: 46174 | BN67: 46174 | BP67: July 2025 LDS and Inspector's letter of Oct 2025. | BQ67: Reg 19 consultation period runs from 19 December 2024 - 14 February 2025. | BS67: 45273 | BT67: 45959 | BU67: 44837 | BV67: 45959 | BW67: 45966 | BX67: Submitted | BZ67: VisualPing
A68: E06000049 | C68: Cheshire East | D68: Cheshire East Local Plan | E68: 2333 | F68: 2028 | G68: 2043 | H68: N | I68: N | J68: 42943 | L68: YES | M68: Nutrient neutrality (March 2022) | W68: =IF(OR(X68="Yes", Y68="Web-page timetable", Z68="YES"), "Yes") -> Yes | X68: Yes | Y68: LDS Document | AA68: https://www.cheshireeast.gov.uk/planning/spatial-planning/cheshire_east_local_plan/local_development_scheme.aspx | AB68: https://www.cheshireeast.gov.uk/pdf/planning/spatial-planning/cheshire-east-lds-march-2025.pdf | AD68: 45717 | BG68: Q1 2027 | BH68: 46419 | BJ68: Q3 2027 | BK68: 46600 | BM68: Q3 2028 | BN68: 46966 | BP68: March 2025 LDS | BQ68: The council has resolved to update the Local Plan Strategy which, once adopted, is expected to replace both the LPS and SADPD. The update will be in the form of a new-style local plan prepared under the government’s proposed reforms to the plan_x0002_making system. | BS68: 45320 | BT68: 45951 | BV68: 45951 | BW68: 46010 | BX68: new plan to be prepared under new system | BZ68: Visualping
A69: E06000050 | C69: Cheshire West and Chester | D69: Local Plan (Part One) Strategic Policies | E69: n/a | J69: 42033 | L69: YES | M69: Nutrient neutrality (March 2022) | U69: 1. 20 Jan 2020 2. 20 April 2022 | V69: 1. A review on 20 Jan 2020 found that the plan did not require updating 2. 20 April 2022 agreed to update local plan | W69: =IF(OR(X69="Yes", Y69="Web-page timetable", Z69="YES"), "Yes") -> Yes | X69: Yes | Y69: LDS Document | AA69: https://www.cheshirewestandchester.gov.uk/your-council/policies-and-performance/council-plans-policies-and-strategies/planning-policy/local-plan | AB69: https://consult.cheshirewestandchester.gov.uk/resources/portal/supportingfiles/800572 | AD69: 45778 | AE69: Summer 2025 | AF69: Reg 18 | AG69: 45839 | BG69: Autumn 2026 | BH69: 46296 | BJ69: 46357 | BK69: 46357 | BM69: Summer/Autumn 2027 | BN69: 46661 | BP69: May 2025 LDS | BQ69: On 20 April 2022 decided to update local plan. On 10 January 2024, the Council formally decided to prepare a new style Local Plan under LURA 2023. Several links and resources related to local governance and planning, including profiles, strategies, and consultations, have been removed from the website. | BS69: 45681 | BT69: 45908 | BU69: 45681 | BV69: 45908 | BW69: 45908 | BX69: had indicated new plan to be prepared under new system, but flipped to current system | BZ69: VisualPing
A70: E07000034 | C70: Chesterfield | D70: Chesterfield Borough Local Plan 2025 - 2044 | E70: 2434 | F70: 2025 | G70: 2044 | H70: N | I70: N | J70: 44027 | W70: =IF(OR(X70="Yes", Y70="Web-page timetable", Z70="YES"), "Yes") -> Yes | X70: Yes | Y70: LDS Document | AA70: https://www.chesterfield.gov.uk/planning-and-building-control/planning-policy-and-the-local-plan/local-development-scheme.aspx | AB70: https://www.chesterfield.gov.uk/media/44nejpem/lds13-december-2025.pdf | AD70: 45992 | AE70: April - May 2025 | AF70: Reg 18 | AG70: 45748 | AH70: 45747 | AI70: 45800 | AJ70: https://www.chesterfield.gov.uk/planning-and-building-control/planning-policy-and-the-local-plan/latest-news-planning/ | AL70: April - May 2026 | AM70: Preferred Strategy and Site Allocations | AN70: 46113 | BG70: 46266 | BH70: 46266 | BJ70: 46357 | BK70: 46357 | BM70: 46661 | BN70: 46661 | BP70: Dec 2025 LDS | BQ70: Consultation under Regulation 18 - May to November 2024 Consultation on Publication (Pre-submission) Draft Plan under Regulation 19 - March 2025 to April 2025 Submission of the Draft Plan to the Government - May 2025 Public Examination (Regulation 22)* May 2025 to July 2026 Inspector’s Final Report published* July 2026 Adoption by the Council* September 2026 | BS70: 45881 | BT70: 46031 | BU70: 45881 | BV70: 46031 | BW70: 46031 | BX70: Reg 18 ongoing | CD70: Yes
A71: E07000225 | C71: Chichester | D71: Chichester Local Plan 2021 - 2039 | E71: 2213 | F71: 2021 | G71: 2039 | H71: N | I71: N | J71: 45888 | K71: 42199 | L71: YES | M71: [Nutrient neutrality (since 2018)] Transport infrastructure; Waste water; Water neutrality | P71: 44960 | Q71: 45415 | R71: 45859 | W71: =IF(OR(X71="Yes", Y71="Web-page timetable", Z71="YES"), "Yes") -> Yes | X71: Yes | Y71: LDS Document | AD71: 45474 | AE71: June-Aug 2017 | AF71: Issues & Options | AG71: 42917 | AH71: 42908 | AI71: 42950 | AJ71: https://www.chichester.gov.uk/article/30930/Issues-and-Options---consultation-June-2017 | AK71: https://mhclg.sharepoint.com/sites/DevelopmentPlans/Shared%20Documents/Data%20and%20Analysis/Planning%20Data%20Unit/Reg%2018%20monitoring/Screenshots/Chichester%20June%202017%20Reg%2018%20FIRST.PNG | AL71: Dec 2018 - Feb 2019 | AM71: Preferred Approach | AN71: 43466 | AO71: 43447 | AP71: 43503 | AQ71: https://www.chichester.gov.uk/article/30923/Preferred-approach---consultation-December-2018 | BG71: Jan - March 2023 | BH71: 44927 | BI71: 44960 | BJ71: early 2024 | BK71: 45323 | BL71: 45415 | BM71: Spring 2025 | BN71: 45778 | BO71: 45888 | BP71: LDS July 2024 | BS71: 45454 | BT71: 45562 | BU71: 44518 | BV71: 45562 | BW71: 45562 | BX71: Adopted | BZ71: Published 3 Feb 2023 | CD71: Yes
A72: E07000005 | C72: Chiltern (defunct - now part of Buckinghamshire) | J72: 40862 | W72: =IF(OR(X72="Yes", Y72="Web-page timetable", Z72="YES"), "Yes") -> FALSE | BX72: DEFUNCT LPA [new unitary authority to prepare plan]
A73: E07000118 | C73: Chorley | D73: Central Lancashire Local Plan | E73: 2100 | F73: 2023 | G73: 2041 | H73: N | I73: Y | J73: 41108 | P73: 45712 | Q73: 45838 | W73: =IF(OR(X73="Yes", Y73="Web-page timetable", Z73="YES"), "Yes") -> Yes | X73: Yes | Y73: LDS Document | AA73: https://centrallocalplan.lancashire.gov.uk/documents/local-development-scheme-2024/ | AB73: https://centrallocalplan.lancashire.gov.uk/media/1340/central-lancashire-local-plan-lds-2024-2026.pdf | AD73: Mar/April 2024 | AE73: July - September 2019 | AF73: Stage 1 - Issues & Options | AG73: 43678 | AH73: 43787 | AI73: 43875 | AJ73: https://centrallocalplan.citizenspace.com/central-team/issuesandoptions/supporting_documents/smaller%20%20Main%20IO%20Consultation%20Paper%20FINAL%20111119.pdf | AL73: 44896 | AM73: Consultation Part One preferred options | AN73: 44896 | AO73: 44896 | AP73: 44981 | AQ73: https://centrallocalplan.lancashire.gov.uk/consultations/ | AS73: 45139 | AT73: Consultation Part two Preferred Options - Draft Plan | AU73: 45139 | AV73: 45139 | AW73: 45199 | BG73: 45689 | BH73: 45689 | BI73: 45712 | BJ73: 45809 | BK73: 45809 | BL73: 45838 | BM73: 46357 | BN73: 46357 | BP73: 5 March 2025 local plans update | BR73: Reg 19 now Feb 2025 and submission by 30th June 2025. | BS73: 45700 | BT73: 45420 | BU73: 45700 | BV73: 45420 | BW73: 45721 | BX73: SUBMITTED | BZ73: VisualPing
A74: E07000048 | C74: Christchurch (defunct - now part of BCP) | J74: 41757 | W74: =IF(OR(X74="Yes", Y74="Web-page timetable", Z74="YES"), "Yes") -> Yes | X74: Yes | Y74: LDS Document | AA74: https://www.bournemouth.gov.uk/planningbuilding/PlanningPolicy/bcp-local-plan/local-development-scheme.aspx | AB74: https://www.bournemouth.gov.uk/planningbuilding/PlanningPolicy/bcp-local-plan/bcp-local-plan-docs/bcp-local-development-scheme.pdf | AD74: 43709 | AE74: Oct/Nov 2019 | AF74: Issues and call fo r sites | AG74: 43739 | AL74: Sep/Oct 2020 | AM74: Issues & Options | AN74: 44075 | BG74: Sep/Oct 2021 | BH74: 44440 | BJ74: 44501 | BK74: 44501 | BM74: 44866 | BN74: 44866 | BS74: 44061 | BX74: DEFUNCT LPA [new unitary authority to prepare plan] | BZ74: Defunct | CD74: Yes
A75: E09000001 | C75: City of London | D75: City Plan 2040 | E75: 1994 | F75: 2025 | G75: 2040 | H75: N | I75: N | J75: 42019 | L75: YES | P75: 44274 | Q75: 45533 | W75: =IF(OR(X75="Yes", Y75="Web-page timetable", Z75="YES"), "Yes") -> Yes | X75: Yes | Y75: LDS Document | AA75: https://www.cityoflondon.gov.uk/services/planning/planning-policy/city-plan-2040 | AB75: https://www.cityoflondon.gov.uk/assets/Services-Environment/2025-city-of-london-corporation-local-development-scheme.pdf | AD75: 45689 | AE75: Sep-Dec 2016 | AF75: Issues & Options | AG75: 42644 | AH75: 42632 | AI75: 42674 | AJ75: https://www.cityoflondon.gov.uk/services/environment-and-planning/planning/planning-policy/local-plan/Documents/local-plan-issues-options-final-20160818.pdf | AK75: https://mhclg.sharepoint.com/sites/DevelopmentPlans/Shared%20Documents/Data%20and%20Analysis/Planning%20Data%20Unit/Reg%2018%20monitoring/Screenshots/City%20of%20London%20Sep%202016%20FIRST.PNG | AL75: Dec 2017 - Feb 2018 | AM75: Draft City Plan | AN75: 43101 | AO75: 43405 | AP75: 43524 | AQ75: https://www.cityoflondon.gov.uk/services/environment-and-planning/planning/planning-policy/local-plan/Documents/draft-city-plan-2036.pdf | BG75: 44256 | BH75: 44256 | BI75: March 2021 April 2024 | BJ75: 45505 | BK75: 45505 | BL75: 45533 | BM75: Spring 2026 | BN75: 46113 | BP75: Feb 2025 LDS | BS75: 45961 | BT75: 45938 | BU75: 45320 | BV75: 45345 | BW75: 45938 | BX75: Submitted August 2024 | BZ75: Published March 2021 To re-publish (exp. Feb-2024) | CD75: Yes
A76: E07000071 | C76: Colchester | D76: Local Plan Review (one combined Plan) | E76: 2352 | H76: N | I76: N | J76: 44228 | K76: CS adopted 2008 amended 16 Jul 2014 | W76: =IF(OR(X76="Yes", Y76="Web-page timetable", Z76="YES"), "Yes") -> Yes | X76: Yes | Y76: LDS Document | AA76: https://www.colchester.gov.uk/local-plan/local-development-scheme/ | AB76: https://cbccrmdata.blob.core.windows.net/noteattachment/CBC-null-LDS-Local%20Development%20Scheme%20March%202025.pdf | AD76: 45717 | AE76: Nov - Dec 2023 | AF76: Consultation on Issues and Options | AG76: 45231 | AH76: 45231 | AI76: 45352 | AJ76: https://colchester.oc2.uk/document/59 | AL76: 45962 | AM76: Preferred Options Local Plan | AN76: 46036 | AO76: 45962 | AP76: 46036 | AQ76: https://www.colchester.gov.uk/local-plan/new-local-plan-to-2041/ | BG76: June/July 2026 | BH76: 46174 | BJ76: Aug/Sep 2026 | BK76: 46235 | BM76: 46508 | BN76: 46508 | BP76: March 2025 LDS & consultation info from website (Dec 2025) | BS76: 46034 | BT76: 45951 | BU76: 46034 | BV76: 45995 | BW76: 45995 | BX76: Reg 18 ongoing * ends Jan 2026
A77: E07000029 | C77: Copeland (defunct, mow part of Cumberland UA) | D77: Copeland Local Plan ("legacy Plan") | E77: 2008 | F77: 2021 | G77: 2039 | H77: N | I77: N | J77: 45601 | K77: 41613 | L77: YES | M77: Nutrient neutrality (March 2022); | P77: 44571 | Q77: 44820 | R77: 45558 | W77: =IF(OR(X77="Yes", Y77="Web-page timetable", Z77="YES"), "Yes") -> Yes | X77: Yes | Y77: LDS Document | AA77: https://www.copeland.gov.uk/content/local-development-scheme | AB77: https://www.copeland.gov.uk/attachments/local-development-scheme-2022 | AD77: 44743 | AE77: Nov 2019 - Jan 2020 | AF77: Issues & Options | AG77: 43770 | AH77: 43794 | AI77: 43850 | AJ77: https://www.copeland.gov.uk/content/copeland-local-plan | AL77: May - June 2020 | AM77: Preferred Options | AN77: 43952 | AO77: 44095 | AP77: 44150 | AQ77: https://www.copeland.gov.uk/content/local-plan-consultations | BG77: May/June 2021 | BH77: 44317 | BI77: 10/01/2022 - | BJ77: 44440 | BK77: 44440 | BL77: 44820 | BM77: Summer 2023 | BN77: July 2023 [missed] | BO77: 45601 | BS77: 44106 | BT77: 45146 | BV77: 45146 | BW77: 44783 | BX77: Adopted Nov 2024 | BZ77: Submitted Sep 2022
A78: E07000150 | C78: Corby - (defunct - replaced by North Northamptonshire from 1 April 2021) | D78: North Northamptonshire Joint Core Strategy Review July 2019 | E78: 1367 | F78: 2011 | G78: 2031 | H78: N | I78: Y | J78: 42565 | U78: 43647 | V78: JPC decided Joint Spatial Core Strategy does not require updating. Decision overtaken by events - unitarisation and now working on an emerging plan. | W78: =IF(OR(X78="Yes", Y78="Web-page timetable", Z78="YES"), "Yes") -> Yes | X78: Yes, but TT refers to adopted Plan | Y78: Web-page timetable | AA78: http://www.nnjpdu.org.uk/news/north-northamptonshire-joint-core-strategy-review-july-2019/ | AD78: 43678 | AE78: Summer 2021 | AF78: Scope & Issues | AG78: 44378 | BG78: Summer 2022 | BH78: 44743 | BJ78: Spring 2023 | BK78: 45017 | BM78: Winter 2023 | BN78: 45292 | BS78: 44547 | BU78: 44547 | BV78: 44278 | BX78: DEFUNCT LPA [new unitary authority to prepare plan] | BZ78: VisualPing
A79: E06000052 | C79: Cornwall | D79: self reviewed. New plan to be prepared under new system | H79: N | I79: N | J79: 42696 | L79: YES | M79: Nutrient neutrality (since 2018) | U79: 44461 | V79: Plan remains up to date and continues to carry full weight in decision-making. | W79: =IF(OR(X79="Yes", Y79="Web-page timetable", Z79="YES"), "Yes") -> Yes | X79: Yes | Y79: LDS Document | AA79: https://www.cornwall.gov.uk/planning-and-building-control/planning-policy/adopted-plans/local-development-scheme-and-statement-of-community-involvement/ | AB79: https://www.cornwall.gov.uk/media/c22phsr0/cornwall-local-development-scheme-january-2025.pdf | AD79: 45658 | AE79: 46023 | AF79: Reg 18 (Gateway 1) | AG79: 46023 | BG79: 46539 | BH79: 46539 | BJ79: 46753 | BK79: 46753 | BM79: 46966 | BN79: 46966 | BP79: Jan 2025 LDS | BS79: 45960 | BT79: 45678 | BU79: 45678 | BV79: 45678 | BW79: 45678 | BX79: new plan to be prepared under new system | BZ79: Visualping
A80: E07000079 | C80: Cotswold | D80: Cotswold District Local Plan 2025-2043 | E80: 2330 | F80: 2025 | G80: 2043 | H80: N | I80: N | J80: 43315 | L80: YES | M80: White Paper NPPF (2023) | W80: =IF(OR(X80="Yes", Y80="Web-page timetable", Z80="YES"), "Yes") -> Yes | X80: Yes | Y80: LDS Document | AA80: https://www.cotswold.gov.uk/planning-and-building/planning-policy/local-plan-update-and-supporting-information/ | AB80: https://meetings.cotswold.gov.uk/documents/s13946/Annex%20B%20Cotswold%20District%20Local%20Development%20Scheme%20October%202025.pdf | AD80: 45931 | AE80: 44562 | AF80: Issues & Options | AG80: 44562 | AH80: 44596 | AI80: 44640 | AJ80: https://www.cotswold.gov.uk/planning-and-building/planning-policy/local-plan-update-and-supporting-information/ | AL80: Q1 2024 | AM80: Local Plan update consultation | AN80: 45323 | AO80: 45323 | AP80: 45368 | AQ80: https://www.cotswold.gov.uk/planning-and-building/planning-policy/local-plan-update-and-supporting-information/ | AS80: 45975 | AT80: Preferred Options | AU80: 46024 | AV80: 45975 | AW80: 46024 | AX80: https://www.cotswold.gov.uk/planning-and-building/planning-policy/local-plan-news-and-consultation/preferred-options-consultation-nov-2025-documents/ | AZ80: Winter/Spring 2026 | BA80: Reg 18 Consultation on technical documents | BB80: 46082 | BG80: Summer 2026 | BH80: 46204 | BJ80: Winter 2026 | BK80: 46357 | BM80: Winter 2027 | BN80: 46753 | BP80: Oct 2025 LDS | BS80: 45320 | BT80: 46008 | BU80: 45141 | BV80: 46008 | BW80: 45868 | BX80: Reg 18 ongoing
A81: E08000026 | C81: Coventry | D81: Local Plan Review | E81: 2319 | F81: 2021 | G81: 2041 | H81: N | I81: N | J81: 43075 | P81: 45677 | Q81: 45909 | W81: =IF(OR(X81="Yes", Y81="Web-page timetable", Z81="YES"), "Yes") -> Yes | X81: Yes | Y81: LDS Document | AA81: https://www.coventry.gov.uk/planning-policy/coventry-local-plan-2011-2031/7 | AB81: https://www.coventry.gov.uk/downloads/download/8037/local-development-scheme-december-2024 | AD81: 45901 | AE81: June - August 2023 | AF81: Issues and Options | AG81: 45078 | AH81: 45125 | AI81: 45198 | AJ81: https://coventrycitycouncil.inconsult.uk/system/listConsultations?type=C | BG81: Q4 2024/Q1 2025 | BH81: 45658 | BI81: 45677 | BJ81: Q3 2025 July - Sep 2025 | BK81: 45870 | BL81: 45909 | BM81: Q3 2026 July - Sep 2026 | BN81: 46235 | BP81: Sep 2025 LDS | BS81: 45695 | BT81: 45960 | BU81: 45678 | BV81: 45960 | BW81: 45960 | BX81: Submitted | BZ81: VisualPing
A82: E07000163 | C82: Craven (defunct - now part of North Yorkshire) | D82: Review abandoned and work undertaken will feed into proposed North Yorkshire Plan | F82: 2012 | G82: 2032 | H82: N | I82: N | J82: 43781 | W82: =IF(OR(X82="Yes", Y82="Web-page timetable", Z82="YES"), "Yes") -> Yes | X82: Yes | Y82: LDS Document | AA82: https://www.cravendc.gov.uk/planning/craven-local-plan/ | AB82: https://www.cravendc.gov.uk/planning/local-development-scheme/ | AD82: 2020 update | BS82: 44039 | BT82: 45012 | BX82: DEFUNCT LPA [new unitary authority to prepare plan] | BZ82: Defunct
A83: E07000226 | C83: Crawley | D83: Crawley Borough Local Plan Review | E83: TBA | H83: N | I83: N | J83: 45581 | K83: 42354 | L83: YES | M83: OTHER; COVID-19; Water neutrality | U83: 44181 | W83: =IF(OR(X83="Yes", Y83="Web-page timetable", Z83="YES"), "Yes") -> Yes | X83: Yes | Y83: LDS Document | AA83: https://crawley.gov.uk/planning/planning-policy/engagement-and-monitoring/local-development-scheme#:~:text=Self%20build%20register-,Local%20Development%20Scheme,timetable%20is%20currently%20being%20reviewed. | AB83: https://crawley.gov.uk/sites/default/files/2025-03/Local%20Development%20Scheme.pdf | AD83: 45689 | AE83: Mid 2027 | AF83: First Consultation | AG83: 46539 | AK83: https://mhclg.sharepoint.com/sites/DevelopmentPlans/Shared%20Documents/Data%20and%20Analysis/Planning%20Data%20Unit/Reg%2018%20monitoring/Screenshots/Crawley%20June%202019%20Reg%2018%20FIRST.PNG | BG83: Autumn 2028 | BH83: 47027 | BJ83: Winter 2028 | BK83: 47119 | BM83: 47392 | BN83: 47392 | BS83: 45961 | BT83: 45908 | BU83: 44932 | BV83: 45908 | BX83: new plan to be prepared under new system | BZ83: Published three times. Submitted 31 July 2023
A84: E09000008 | C84: Croydon | D84: Croydon Local Plan Partial Review | E84: 2144 | F84: 2019 | G84: 2040 | H84: N | I84: N | J84: 43158 | L84: YES | M84: Other (financial) | P84: 44567 | Q84: 45625 | W84: =IF(OR(X84="Yes", Y84="Web-page timetable", Z84="YES"), "Yes") -> Yes | X84: Yes | Y84: LDS Document | AA84: https://www.croydon.gov.uk/planning-and-regeneration/planning-policy/local-plan-review/local-plan-programme | AB84: https://www.croydon.gov.uk/sites/default/files/2025-07/local-development-scheme-july-2025-v2.pdf | AD84: 45839 | AE84: Autumn 2019 | AF84: Issues and Options | AG84: 43739 | AH84: 43770 | AI84: 43831 | AJ84: https://new.croydon.gov.uk/sites/default/files/Planning/local%20plan%20review/Croydon%20Local%20Plan%20review%20-%20Issues%20and%20Options%20(Ch1%20Introduction).pdf | BG84: Spring/Summer 2021 | BH84: 44317 | BI84: Jan 2022 July 2024 | BJ84: BEF end of 2024 | BK84: 45627 | BL84: 45625 | BM84: Spring 2026 | BN84: 46113 | BP84: July 2025 LDS & post-hearings action point letter (Nov 2025) | BQ84: LPA say they are on track with this timetable: key milestones are as listed below: • Proposed submission consultation: January to February 2024 • Submission of plan to Secretary of State: Summer 2024 • Local plan examination anticipated during late 2024 • Local plan adoption anticipated December 2025 | BS84: 45320 | BT84: 45950 | BV84: 45950 | BW84: 46031 | BX84: Submitted Nov 2024 | BZ84: Published Jan 2022 / Visualping | CA84: x
A85: E06000063 | C85: Cumberland | D85: Cumberland Local Plan | E85: TBA | F85: 2025 | G85: 2045 | H85: N | I85: N | J85: new LPA | W85: =IF(OR(X85="Yes", Y85="Web-page timetable", Z85="YES"), "Yes") -> Yes | X85: Yes | Y85: LDS Document | AA85: https://www.cumberland.gov.uk/planning-and-building-control/planning-policy/cumberland-local-plan | AB85: https://www.cumberland.gov.uk/sites/default/files/2025-04/Cumberland%20Local%20Development%20Scheme%202025.pdf | AD85: 45717 | AE85: March 2025-March 2026 | AF85: Issues/Scope, Scope, Options and Draft (Regulation 18) and Consultation | AG85: 45717 | AH85: 45901 | AI85: 45931 | AJ85: https://www.cumberland.gov.uk/planning-and-building-control/planning-policy/cumberland-local-plan-issues-and-options-consultation | BG85: 46447 | BH85: 46447 | BJ85: 46539 | BK85: 46539 | BM85: 46813 | BN85: 46813 | BP85: PINS intel (Jan 2025) & LPA Issues and Options document (Sep 2025) | BS85: 45562 | BT85: 45932 | BV85: 45932 | BW85: 45932 | BX85: new plan to be prepared under new system
B86: E07000096-01 | C86: Dacorum | D86: South West Hertfordshire 2050 Joint Strategic Plan | E86: 2285 | F86: 2025 | G86: 2050 | H86: N | I86: Y | J86: 41542 | W86: =IF(OR(X86="Yes", Y86="Web-page timetable", Z86="YES"), "Yes") -> Yes | X86: Yes | Y86: Web-page timetable | AA86: https://www.swhertsplan.com/ | AB86: https://www.swhertsplan.com/what-is-the-joint-strategic-plan | AD86: 45047 | AE86: 44805 | AF86: First Reg 18 consultation 'Realising our Potential' | AG86: 44805 | AH86: 44809 | AI86: 44869 | AL86: mid-2024 | AM86: Options for scale and pattern of growth | AN86: 45444 | BG86: 45658 | BH86: 45658 | BJ86: 45717 | BK86: 45717 | BM86: TBC | BN86: TBC | BP86: website Oct 2025 | BQ86: At their meeting on 14 October 2024, Dacorum's Cabinet will consider any requests that their Oversight and Scrutiny Committee may make to amend the draft plan prior to it being finalised and published under Regulation 19. Officers will advise Cabinet on whether the changes are such that further work will need to be undertaken prior to the document being finalised and published under Regulation 19. | BR86: First Reg 18 consultation started 5 Sept and closed 4 November 2022. | BS86: 45468 | BU86: 44803 | BV86: 45345 | BW86: 45950 | BX86: now likely to be an SDS
A87: E07000096 | C87: Dacorum | D87: Dacorum Local Plan 2026 - 2041 | E87: 2133 | F87: 2026 | G87: 2041 | H87: N | I87: N | J87: 41542 | L87: YES | M87: Other | P87: 45600 | Q87: 45727 | W87: =IF(OR(X87="Yes", Y87="Web-page timetable", Z87="YES"), "Yes") -> Yes | X87: Yes | Y87: LDS Document | AA87: https://www.dacorum.gov.uk/home/planning-development/planning-strategic-planning/local-development-scheme | AB87: https://www.dacorum.gov.uk/docs/default-source/strategic-planning/local-development-schemea449724551156b7f9bc7ff00000246a4.pdf?sfvrsn=315c199e_3 | AD87: 45566 | AE87: November/December 2017 | AF87: Issues & Options | AG87: 43040 | AH87: 43040 | AI87: 43082 | AJ87: http://www.dacorum.gov.uk/home/planning-development/planning-strategic-planning/new-single-local-plan | AK87: https://mhclg.sharepoint.com/sites/DevelopmentPlans/Shared%20Documents/Data%20and%20Analysis/Planning%20Data%20Unit/Reg%2018%20monitoring/Screenshots/Dacorum%20Nov%202017%20Reg%2018%20FIRST.PNG | AL87: 44136 | AM87: Strategy for Growth / Preferred Option [emerging strategy] | AN87: 44136 | AO87: 44136 | AP87: 44256 | AQ87: https://www.dacorum.gov.uk/home/planning-development/planning-strategic-planning/new-single-local-plan | AS87: June - July 2023 | AT87: Revised Strategy for Growth consultation | AU87: 45078 | AV87: 45229 | AW87: 45271 | AX87: https://www.dacorum.gov.uk/home/planning-development/planning-strategic-planning/new-single-local-plan | BG87: 45566 | BH87: 45566 | BI87: 45600 | BJ87: 45717 | BK87: 45717 | BL87: 45727 | BM87: 46054 | BN87: 46054 | BP87: Inspector's letter of 10 Oct 2025 | BR87: First Reg 18 consultation started 5 Sept and closed 4 November 2022. | BS87: 45952 | BT87: 45950 | BU87: 45950 | BV87: 45687 | BW87: 45966 | BX87: Submitted | BZ87: VisualPing | CD87: Yes
A88: E06000005 | C88: Darlington | D88: Darlington Local Plan Review 2026-2042 | F88: 2026 | G88: 2042 | H88: N | I88: N | J88: 44609 | K88: 40669 | L88: YES | M88: Nutrient neutrality (March 2022) | W88: =IF(OR(X88="Yes", Y88="Web-page timetable", Z88="YES"), "Yes") -> Yes | X88: Yes | Y88: LDS Document | AA88: https://www.darlington.gov.uk/planning-and-building-regs/planning/planning-and-environmental-policy/other-statutory-documents/local-development-scheme/ | AB88: https://www.darlington.gov.uk/media/yuwdv0yk/lds-feb-2025.pdf | AD88: 45689 | AE88: 45901 | AF88: draft plan consultation | AG88: 45901 | BG88: 46082 | BH88: 46082 | BJ88: 46266 | BK88: 46266 | BM88: Summer 2027 | BN88: 46569 | BP88: Feb 2025 LDS | BS88: 45961 | BT88: 45701 | BU88: 45960 | BV88: 45701 | BW88: 45960 | BX88: Reg 18 yet to start [missed] | CD88: Yes
A89: E07000107 | C89: Dartford | D89: Dartford Local Plan | E89: TBA | H89: N | I89: N | J89: 45404 | K89: 40812 | W89: =IF(OR(X89="Yes", Y89="Web-page timetable", Z89="YES"), "Yes") -> FALSE | X89: No | Y89: None | BQ89: Timetable in 2018 LDS out of date. Published 26 Feb 2021 and re-published Sept 2021. Dartford carried out a consultation on the second Pre-Submission (Publication) Local Plan from 15th September to 27th October 2021. The Plan was re-published as changes had to be made to take account of Natural England’s notification of the Swanscombe Peninsula SSSI. The new Plan will replace the existing adopted Core Strategy and Development Policies Plans and will set out the location, type and amount of new development to 2037. PINS Intel: Submission expected Dec 2021. Gravesham want help from Dartford meeting their housing need. | BS89: 44257 | BV89: 45413 | BW89: 44516 | BX89: new plan to be prepared under new system | BZ89: Found Sound
A90: E26000001 | C90: Dartmoor NP | D90: Dartmoor National Park Local Plan | E90: TBA | H90: N | I90: N | J90: 44533 | K90: 39542 | W90: =IF(OR(X90="Yes", Y90="Web-page timetable", Z90="YES"), "Yes") -> Yes | X90: Yes | Y90: LDS Document | AA90: https://www.dartmoor.gov.uk/living-and-working/business/planning-policy/local-plan-review | AB90: https://www.dartmoor.gov.uk/__data/assets/pdf_file/0025/540826/Local_Development_Scheme-2025_Review.pdf | AD90: 45689 | AE90: 2028/29 | AG90: 2028/29 | BG90: 2030/31 | BH90: 2030/31 | BJ90: 2031/32 | BK90: 2031/32 | BP90: Feb 2025 LDS | BQ90: 20/03/24 LPA advised no Plan will be submitted between 2024-2026 | BS90: 45961 | BT90: 45908 | BV90: 45908 | BW90: 45908 | BX90: new plan to be prepared under new system
A91: E07000151 | C91: Daventry (defunct - replaced by West Northamptonshire) | D91: West Northants Strategic Plan (WNSP) | E91: 2086 | F91: 2019 | G91: 2050 | H91: N | I91: Y | J91: 41988 | U91: 43800 | V91: Daventry, Northampton & South Northants have already committed to a review of the plan with work on the West Northants Strategic Plan already underway. December 2019 Review of JCS (adopted Dec 2014) undertaken to comply with regulation. | W91: =IF(OR(X91="Yes", Y91="Web-page timetable", Z91="YES"), "Yes") -> Yes | X91: Yes | Y91: LDS Document | AA91: http://www.westnorthamptonshirejpu.org/connect.ti/website/view?objectId=2737360&expa=exp&expf=2737360&expl=2 | AB91: http://www.westnorthamptonshirejpu.org/connect.ti/website/view?objectId=42277797#42277797 | AC91: https://mhclg.sharepoint.com/:i:/s/DevelopmentPlans/EVktz4ps2nhJlEQOS9hjffQBzMTtD8P2GGEKflsKB9pNxA?e=umZhCT | AD91: 43374 | AE91: 43525 | AF91: Issues Consultation | AG91: 43525 | AH91: 43682 | AI91: 43749 | AJ91: https://www.maidwellwithdraughton.co.uk/west-northamptonshire-strategic-plan-issues-consultation | AK91: https://mhclg.sharepoint.com/sites/DevelopmentPlans/Shared%20Documents/Data%20and%20Analysis/Planning%20Data%20Unit/Reg%2018%20monitoring/Screenshots/West%20Northants%20JSP%20Issues%20Aug%202019.PNG | AL91: Oct - Nov 2021 | AM91: Spatial Options Consultation | AN91: 44470 | AO91: 44480 | AP91: 44536 | AQ91: https://westnorthantsplan.inconsult.uk/consult.ti/system/listConsultations?type=O | AS91: 44713 | AT91: Draft Plan (Reg 18) | AU91: 44713 | BG91: 44896 | BH91: 44896 | BJ91: 45017 | BK91: 45017 | BM91: 45352 | BN91: 45352 | BS91: 44547 | BT91: 44477 | BU91: 44547 | BV91: 44477 | BX91: DEFUNCT LPA [new unitary authority to prepare plan] | BZ91: VisualPing LDS & Reg 18
A92: E06000015 | C92: Derby | D92: Local Plan for Derby | G92: 2040 | H92: N | I92: N | J92: 42760 | U92: 44531 | V92: Update - particularly to housing requirement is needed. New single plan will look forward to 2040 and include work on Part 2 already undertaken. | W92: =IF(OR(X92="Yes", Y92="Web-page timetable", Z92="YES"), "Yes") -> Yes | X92: Yes | Y92: LDS Document | AA92: https://www.derby.gov.uk/environment-and-planning/planning/local-plan/emerging/ | AB92: https://www.derby.gov.uk/media/derbycitycouncil/contentassets/documents/environmentandplanning/planning/pispondon/12-07-local-development-scheme-v9-2025.pdf | AD92: 45689 | AE92: 45992 | AF92: Draft Plan Consultation | AG92: 45992 | BG92: Summer 2026 | BH92: 46204 | BJ92: 46357 | BK92: 46357 | BM92: Summer 2027 | BN92: 46569 | BP92: Feb 2025 LDS | BS92: 45960 | BT92: 45950 | BU92: 45960 | BV92: 45950 | BW92: 45950 | BX92: Reg 18 yet to start | BZ92: Visualping
A93: E07000035 | C93: Derbyshire Dales | D93: Local Plan Review | E93: 2334 | F93: 2017 | G93: 2040 | H93: N | I93: N | J93: 43076 | L93: YES | M93: Nutrient neutrality (March 2022) | U93: Jan 2022 (10A) | V93: Some parts of adopted plan need to be modified | W93: Yes | X93: Yes | Y93: LDS Document | AA93: https://www.derbyshiredales.gov.uk/planning-a-building-control/planning-policy/local-development-scheme | AB93: https://www.derbyshiredales.gov.uk/documents/derbyshire-dales-local-development-scheme-pdf-1-04mb/download | AD93: 45658 | AE93: 45352 | AF93: A New Approach to Housing - Consultation May 2024 (non-Reg 18) | AG93: 45352 | AH93: 45421 | AI93: 45463 | AJ93: https://www.derbyshiredales.gov.uk/documents/derbyshire-dales-local-plan-review-a-new-approach-to-housing-consultation-may-2024-leaflet-pdf-2mb/download | AL93: 46023 | AM93: Draft Derbyshire Dales Local Plan consultation (Reg 18) | AN93: 46023 | BG93: 46235 | BH93: 46235 | BJ93: 46357 | BK93: 46357 | BM93: 46631 | BN93: 46631 | BP93: Jan 2025 LDS | BS93: 45960 | BT93: 45700 | BU93: 45960 | BV93: 45700 | BW93: 45960 | BX93: Reg 18 ongoing | BZ93: VisualPing
A94: E08000017 | C94: Doncaster | D94: none | E94: n/a | H94: N | I94: N | J94: 44462 | K94: 41047 | W94: =IF(OR(X94="Yes", Y94="Web-page timetable", Z94="YES"), "Yes") -> FALSE | X94: No | Y94: None | AA94: n/a | AB94: n/a | AD94: none found | BP94: PINS intel (Jan 2025) | BQ94: 20/02/24 LPA advise they have no intention of submitting a Plan before 2027 | BS94: 29/01/2024 [none found] | BT94: 45014 | BX94: new plan to be prepared under new system | CD94: Yes
A95: E06000059 | C95: Dorset | D95: Dorset Council Local Plan | E95: 2145 | F95: 2026 | G95: 2043 | H95: N | I95: N | J95: new LPA | L95: YES | M95: Nutrient neutrality (since 2018) Uncertainty surrounding national policy | W95: =IF(OR(X95="Yes", Y95="Web-page timetable", Z95="YES"), "Yes") -> Yes | X95: Yes | Y95: LDS Document | AA95: https://www.dorsetcouncil.gov.uk/w/the-local-development-scheme-for-dorset-council#adopted-development-plan-documents | AB95: https://www.dorsetcouncil.gov.uk/documents/35024/282495/20250225+-+Dorset+Council+LDS+-+March+2025.pdf/b004ba28-a02f-54d3-98d0-515d0c99813f | AD95: 45717 | AE95: 44197 | AF95: Options consultation | AG95: 44197 | AH95: 44197 | AL95: 45870 | AM95: Options consultation (Reg 18) | AN95: 45887 | AO95: 45943 | AP95: 45943 | AQ95: https://consultation.dorsetcouncil.gov.uk/spatial-planning/dorset-council-local-plan-consultation-2025/ | BG95: 46235 | BH95: 46235 | BJ95: 46357 | BK95: 46357 | BM95: Winter 2027 | BN95: 46753 | BP95: March 2025 LDS | BS95: 45932 | BT95: 45716 | BU95: 45681 | BV95: 45932 | BW95: 45932 | BX95: Reg 18 completed | BZ95: VisualPing
A96: E07000108 | C96: Dover | D96: Local Plan Review | E96: 2117 | F96: 2020 | G96: 2040 | H96: N | I96: N | J96: 45581 | K96: 40233 | L96: YES | M96: Nutrient neutrality (since 2018) | P96: 44855 | Q96: 45016 | R96: 45555 | W96: =IF(OR(X96="Yes", Y96="Web-page timetable", Z96="YES"), "Yes") -> FALSE | X96: Yes, but refers to something else | Y96: LDS Document | AA96: https://www.dover.gov.uk/Planning/Planning-Policy/Local-Development-Scheme.aspx | AB96: https://www.dover.gov.uk/Planning/Planning-Policy/District-Local-Plan/FINALV-LDS-2025.pdf | AD96: 45689 | AE96: 44197 | AG96: 44197 | AH96: 44216 | AI96: 44272 | AJ96: https://www.dover.gov.uk/Planning/Planning-Policy-and-Regeneration/New-District-Local-Plan/Home.aspx | BG96: 44835 | BH96: 44835 | BI96: 44855 | BJ96: Qtr 1/2 2023 | BK96: 44986 | BL96: 45016 | BM96: 2024 | BN96: 2024 | BO96: 45581 | BP96: Feb 2025 LDS | BQ96: no new plan being prepared | BS96: 45961 | BT96: 45937 | BU96: 45937 | BV96: 44860 | BW96: 45937 | BX96: Adopted Oct 2024 | BZ96: Visual Ping: Submitted March 2023
B97: E08000027-01 | C97: Dudley | D97: Black Country Plan 2039 | E97: 2044 | F97: 2020 | G97: 2039 | H97: N | I97: Y | J97: 40577 | L97: YES | N97: PAS | W97: =IF(OR(X97="Yes", Y97="Web-page timetable", Z97="YES"), "Yes") -> Yes | X97: Yes | Y97: Web-page timetable | AA97: https://blackcountryplan.dudley.gov.uk/t2/p1/ | AB97: https://blackcountryplan.dudley.gov.uk/t2/p1/ | AD97: 44682 | AE97: July - Sept 2017 | AF97: Issues & Options | AG97: 42917 | AH97: 42917 | AI97: 42979 | AJ97: http://blackcountrycorestrategy.dudley.gov.uk/t1/p3/ | AK97: https://mhclg.sharepoint.com/sites/DevelopmentPlans/Shared%20Documents/Data%20and%20Analysis/Planning%20Data%20Unit/Reg%2018%20monitoring/Screenshots/Dudley%20-%20Black%20Country%20Issues%20&%20Options%20July%202017.PNG | AL97: Aug - Sept 2021 | AM97: Draft Plan for Consultation (Reg 18) | AN97: 44409 | AO97: 44424 | AP97: 44480 | AQ97: https://blackcountryplan.dudley.gov.uk/t2/p4/ | AS97: July - Sept 2022 | AT97: Additional Consultation on Draft Plan (Reg. 18ii) - Additional Walsall sites only | AU97: 44743 | BG97: Oct/Nov - Dec 2022 | BH97: 44835 | BJ97: March - May 2023 | BK97: 44986 | BM97: March - May 2024 | BN97: 45352 | BR97: Timetable revised May 2022. Additional Reg 18 July - Sept 2022; Reg 19 Oct/Nov 2022 - Dec 2022; Submission March - May 2023; Adoption March - May 2024. DLUHC intel: delay to R19 by couple of months. WORK ON PLAN STOPPED 19 OCT 2022 | BS97: 44672 | BT97: 44713 | BU97: 44758 | BV97: 44713 | BW97: 44741 | BX97: work stopped [work stopped on joint plan Oct 2022] | BZ97: e-mail alert & VisualPing
A98: E08000027 | C98: Dudley | D98: Dudley Local Plan 2041 | E98: 2417 | F98: 2023 | G98: 2041 | H98: N | I98: N | J98: 40577 | L98: YES | M98: Work on Black Country Plan stopped | P98: 45583 | Q98: 45702 | W98: =IF(OR(X98="Yes", Y98="Web-page timetable", Z98="YES"), "Yes") -> Yes | X98: Yes | Y98: LDS Document | AA98: https://www.dudley.gov.uk/residents/planning/planning-policy/dudley-local-plan/local-development-scheme/ | AB98: https://www.dudley.gov.uk/media/4n2p0cdd/local-development-scheme-report-november-2024.pdf | AD98: 45597 | AE98: Autumn 2023 | AF98: Draft Dudley Local Plan Reg 18 Consultation | AG98: Oct-2023 (was Jul-2023) | AH98: 45240 | AI98: 45282 | AJ98: https://dudley.oc2.uk/document/1/1#d1 | BG98: Autumn 2024 | BH98: 45566 | BI98: 45583 | BJ98: 45689 | BK98: 45689 | BL98: 45702 | BM98: Winter 2025/Spring 2026 | BN98: 46113 | BP98: Post Hearings Letter (Jan 2026) | BQ98: Reg 19 consultation ran from 18 October 2024 to 29 November 2024 | BS98: 45952 | BT98: 45632 | BU98: 45929 | BV98: 45687 | BW98: 46031 | BX98: Submitted
A99: E06000047 | C99: Durham | D99: none | E99: n/a | H99: N | I99: N | J99: 44125 | K99: none [Oct 2020 adopted plan is first post-2004 Act Plan] | W99: =IF(OR(X99="Yes", Y99="Web-page timetable", Z99="YES"), "Yes") -> Yes | X99: Yes | Y99: LDS Document | AA99: https://durham.gov.uk/article/3266/Development-Plan-for-County-Durham | AB99: https://durham.gov.uk/media/46287/County-Durham-Local-Development-Scheme-March-2025/pdf/CountyDurhamLocalDevelopmentSchemeMarch2025.pdf?m=1744890694817 | AD99: 45717 | AE99: March 2026 - April 2026 | AF99: First public consultation | AG99: 46082 | BG99: Nov 2026 - Dec 2026 | BH99: 46327 | BJ99: July - Aug 2027 | BK99: 46569 | BM99: 46844 | BN99: 46844 | BP99: March 2025 LDS | BS99: 45320 | BT99: 45937 | BV99: 45937 | BW99: 45937 | BX99: new plan to be prepared under new system | CD99: Yes
A100: E09000009 | C100: Ealing | D100: New Local Plan | E100: 2296 | F100: 2024 | G100: 2039 | H100: N | I100: N | J100: 41002 | P100: 45350 | Q100: 45614 | W100: =IF(OR(X100="Yes", Y100="Web-page timetable", Z100="YES"), "Yes") -> Yes | X100: Yes | Y100: LDS Document | AA100: https://www.ealing.gov.uk/info/201164/local_plans/616/local_development_scheme/1 | AB100: https://www.ealing.gov.uk/downloads/download/597/local_development_scheme_lds | AD100: 45108 | AE100: 44866 | AF100: Initial Proposals (new draft plan (Reg 18)) | AG100: 44866 | AH100: 44895 | AI100: 44965 | AJ100: https://www.ealing.gov.uk/info/201164/local_plan/3125/new_local_plan | AL100: 5 July - 16 Aug 2023 | AM100: Additional site allocations for gyspy and traveller pitch provision | AN100: 45108 | AO100: 45112 | AP100: 45154 | AQ100: https://www.ealing.gov.uk/info/201164/local_plan/3125/new_local_plan | BG100: 45323 | BH100: 45292 | BI100: 45350 | BJ100: 45444 | BK100: 45444 | BL100: 45614 | BM100: end of 2024/early 2025 | BN100: 45658 | BP100: PINS intel May 2024 | BQ100: The Reg 19 consultation will run from 28 February 2024 until 6pm on 10 April 2024. | BS100: 45950 | BT100: 45345 | BU100: 45170 | BV100: 45440 | BW100: 45440 | BX100: Submitted Nov 2024 | BZ100: VisualPing; published
...

Sheet This is the original VLS!

Sheet updated 12 Jan 2026

Sheet Pre-Reg 19 Emerging Plans
A1: LIVE DOCUMENT - DO NOT EDIT - SUMMARY OF LOCAL PLAN POSITION
A2: NOTE: PRE-PUBLICATION PLANS ONLY ARE RECORDED HERE
A3: ONSCODE | B3: Unique VLS code [only to be used where there is more than one plan] | C3: Local authority name | D3: "defunct LPA"? | E3: New LPA? (2019 - 2023) | F3: Title of Emerging Development Plan Document | G3: Emerging Plan Period Start (YYYY) | H3: Emerging Plan Period End (YYYY) | I3: Aligned Plan (Y/N) | J3: Joint Plan (Y/N) | K3: Last Plan Adopted | L3: First Reg 18 consultation (expected) | M3: First Reg 18 consultation (actual) | N3: Second Reg 18 consultation (expected) | O3: Second Reg 18 consultation (actual) | P3: Third Reg 18 consultation (expected) | Q3: Third Reg 18 consultation (actual) | R3: Fourth Reg 18 consultation (expected) | S3: Fourth Reg 18 consultation (actual) | T3: Expected Publication | U3: Expected Submission | V3: Expected Adoption | W3: Summary Stage | X3: Summary Stage for PowerBi Live or Completed Reg 18? | Y3: Date LDS checked (no change) | Z3: Date LDS updated | AA3: Date timetable checked (no change) | AB3: Date timetable updated
A4: E07000223 | C4: Adur | F4: =IF(VLOOKUP($A4,'8 Oct - LIVE LDS Data'!$A$3:$AAD$1504,4,FALSE)=0/1/1900,"",VLOOKUP($A4,'8 Oct - LIVE LDS Data'!$A$3:$AAD$1504,4,FALSE)) -> Adur Local Plan | G4: =IF(VLOOKUP($A4,'8 Oct - LIVE LDS Data'!$A$3:$AAD$1504,6,FALSE)=0/1/1900,"",VLOOKUP($A4,'8 Oct - LIVE LDS Data'!$A$3:$AAD$1504,6,FALSE)) -> 2024 | H4: =IF(VLOOKUP($A4,'8 Oct - LIVE LDS Data'!$A$3:$AAD$1504,7,FALSE)=0/1/1900,"",VLOOKUP($A4,'8 Oct - LIVE LDS Data'!$A$3:$AAD$1504,7,FALSE)) -> 2039 | I4: =IF(VLOOKUP($A4,'8 Oct - LIVE LDS Data'!$A$3:$AAD$1504,8,FALSE)=0/1/1900,"",VLOOKUP($A4,'8 Oct - LIVE LDS Data'!$A$3:$AAD$1504,8,FALSE)) -> N | J4: =IF(VLOOKUP($A4,'8 Oct - LIVE LDS Data'!$A$3:$AAD$1504,9,FALSE)=0/1/1900,"",VLOOKUP($A4,'8 Oct - LIVE LDS Data'!$A$3:$AAD$1504,9,FALSE)) -> N | K4: =IF(VLOOKUP($A4,'8 Oct - LIVE LDS Data'!$A$3:$AAD$1504,10,FALSE)=0/1/1900,"",VLOOKUP($A4,'8 Oct - LIVE LDS Data'!$A$3:$AAD$1504,10,FALSE)) -> 43083 | L4: =IF(VLOOKUP($A4,'8 Oct - LIVE LDS Data'!$A$3:$AAD$1504,34,FALSE)=0/1/1900,"",VLOOKUP($A4,'8 Oct - LIVE LDS Data'!$A$3:$AAD$1504,34,FALSE)) -> 45622 | M4: =IF(VLOOKUP($A4,'8 Oct - LIVE LDS Data'!$A$3:$AAD$1504,35,FALSE)=0/1/1900,"",VLOOKUP($A4,'8 Oct - LIVE LDS Data'!$A$3:$AAD$1504,35,FALSE)) -> 46027 | N4: =IF(VLOOKUP($A4,'8 Oct - LIVE LDS Data'!$A$3:$AAD$1504,41,FALSE)=0/1/1900,"",VLOOKUP($A4,'8 Oct - LIVE LDS Data'!$A$3:$AAD$1504,41,FALSE)) | O4: =IF(VLOOKUP($A4,'8 Oct - LIVE LDS Data'!$A$3:$AAD$1504,42,FALSE)=0/1/1900,"",VLOOKUP($A4,'8 Oct - LIVE LDS Data'!$A$3:$AAD$1504,42,FALSE)) | P4: =IF(VLOOKUP($A4,'8 Oct - LIVE LDS Data'!$A$3:$AAD$1504,48,FALSE)=0/1/1900,"",VLOOKUP($A4,'8 Oct - LIVE LDS Data'!$A$3:$AAD$1504,48,FALSE)) | Q4: =IF(VLOOKUP($A4,'8 Oct - LIVE LDS Data'!$A$3:$AAD$1504,49,FALSE)=0/1/1900,"",VLOOKUP($A4,'8 Oct - LIVE LDS Data'!$A$3:$AAD$1504,49,FALSE)) | R4: =IF(VLOOKUP($A4,'8 Oct - LIVE LDS Data'!$A$3:$AAD$1504,55,FALSE)=0/1/1900,"",VLOOKUP($A4,'8 Oct - LIVE LDS Data'!$A$3:$AAD$1504,55,FALSE)) | S4: =IF(VLOOKUP($A4,'8 Oct - LIVE LDS Data'!$A$3:$AAD$1504,56,FALSE)=0/1/1900,"",VLOOKUP($A4,'8 Oct - LIVE LDS Data'!$A$3:$AAD$1504,56,FALSE)) | T4: =IF(VLOOKUP($A4,'8 Oct - LIVE LDS Data'!$A$3:$AAD$1504,61,FALSE)=0/1/1900,"",VLOOKUP($A4,'8 Oct - LIVE LDS Data'!$A$3:$AAD$1504,61,FALSE)) | U4: =IF(VLOOKUP($A4,'8 Oct - LIVE LDS Data'!$A$3:$AAD$1504,64,FALSE)=0/1/1900,"",VLOOKUP($A4,'8 Oct - LIVE LDS Data'!$A$3:$AAD$1504,64,FALSE)) | V4: =IF(VLOOKUP($A4,'8 Oct - LIVE LDS Data'!$A$3:$AAD$1504,67,FALSE)=0/1/1900,"",VLOOKUP($A4,'8 Oct - LIVE LDS Data'!$A$3:$AAD$1504,67,FALSE)) | W4: =IF(VLOOKUP($A4,'8 Oct - LIVE LDS Data'!$A$3:$AAD$1504,80,FALSE)=0/1/1900,"",VLOOKUP($A4,'8 Oct - LIVE LDS Data'!$A$3:$AAD$1504,80,FALSE)) | X4: YES | Y4: =IF(VLOOKUP($A4,'8 Oct - LIVE LDS Data'!$A$3:$AAD$1504,73,FALSE)=0/1/1900,"",VLOOKUP($A4,'8 Oct - LIVE LDS Data'!$A$3:$AAD$1504,73,FALSE)) -> 45743 | Z4: =IF(VLOOKUP($A4,'8 Oct - LIVE LDS Data'!$A$3:$AAD$1504,74,FALSE)=0/1/1900,"",VLOOKUP($A4,'8 Oct - LIVE LDS Data'!$A$3:$AAD$1504,74,FALSE)) -> Shannon Franklin | AA4: =IF(VLOOKUP($A4,'8 Oct - LIVE LDS Data'!$A$3:$AAD$1504,76,FALSE)=0/1/1900,"",VLOOKUP($A4,'8 Oct - LIVE LDS Data'!$A$3:$AAD$1504,76,FALSE)) -> 45743 | AB4: =IF(VLOOKUP($A4,'8 Oct - LIVE LDS Data'!$A$3:$AAD$1504,77,FALSE)=0/1/1900,"",VLOOKUP($A4,'8 Oct - LIVE LDS Data'!$A$3:$AAD$1504,77,FALSE)) -> Shannon Franklin
A5: E07000224 | C5: Arun | F5: =IF(VLOOKUP($A5,'8 Oct - LIVE LDS Data'!$A$3:$AAD$1504,4,FALSE)=0/1/1900,"",VLOOKUP($A5,'8 Oct - LIVE LDS Data'!$A$3:$AAD$1504,4,FALSE)) -> Arun Local Plan Update 2023 - 2041 | G5: =IF(VLOOKUP($A5,'8 Oct - LIVE LDS Data'!$A$3:$AAD$1504,6,FALSE)=0/1/1900,"",VLOOKUP($A5,'8 Oct - LIVE LDS Data'!$A$3:$AAD$1504,6,FALSE)) -> 2023 | H5: =IF(VLOOKUP($A5,'8 Oct - LIVE LDS Data'!$A$3:$AAD$1504,7,FALSE)=0/1/1900,"",VLOOKUP($A5,'8 Oct - LIVE LDS Data'!$A$3:$AAD$1504,7,FALSE)) -> 2041 | I5: =IF(VLOOKUP($A5,'8 Oct - LIVE LDS Data'!$A$3:$AAD$1504,8,FALSE)=0/1/1900,"",VLOOKUP($A5,'8 Oct - LIVE LDS Data'!$A$3:$AAD$1504,8,FALSE)) -> N | J5: =IF(VLOOKUP($A5,'8 Oct - LIVE LDS Data'!$A$3:$AAD$1504,9,FALSE)=0/1/1900,"",VLOOKUP($A5,'8 Oct - LIVE LDS Data'!$A$3:$AAD$1504,9,FALSE)) -> N | K5: =IF(VLOOKUP($A5,'8 Oct - LIVE LDS Data'!$A$3:$AAD$1504,10,FALSE)=0/1/1900,"",VLOOKUP($A5,'8 Oct - LIVE LDS Data'!$A$3:$AAD$1504,10,FALSE)) -> 43299 | L5: =IF(VLOOKUP($A5,'8 Oct - LIVE LDS Data'!$A$3:$AAD$1504,34,FALSE)=0/1/1900,"",VLOOKUP($A5,'8 Oct - LIVE LDS Data'!$A$3:$AAD$1504,34,FALSE)) -> 45376 | M5: =IF(VLOOKUP($A5,'8 Oct - LIVE LDS Data'!$A$3:$AAD$1504,35,FALSE)=0/1/1900,"",VLOOKUP($A5,'8 Oct - LIVE LDS Data'!$A$3:$AAD$1504,35,FALSE)) -> 45536 | N5: =IF(VLOOKUP($A5,'8 Oct - LIVE LDS Data'!$A$3:$AAD$1504,41,FALSE)=0/1/1900,"",VLOOKUP($A5,'8 Oct - LIVE LDS Data'!$A$3:$AAD$1504,41,FALSE)) | O5: =IF(VLOOKUP($A5,'8 Oct - LIVE LDS Data'!$A$3:$AAD$1504,42,FALSE)=0/1/1900,"",VLOOKUP($A5,'8 Oct - LIVE LDS Data'!$A$3:$AAD$1504,42,FALSE)) | P5: =IF(VLOOKUP($A5,'8 Oct - LIVE LDS Data'!$A$3:$AAD$1504,48,FALSE)=0/1/1900,"",VLOOKUP($A5,'8 Oct - LIVE LDS Data'!$A$3:$AAD$1504,48,FALSE)) | Q5: =IF(VLOOKUP($A5,'8 Oct - LIVE LDS Data'!$A$3:$AAD$1504,49,FALSE)=0/1/1900,"",VLOOKUP($A5,'8 Oct - LIVE LDS Data'!$A$3:$AAD$1504,49,FALSE)) | R5: =IF(VLOOKUP($A5,'8 Oct - LIVE LDS Data'!$A$3:$AAD$1504,55,FALSE)=0/1/1900,"",VLOOKUP($A5,'8 Oct - LIVE LDS Data'!$A$3:$AAD$1504,55,FALSE)) | S5: =IF(VLOOKUP($A5,'8 Oct - LIVE LDS Data'!$A$3:$AAD$1504,56,FALSE)=0/1/1900,"",VLOOKUP($A5,'8 Oct - LIVE LDS Data'!$A$3:$AAD$1504,56,FALSE)) | T5: =IF(VLOOKUP($A5,'8 Oct - LIVE LDS Data'!$A$3:$AAD$1504,61,FALSE)=0/1/1900,"",VLOOKUP($A5,'8 Oct - LIVE LDS Data'!$A$3:$AAD$1504,61,FALSE)) | U5: =IF(VLOOKUP($A5,'8 Oct - LIVE LDS Data'!$A$3:$AAD$1504,64,FALSE)=0/1/1900,"",VLOOKUP($A5,'8 Oct - LIVE LDS Data'!$A$3:$AAD$1504,64,FALSE)) | V5: =IF(VLOOKUP($A5,'8 Oct - LIVE LDS Data'!$A$3:$AAD$1504,67,FALSE)=0/1/1900,"",VLOOKUP($A5,'8 Oct - LIVE LDS Data'!$A$3:$AAD$1504,67,FALSE)) | W5: =IF(VLOOKUP($A5,'8 Oct - LIVE LDS Data'!$A$3:$AAD$1504,80,FALSE)=0/1/1900,"",VLOOKUP($A5,'8 Oct - LIVE LDS Data'!$A$3:$AAD$1504,80,FALSE)) | X5: YES | Y5: =IF(VLOOKUP($A5,'8 Oct - LIVE LDS Data'!$A$3:$AAD$1504,73,FALSE)=0/1/1900,"",VLOOKUP($A5,'8 Oct - LIVE LDS Data'!$A$3:$AAD$1504,73,FALSE)) -> 45743 | Z5: =IF(VLOOKUP($A5,'8 Oct - LIVE LDS Data'!$A$3:$AAD$1504,74,FALSE)=0/1/1900,"",VLOOKUP($A5,'8 Oct - LIVE LDS Data'!$A$3:$AAD$1504,74,FALSE)) -> Shannon Franklin | AA5: =IF(VLOOKUP($A5,'8 Oct - LIVE LDS Data'!$A$3:$AAD$1504,76,FALSE)=0/1/1900,"",VLOOKUP($A5,'8 Oct - LIVE LDS Data'!$A$3:$AAD$1504,76,FALSE)) -> 45743 | AB5: =IF(VLOOKUP($A5,'8 Oct - LIVE LDS Data'!$A$3:$AAD$1504,77,FALSE)=0/1/1900,"",VLOOKUP($A5,'8 Oct - LIVE LDS Data'!$A$3:$AAD$1504,77,FALSE)) -> Shannon Franklin
A6: E07000105 | C6: Ashford | F6: =IF(VLOOKUP($A6,'8 Oct - LIVE LDS Data'!$A$3:$AAD$1504,4,FALSE)=0/1/1900,"",VLOOKUP($A6,'8 Oct - LIVE LDS Data'!$A$3:$AAD$1504,4,FALSE)) -> Ashford Local Plan 2042 | G6: =IF(VLOOKUP($A6,'8 Oct - LIVE LDS Data'!$A$3:$AAD$1504,6,FALSE)=0/1/1900,"",VLOOKUP($A6,'8 Oct - LIVE LDS Data'!$A$3:$AAD$1504,6,FALSE)) | H6: =IF(VLOOKUP($A6,'8 Oct - LIVE LDS Data'!$A$3:$AAD$1504,7,FALSE)=0/1/1900,"",VLOOKUP($A6,'8 Oct - LIVE LDS Data'!$A$3:$AAD$1504,7,FALSE)) -> 2042 | I6: =IF(VLOOKUP($A6,'8 Oct - LIVE LDS Data'!$A$3:$AAD$1504,8,FALSE)=0/1/1900,"",VLOOKUP($A6,'8 Oct - LIVE LDS Data'!$A$3:$AAD$1504,8,FALSE)) -> N | J6: =IF(VLOOKUP($A6,'8 Oct - LIVE LDS Data'!$A$3:$AAD$1504,9,FALSE)=0/1/1900,"",VLOOKUP($A6,'8 Oct - LIVE LDS Data'!$A$3:$AAD$1504,9,FALSE)) -> N | K6: =IF(VLOOKUP($A6,'8 Oct - LIVE LDS Data'!$A$3:$AAD$1504,10,FALSE)=0/1/1900,"",VLOOKUP($A6,'8 Oct - LIVE LDS Data'!$A$3:$AAD$1504,10,FALSE)) -> 43517 | L6: =IF(VLOOKUP($A6,'8 Oct - LIVE LDS Data'!$A$3:$AAD$1504,34,FALSE)=0/1/1900,"",VLOOKUP($A6,'8 Oct - LIVE LDS Data'!$A$3:$AAD$1504,34,FALSE)) -> 45887 | M6: =IF(VLOOKUP($A6,'8 Oct - LIVE LDS Data'!$A$3:$AAD$1504,35,FALSE)=0/1/1900,"",VLOOKUP($A6,'8 Oct - LIVE LDS Data'!$A$3:$AAD$1504,35,FALSE)) -> 45943 | N6: =IF(VLOOKUP($A6,'8 Oct - LIVE LDS Data'!$A$3:$AAD$1504,41,FALSE)=0/1/1900,"",VLOOKUP($A6,'8 Oct - LIVE LDS Data'!$A$3:$AAD$1504,41,FALSE)) | O6: =IF(VLOOKUP($A6,'8 Oct - LIVE LDS Data'!$A$3:$AAD$1504,42,FALSE)=0/1/1900,"",VLOOKUP($A6,'8 Oct - LIVE LDS Data'!$A$3:$AAD$1504,42,FALSE)) | P6: =IF(VLOOKUP($A6,'8 Oct - LIVE LDS Data'!$A$3:$AAD$1504,48,FALSE)=0/1/1900,"",VLOOKUP($A6,'8 Oct - LIVE LDS Data'!$A$3:$AAD$1504,48,FALSE)) | Q6: =IF(VLOOKUP($A6,'8 Oct - LIVE LDS Data'!$A$3:$AAD$1504,49,FALSE)=0/1/1900,"",VLOOKUP($A6,'8 Oct - LIVE LDS Data'!$A$3:$AAD$1504,49,FALSE)) | R6: =IF(VLOOKUP($A6,'8 Oct - LIVE LDS Data'!$A$3:$AAD$1504,55,FALSE)=0/1/1900,"",VLOOKUP($A6,'8 Oct - LIVE LDS Data'!$A$3:$AAD$1504,55,FALSE)) | S6: =IF(VLOOKUP($A6,'8 Oct - LIVE LDS Data'!$A$3:$AAD$1504,56,FALSE)=0/1/1900,"",VLOOKUP($A6,'8 Oct - LIVE LDS Data'!$A$3:$AAD$1504,56,FALSE)) | T6: =IF(VLOOKUP($A6,'8 Oct - LIVE LDS Data'!$A$3:$AAD$1504,61,FALSE)=0/1/1900,"",VLOOKUP($A6,'8 Oct - LIVE LDS Data'!$A$3:$AAD$1504,61,FALSE)) | U6: =IF(VLOOKUP($A6,'8 Oct - LIVE LDS Data'!$A$3:$AAD$1504,64,FALSE)=0/1/1900,"",VLOOKUP($A6,'8 Oct - LIVE LDS Data'!$A$3:$AAD$1504,64,FALSE)) | V6: =IF(VLOOKUP($A6,'8 Oct - LIVE LDS Data'!$A$3:$AAD$1504,67,FALSE)=0/1/1900,"",VLOOKUP($A6,'8 Oct - LIVE LDS Data'!$A$3:$AAD$1504,67,FALSE)) | W6: =IF(VLOOKUP($A6,'8 Oct - LIVE LDS Data'!$A$3:$AAD$1504,80,FALSE)=0/1/1900,"",VLOOKUP($A6,'8 Oct - LIVE LDS Data'!$A$3:$AAD$1504,80,FALSE)) | X6: YES | Y6: =IF(VLOOKUP($A6,'8 Oct - LIVE LDS Data'!$A$3:$AAD$1504,73,FALSE)=0/1/1900,"",VLOOKUP($A6,'8 Oct - LIVE LDS Data'!$A$3:$AAD$1504,73,FALSE)) -> 45743 | Z6: =IF(VLOOKUP($A6,'8 Oct - LIVE LDS Data'!$A$3:$AAD$1504,74,FALSE)=0/1/1900,"",VLOOKUP($A6,'8 Oct - LIVE LDS Data'!$A$3:$AAD$1504,74,FALSE)) -> Shannon Franklin | AA6: =IF(VLOOKUP($A6,'8 Oct - LIVE LDS Data'!$A$3:$AAD$1504,76,FALSE)=0/1/1900,"",VLOOKUP($A6,'8 Oct - LIVE LDS Data'!$A$3:$AAD$1504,76,FALSE)) -> 45918 | AB6: =IF(VLOOKUP($A6,'8 Oct - LIVE LDS Data'!$A$3:$AAD$1504,77,FALSE)=0/1/1900,"",VLOOKUP($A6,'8 Oct - LIVE LDS Data'!$A$3:$AAD$1504,77,FALSE)) -> Robert Putnam
A7: E07000004 | C7: Aylesbury Vale (defunct - now part of Buckinghamshire) | D7: YES (Buckinghamshire] | F7: =IF(VLOOKUP($A7,'8 Oct - LIVE LDS Data'!$A$3:$AAD$1504,4,FALSE)=0/1/1900,"",VLOOKUP($A7,'8 Oct - LIVE LDS Data'!$A$3:$AAD$1504,4,FALSE)) -> The Vale of Aylesbury Local Plan (VALP) | G7: =IF(VLOOKUP($A7,'8 Oct - LIVE LDS Data'!$A$3:$AAD$1504,6,FALSE)=0/1/1900,"",VLOOKUP($A7,'8 Oct - LIVE LDS Data'!$A$3:$AAD$1504,6,FALSE)) | H7: =IF(VLOOKUP($A7,'8 Oct - LIVE LDS Data'!$A$3:$AAD$1504,7,FALSE)=0/1/1900,"",VLOOKUP($A7,'8 Oct - LIVE LDS Data'!$A$3:$AAD$1504,7,FALSE)) | I7: =IF(VLOOKUP($A7,'8 Oct - LIVE LDS Data'!$A$3:$AAD$1504,8,FALSE)=0/1/1900,"",VLOOKUP($A7,'8 Oct - LIVE LDS Data'!$A$3:$AAD$1504,8,FALSE)) | J7: =IF(VLOOKUP($A7,'8 Oct - LIVE LDS Data'!$A$3:$AAD$1504,9,FALSE)=0/1/1900,"",VLOOKUP($A7,'8 Oct - LIVE LDS Data'!$A$3:$AAD$1504,9,FALSE)) | K7: =IF(VLOOKUP($A7,'8 Oct - LIVE LDS Data'!$A$3:$AAD$1504,10,FALSE)=0/1/1900,"",VLOOKUP($A7,'8 Oct - LIVE LDS Data'!$A$3:$AAD$1504,10,FALSE)) -> 44454 | L7: =IF(VLOOKUP($A7,'8 Oct - LIVE LDS Data'!$A$3:$AAD$1504,34,FALSE)=0/1/1900,"",VLOOKUP($A7,'8 Oct - LIVE LDS Data'!$A$3:$AAD$1504,34,FALSE)) | M7: =IF(VLOOKUP($A7,'8 Oct - LIVE LDS Data'!$A$3:$AAD$1504,35,FALSE)=0/1/1900,"",VLOOKUP($A7,'8 Oct - LIVE LDS Data'!$A$3:$AAD$1504,35,FALSE)) | N7: =IF(VLOOKUP($A7,'8 Oct - LIVE LDS Data'!$A$3:$AAD$1504,41,FALSE)=0/1/1900,"",VLOOKUP($A7,'8 Oct - LIVE LDS Data'!$A$3:$AAD$1504,41,FALSE)) | O7: =IF(VLOOKUP($A7,'8 Oct - LIVE LDS Data'!$A$3:$AAD$1504,42,FALSE)=0/1/1900,"",VLOOKUP($A7,'8 Oct - LIVE LDS Data'!$A$3:$AAD$1504,42,FALSE)) | P7: =IF(VLOOKUP($A7,'8 Oct - LIVE LDS Data'!$A$3:$AAD$1504,48,FALSE)=0/1/1900,"",VLOOKUP($A7,'8 Oct - LIVE LDS Data'!$A$3:$AAD$1504,48,FALSE)) | Q7: =IF(VLOOKUP($A7,'8 Oct - LIVE LDS Data'!$A$3:$AAD$1504,49,FALSE)=0/1/1900,"",VLOOKUP($A7,'8 Oct - LIVE LDS Data'!$A$3:$AAD$1504,49,FALSE)) | R7: =IF(VLOOKUP($A7,'8 Oct - LIVE LDS Data'!$A$3:$AAD$1504,55,FALSE)=0/1/1900,"",VLOOKUP($A7,'8 Oct - LIVE LDS Data'!$A$3:$AAD$1504,55,FALSE)) | S7: =IF(VLOOKUP($A7,'8 Oct - LIVE LDS Data'!$A$3:$AAD$1504,56,FALSE)=0/1/1900,"",VLOOKUP($A7,'8 Oct - LIVE LDS Data'!$A$3:$AAD$1504,56,FALSE)) | T7: =IF(VLOOKUP($A7,'8 Oct - LIVE LDS Data'!$A$3:$AAD$1504,61,FALSE)=0/1/1900,"",VLOOKUP($A7,'8 Oct - LIVE LDS Data'!$A$3:$AAD$1504,61,FALSE)) -> 43041 | U7: =IF(VLOOKUP($A7,'8 Oct - LIVE LDS Data'!$A$3:$AAD$1504,64,FALSE)=0/1/1900,"",VLOOKUP($A7,'8 Oct - LIVE LDS Data'!$A$3:$AAD$1504,64,FALSE)) -> 43159 | V7: =IF(VLOOKUP($A7,'8 Oct - LIVE LDS Data'!$A$3:$AAD$1504,67,FALSE)=0/1/1900,"",VLOOKUP($A7,'8 Oct - LIVE LDS Data'!$A$3:$AAD$1504,67,FALSE)) -> 44440 | W7: =IF(VLOOKUP($A7,'8 Oct - LIVE LDS Data'!$A$3:$AAD$1504,80,FALSE)=0/1/1900,"",VLOOKUP($A7,'8 Oct - LIVE LDS Data'!$A$3:$AAD$1504,80,FALSE)) | X7: YES | Y7: =IF(VLOOKUP($A7,'8 Oct - LIVE LDS Data'!$A$3:$AAD$1504,73,FALSE)=0/1/1900,"",VLOOKUP($A7,'8 Oct - LIVE LDS Data'!$A$3:$AAD$1504,73,FALSE)) | Z7: =IF(VLOOKUP($A7,'8 Oct - LIVE LDS Data'!$A$3:$AAD$1504,74,FALSE)=0/1/1900,"",VLOOKUP($A7,'8 Oct - LIVE LDS Data'!$A$3:$AAD$1504,74,FALSE)) -> Robert Putnam | AA7: =IF(VLOOKUP($A7,'8 Oct - LIVE LDS Data'!$A$3:$AAD$1504,76,FALSE)=0/1/1900,"",VLOOKUP($A7,'8 Oct - LIVE LDS Data'!$A$3:$AAD$1504,76,FALSE)) | AB7: =IF(VLOOKUP($A7,'8 Oct - LIVE LDS Data'!$A$3:$AAD$1504,77,FALSE)=0/1/1900,"",VLOOKUP($A7,'8 Oct - LIVE LDS Data'!$A$3:$AAD$1504,77,FALSE))
A8: E08000016 | C8: Barnsley | F8: =IF(VLOOKUP($A8,'8 Oct - LIVE LDS Data'!$A$3:$AAD$1504,4,FALSE)=0/1/1900,"",VLOOKUP($A8,'8 Oct - LIVE LDS Data'!$A$3:$AAD$1504,4,FALSE)) -> new system | G8: =IF(VLOOKUP($A8,'8 Oct - LIVE LDS Data'!$A$3:$AAD$1504,6,FALSE)=0/1/1900,"",VLOOKUP($A8,'8 Oct - LIVE LDS Data'!$A$3:$AAD$1504,6,FALSE)) | H8: =IF(VLOOKUP($A8,'8 Oct - LIVE LDS Data'!$A$3:$AAD$1504,7,FALSE)=0/1/1900,"",VLOOKUP($A8,'8 Oct - LIVE LDS Data'!$A$3:$AAD$1504,7,FALSE)) | I8: =IF(VLOOKUP($A8,'8 Oct - LIVE LDS Data'!$A$3:$AAD$1504,8,FALSE)=0/1/1900,"",VLOOKUP($A8,'8 Oct - LIVE LDS Data'!$A$3:$AAD$1504,8,FALSE)) | J8: =IF(VLOOKUP($A8,'8 Oct - LIVE LDS Data'!$A$3:$AAD$1504,9,FALSE)=0/1/1900,"",VLOOKUP($A8,'8 Oct - LIVE LDS Data'!$A$3:$AAD$1504,9,FALSE)) | K8: =IF(VLOOKUP($A8,'8 Oct - LIVE LDS Data'!$A$3:$AAD$1504,10,FALSE)=0/1/1900,"",VLOOKUP($A8,'8 Oct - LIVE LDS Data'!$A$3:$AAD$1504,10,FALSE)) -> 43468 | L8: =IF(VLOOKUP($A8,'8 Oct - LIVE LDS Data'!$A$3:$AAD$1504,34,FALSE)=0/1/1900,"",VLOOKUP($A8,'8 Oct - LIVE LDS Data'!$A$3:$AAD$1504,34,FALSE)) | M8: =IF(VLOOKUP($A8,'8 Oct - LIVE LDS Data'!$A$3:$AAD$1504,35,FALSE)=0/1/1900,"",VLOOKUP($A8,'8 Oct - LIVE LDS Data'!$A$3:$AAD$1504,35,FALSE)) | N8: =IF(VLOOKUP($A8,'8 Oct - LIVE LDS Data'!$A$3:$AAD$1504,41,FALSE)=0/1/1900,"",VLOOKUP($A8,'8 Oct - LIVE LDS Data'!$A$3:$AAD$1504,41,FALSE)) | O8: =IF(VLOOKUP($A8,'8 Oct - LIVE LDS Data'!$A$3:$AAD$1504,42,FALSE)=0/1/1900,"",VLOOKUP($A8,'8 Oct - LIVE LDS Data'!$A$3:$AAD$1504,42,FALSE)) | P8: =IF(VLOOKUP($A8,'8 Oct - LIVE LDS Data'!$A$3:$AAD$1504,48,FALSE)=0/1/1900,"",VLOOKUP($A8,'8 Oct - LIVE LDS Data'!$A$3:$AAD$1504,48,FALSE)) | Q8: =IF(VLOOKUP($A8,'8 Oct - LIVE LDS Data'!$A$3:$AAD$1504,49,FALSE)=0/1/1900,"",VLOOKUP($A8,'8 Oct - LIVE LDS Data'!$A$3:$AAD$1504,49,FALSE)) | R8: =IF(VLOOKUP($A8,'8 Oct - LIVE LDS Data'!$A$3:$AAD$1504,55,FALSE)=0/1/1900,"",VLOOKUP($A8,'8 Oct - LIVE LDS Data'!$A$3:$AAD$1504,55,FALSE)) | S8: =IF(VLOOKUP($A8,'8 Oct - LIVE LDS Data'!$A$3:$AAD$1504,56,FALSE)=0/1/1900,"",VLOOKUP($A8,'8 Oct - LIVE LDS Data'!$A$3:$AAD$1504,56,FALSE)) | T8: =IF(VLOOKUP($A8,'8 Oct - LIVE LDS Data'!$A$3:$AAD$1504,61,FALSE)=0/1/1900,"",VLOOKUP($A8,'8 Oct - LIVE LDS Data'!$A$3:$AAD$1504,61,FALSE)) | U8: =IF(VLOOKUP($A8,'8 Oct - LIVE LDS Data'!$A$3:$AAD$1504,64,FALSE)=0/1/1900,"",VLOOKUP($A8,'8 Oct - LIVE LDS Data'!$A$3:$AAD$1504,64,FALSE)) | V8: =IF(VLOOKUP($A8,'8 Oct - LIVE LDS Data'!$A$3:$AAD$1504,67,FALSE)=0/1/1900,"",VLOOKUP($A8,'8 Oct - LIVE LDS Data'!$A$3:$AAD$1504,67,FALSE)) | W8: =IF(VLOOKUP($A8,'8 Oct - LIVE LDS Data'!$A$3:$AAD$1504,80,FALSE)=0/1/1900,"",VLOOKUP($A8,'8 Oct - LIVE LDS Data'!$A$3:$AAD$1504,80,FALSE)) | X8: YES | Y8: =IF(VLOOKUP($A8,'8 Oct - LIVE LDS Data'!$A$3:$AAD$1504,73,FALSE)=0/1/1900,"",VLOOKUP($A8,'8 Oct - LIVE LDS Data'!$A$3:$AAD$1504,73,FALSE)) | Z8: =IF(VLOOKUP($A8,'8 Oct - LIVE LDS Data'!$A$3:$AAD$1504,74,FALSE)=0/1/1900,"",VLOOKUP($A8,'8 Oct - LIVE LDS Data'!$A$3:$AAD$1504,74,FALSE)) -> Robert Putnam | AA8: =IF(VLOOKUP($A8,'8 Oct - LIVE LDS Data'!$A$3:$AAD$1504,76,FALSE)=0/1/1900,"",VLOOKUP($A8,'8 Oct - LIVE LDS Data'!$A$3:$AAD$1504,76,FALSE)) | AB8: =IF(VLOOKUP($A8,'8 Oct - LIVE LDS Data'!$A$3:$AAD$1504,77,FALSE)=0/1/1900,"",VLOOKUP($A8,'8 Oct - LIVE LDS Data'!$A$3:$AAD$1504,77,FALSE)) -> Robert Putnam
A9: E07000027 | C9: Barrow-in-Furness (defunct - now part of Westmorland and Furness) | D9: YES [Westmorland & Furness] | F9: =IF(VLOOKUP($A9,'8 Oct - LIVE LDS Data'!$A$3:$AAD$1504,4,FALSE)=0/1/1900,"",VLOOKUP($A9,'8 Oct - LIVE LDS Data'!$A$3:$AAD$1504,4,FALSE)) -> Barrow Borough Council Local Plan | G9: =IF(VLOOKUP($A9,'8 Oct - LIVE LDS Data'!$A$3:$AAD$1504,6,FALSE)=0/1/1900,"",VLOOKUP($A9,'8 Oct - LIVE LDS Data'!$A$3:$AAD$1504,6,FALSE)) | H9: =IF(VLOOKUP($A9,'8 Oct - LIVE LDS Data'!$A$3:$AAD$1504,7,FALSE)=0/1/1900,"",VLOOKUP($A9,'8 Oct - LIVE LDS Data'!$A$3:$AAD$1504,7,FALSE)) | I9: =IF(VLOOKUP($A9,'8 Oct - LIVE LDS Data'!$A$3:$AAD$1504,8,FALSE)=0/1/1900,"",VLOOKUP($A9,'8 Oct - LIVE LDS Data'!$A$3:$AAD$1504,8,FALSE)) | J9: =IF(VLOOKUP($A9,'8 Oct - LIVE LDS Data'!$A$3:$AAD$1504,9,FALSE)=0/1/1900,"",VLOOKUP($A9,'8 Oct - LIVE LDS Data'!$A$3:$AAD$1504,9,FALSE)) | K9: =IF(VLOOKUP($A9,'8 Oct - LIVE LDS Data'!$A$3:$AAD$1504,10,FALSE)=0/1/1900,"",VLOOKUP($A9,'8 Oct - LIVE LDS Data'!$A$3:$AAD$1504,10,FALSE)) -> 43620 | L9: =IF(VLOOKUP($A9,'8 Oct - LIVE LDS Data'!$A$3:$AAD$1504,34,FALSE)=0/1/1900,"",VLOOKUP($A9,'8 Oct - LIVE LDS Data'!$A$3:$AAD$1504,34,FALSE)) | M9: =IF(VLOOKUP($A9,'8 Oct - LIVE LDS Data'!$A$3:$AAD$1504,35,FALSE)=0/1/1900,"",VLOOKUP($A9,'8 Oct - LIVE LDS Data'!$A$3:$AAD$1504,35,FALSE)) | N9: =IF(VLOOKUP($A9,'8 Oct - LIVE LDS Data'!$A$3:$AAD$1504,41,FALSE)=0/1/1900,"",VLOOKUP($A9,'8 Oct - LIVE LDS Data'!$A$3:$AAD$1504,41,FALSE)) | O9: =IF(VLOOKUP($A9,'8 Oct - LIVE LDS Data'!$A$3:$AAD$1504,42,FALSE)=0/1/1900,"",VLOOKUP($A9,'8 Oct - LIVE LDS Data'!$A$3:$AAD$1504,42,FALSE)) | P9: =IF(VLOOKUP($A9,'8 Oct - LIVE LDS Data'!$A$3:$AAD$1504,48,FALSE)=0/1/1900,"",VLOOKUP($A9,'8 Oct - LIVE LDS Data'!$A$3:$AAD$1504,48,FALSE)) | Q9: =IF(VLOOKUP($A9,'8 Oct - LIVE LDS Data'!$A$3:$AAD$1504,49,FALSE)=0/1/1900,"",VLOOKUP($A9,'8 Oct - LIVE LDS Data'!$A$3:$AAD$1504,49,FALSE)) | R9: =IF(VLOOKUP($A9,'8 Oct - LIVE LDS Data'!$A$3:$AAD$1504,55,FALSE)=0/1/1900,"",VLOOKUP($A9,'8 Oct - LIVE LDS Data'!$A$3:$AAD$1504,55,FALSE)) | S9: =IF(VLOOKUP($A9,'8 Oct - LIVE LDS Data'!$A$3:$AAD$1504,56,FALSE)=0/1/1900,"",VLOOKUP($A9,'8 Oct - LIVE LDS Data'!$A$3:$AAD$1504,56,FALSE)) | T9: =IF(VLOOKUP($A9,'8 Oct - LIVE LDS Data'!$A$3:$AAD$1504,61,FALSE)=0/1/1900,"",VLOOKUP($A9,'8 Oct - LIVE LDS Data'!$A$3:$AAD$1504,61,FALSE)) | U9: =IF(VLOOKUP($A9,'8 Oct - LIVE LDS Data'!$A$3:$AAD$1504,64,FALSE)=0/1/1900,"",VLOOKUP($A9,'8 Oct - LIVE LDS Data'!$A$3:$AAD$1504,64,FALSE)) | V9: =IF(VLOOKUP($A9,'8 Oct - LIVE LDS Data'!$A$3:$AAD$1504,67,FALSE)=0/1/1900,"",VLOOKUP($A9,'8 Oct - LIVE LDS Data'!$A$3:$AAD$1504,67,FALSE)) | W9: =IF(VLOOKUP($A9,'8 Oct - LIVE LDS Data'!$A$3:$AAD$1504,80,FALSE)=0/1/1900,"",VLOOKUP($A9,'8 Oct - LIVE LDS Data'!$A$3:$AAD$1504,80,FALSE)) | X9: YES | Y9: =IF(VLOOKUP($A9,'8 Oct - LIVE LDS Data'!$A$3:$AAD$1504,73,FALSE)=0/1/1900,"",VLOOKUP($A9,'8 Oct - LIVE LDS Data'!$A$3:$AAD$1504,73,FALSE)) | Z9: =IF(VLOOKUP($A9,'8 Oct - LIVE LDS Data'!$A$3:$AAD$1504,74,FALSE)=0/1/1900,"",VLOOKUP($A9,'8 Oct - LIVE LDS Data'!$A$3:$AAD$1504,74,FALSE)) -> Robert Putnam | AA9: =IF(VLOOKUP($A9,'8 Oct - LIVE LDS Data'!$A$3:$AAD$1504,76,FALSE)=0/1/1900,"",VLOOKUP($A9,'8 Oct - LIVE LDS Data'!$A$3:$AAD$1504,76,FALSE)) | AB9: =IF(VLOOKUP($A9,'8 Oct - LIVE LDS Data'!$A$3:$AAD$1504,77,FALSE)=0/1/1900,"",VLOOKUP($A9,'8 Oct - LIVE LDS Data'!$A$3:$AAD$1504,77,FALSE))
A10: E07000066 | C10: Basildon | F10: =IF(VLOOKUP($A10,'8 Oct - LIVE LDS Data'!$A$3:$AAD$1504,4,FALSE)=0/1/1900,"",VLOOKUP($A10,'8 Oct - LIVE LDS Data'!$A$3:$AAD$1504,4,FALSE)) -> New Local Plan (previous emerging plan withdrawn from examination) | G10: =IF(VLOOKUP($A10,'8 Oct - LIVE LDS Data'!$A$3:$AAD$1504,6,FALSE)=0/1/1900,"",VLOOKUP($A10,'8 Oct - LIVE LDS Data'!$A$3:$AAD$1504,6,FALSE)) -> 2023 | H10: =IF(VLOOKUP($A10,'8 Oct - LIVE LDS Data'!$A$3:$AAD$1504,7,FALSE)=0/1/1900,"",VLOOKUP($A10,'8 Oct - LIVE LDS Data'!$A$3:$AAD$1504,7,FALSE)) -> 2043 | I10: =IF(VLOOKUP($A10,'8 Oct - LIVE LDS Data'!$A$3:$AAD$1504,8,FALSE)=0/1/1900,"",VLOOKUP($A10,'8 Oct - LIVE LDS Data'!$A$3:$AAD$1504,8,FALSE)) -> N | J10: =IF(VLOOKUP($A10,'8 Oct - LIVE LDS Data'!$A$3:$AAD$1504,9,FALSE)=0/1/1900,"",VLOOKUP($A10,'8 Oct - LIVE LDS Data'!$A$3:$AAD$1504,9,FALSE)) -> N | K10: =IF(VLOOKUP($A10,'8 Oct - LIVE LDS Data'!$A$3:$AAD$1504,10,FALSE)=0/1/1900,"",VLOOKUP($A10,'8 Oct - LIVE LDS Data'!$A$3:$AAD$1504,10,FALSE)) -> none | L10: =IF(VLOOKUP($A10,'8 Oct - LIVE LDS Data'!$A$3:$AAD$1504,34,FALSE)=0/1/1900,"",VLOOKUP($A10,'8 Oct - LIVE LDS Data'!$A$3:$AAD$1504,34,FALSE)) -> 45104 | M10: =IF(VLOOKUP($A10,'8 Oct - LIVE LDS Data'!$A$3:$AAD$1504,35,FALSE)=0/1/1900,"",VLOOKUP($A10,'8 Oct - LIVE LDS Data'!$A$3:$AAD$1504,35,FALSE)) -> 45174 | N10: =IF(VLOOKUP($A10,'8 Oct - LIVE LDS Data'!$A$3:$AAD$1504,41,FALSE)=0/1/1900,"",VLOOKUP($A10,'8 Oct - LIVE LDS Data'!$A$3:$AAD$1504,41,FALSE)) -> 45597 | O10: =IF(VLOOKUP($A10,'8 Oct - LIVE LDS Data'!$A$3:$AAD$1504,42,FALSE)=0/1/1900,"",VLOOKUP($A10,'8 Oct - LIVE LDS Data'!$A$3:$AAD$1504,42,FALSE)) -> 45658 | P10: =IF(VLOOKUP($A10,'8 Oct - LIVE LDS Data'!$A$3:$AAD$1504,48,FALSE)=0/1/1900,"",VLOOKUP($A10,'8 Oct - LIVE LDS Data'!$A$3:$AAD$1504,48,FALSE)) -> 45719 | Q10: =IF(VLOOKUP($A10,'8 Oct - LIVE LDS Data'!$A$3:$AAD$1504,49,FALSE)=0/1/1900,"",VLOOKUP($A10,'8 Oct - LIVE LDS Data'!$A$3:$AAD$1504,49,FALSE)) -> 45761 | R10: =IF(VLOOKUP($A10,'8 Oct - LIVE LDS Data'!$A$3:$AAD$1504,55,FALSE)=0/1/1900,"",VLOOKUP($A10,'8 Oct - LIVE LDS Data'!$A$3:$AAD$1504,55,FALSE)) | S10: =IF(VLOOKUP($A10,'8 Oct - LIVE LDS Data'!$A$3:$AAD$1504,56,FALSE)=0/1/1900,"",VLOOKUP($A10,'8 Oct - LIVE LDS Data'!$A$3:$AAD$1504,56,FALSE)) | T10: =IF(VLOOKUP($A10,'8 Oct - LIVE LDS Data'!$A$3:$AAD$1504,61,FALSE)=0/1/1900,"",VLOOKUP($A10,'8 Oct - LIVE LDS Data'!$A$3:$AAD$1504,61,FALSE)) | U10: =IF(VLOOKUP($A10,'8 Oct - LIVE LDS Data'!$A$3:$AAD$1504,64,FALSE)=0/1/1900,"",VLOOKUP($A10,'8 Oct - LIVE LDS Data'!$A$3:$AAD$1504,64,FALSE)) | V10: =IF(VLOOKUP($A10,'8 Oct - LIVE LDS Data'!$A$3:$AAD$1504,67,FALSE)=0/1/1900,"",VLOOKUP($A10,'8 Oct - LIVE LDS Data'!$A$3:$AAD$1504,67,FALSE)) | W10: =IF(VLOOKUP($A10,'8 Oct - LIVE LDS Data'!$A$3:$AAD$1504,80,FALSE)=0/1/1900,"",VLOOKUP($A10,'8 Oct - LIVE LDS Data'!$A$3:$AAD$1504,80,FALSE)) | X10: YES | Y10: =IF(VLOOKUP($A10,'8 Oct - LIVE LDS Data'!$A$3:$AAD$1504,73,FALSE)=0/1/1900,"",VLOOKUP($A10,'8 Oct - LIVE LDS Data'!$A$3:$AAD$1504,73,FALSE)) -> 45743 | Z10: =IF(VLOOKUP($A10,'8 Oct - LIVE LDS Data'!$A$3:$AAD$1504,74,FALSE)=0/1/1900,"",VLOOKUP($A10,'8 Oct - LIVE LDS Data'!$A$3:$AAD$1504,74,FALSE)) -> Shannon Franklin | AA10: =IF(VLOOKUP($A10,'8 Oct - LIVE LDS Data'!$A$3:$AAD$1504,76,FALSE)=0/1/1900,"",VLOOKUP($A10,'8 Oct - LIVE LDS Data'!$A$3:$AAD$1504,76,FALSE)) -> 45740 | AB10: =IF(VLOOKUP($A10,'8 Oct - LIVE LDS Data'!$A$3:$AAD$1504,77,FALSE)=0/1/1900,"",VLOOKUP($A10,'8 Oct - LIVE LDS Data'!$A$3:$AAD$1504,77,FALSE)) -> Robert Putnam
A11: E07000084 | C11: Basingstoke and Deane | F11: =IF(VLOOKUP($A11,'8 Oct - LIVE LDS Data'!$A$3:$AAD$1504,4,FALSE)=0/1/1900,"",VLOOKUP($A11,'8 Oct - LIVE LDS Data'!$A$3:$AAD$1504,4,FALSE)) -> Local Plan | G11: =IF(VLOOKUP($A11,'8 Oct - LIVE LDS Data'!$A$3:$AAD$1504,6,FALSE)=0/1/1900,"",VLOOKUP($A11,'8 Oct - LIVE LDS Data'!$A$3:$AAD$1504,6,FALSE)) -> 2021 | H11: =IF(VLOOKUP($A11,'8 Oct - LIVE LDS Data'!$A$3:$AAD$1504,7,FALSE)=0/1/1900,"",VLOOKUP($A11,'8 Oct - LIVE LDS Data'!$A$3:$AAD$1504,7,FALSE)) -> 2040 | I11: =IF(VLOOKUP($A11,'8 Oct - LIVE LDS Data'!$A$3:$AAD$1504,8,FALSE)=0/1/1900,"",VLOOKUP($A11,'8 Oct - LIVE LDS Data'!$A$3:$AAD$1504,8,FALSE)) -> N | J11: =IF(VLOOKUP($A11,'8 Oct - LIVE LDS Data'!$A$3:$AAD$1504,9,FALSE)=0/1/1900,"",VLOOKUP($A11,'8 Oct - LIVE LDS Data'!$A$3:$AAD$1504,9,FALSE)) -> N | K11: =IF(VLOOKUP($A11,'8 Oct - LIVE LDS Data'!$A$3:$AAD$1504,10,FALSE)=0/1/1900,"",VLOOKUP($A11,'8 Oct - LIVE LDS Data'!$A$3:$AAD$1504,10,FALSE)) -> 42516 | L11: =IF(VLOOKUP($A11,'8 Oct - LIVE LDS Data'!$A$3:$AAD$1504,34,FALSE)=0/1/1900,"",VLOOKUP($A11,'8 Oct - LIVE LDS Data'!$A$3:$AAD$1504,34,FALSE)) -> 45313 | M11: =IF(VLOOKUP($A11,'8 Oct - LIVE LDS Data'!$A$3:$AAD$1504,35,FALSE)=0/1/1900,"",VLOOKUP($A11,'8 Oct - LIVE LDS Data'!$A$3:$AAD$1504,35,FALSE)) -> 45355 | N11: =IF(VLOOKUP($A11,'8 Oct - LIVE LDS Data'!$A$3:$AAD$1504,41,FALSE)=0/1/1900,"",VLOOKUP($A11,'8 Oct - LIVE LDS Data'!$A$3:$AAD$1504,41,FALSE)) | O11: =IF(VLOOKUP($A11,'8 Oct - LIVE LDS Data'!$A$3:$AAD$1504,42,FALSE)=0/1/1900,"",VLOOKUP($A11,'8 Oct - LIVE LDS Data'!$A$3:$AAD$1504,42,FALSE)) | P11: =IF(VLOOKUP($A11,'8 Oct - LIVE LDS Data'!$A$3:$AAD$1504,48,FALSE)=0/1/1900,"",VLOOKUP($A11,'8 Oct - LIVE LDS Data'!$A$3:$AAD$1504,48,FALSE)) | Q11: =IF(VLOOKUP($A11,'8 Oct - LIVE LDS Data'!$A$3:$AAD$1504,49,FALSE)=0/1/1900,"",VLOOKUP($A11,'8 Oct - LIVE LDS Data'!$A$3:$AAD$1504,49,FALSE)) | R11: =IF(VLOOKUP($A11,'8 Oct - LIVE LDS Data'!$A$3:$AAD$1504,55,FALSE)=0/1/1900,"",VLOOKUP($A11,'8 Oct - LIVE LDS Data'!$A$3:$AAD$1504,55,FALSE)) | S11: =IF(VLOOKUP($A11,'8 Oct - LIVE LDS Data'!$A$3:$AAD$1504,56,FALSE)=0/1/1900,"",VLOOKUP($A11,'8 Oct - LIVE LDS Data'!$A$3:$AAD$1504,56,FALSE)) | T11: =IF(VLOOKUP($A11,'8 Oct - LIVE LDS Data'!$A$3:$AAD$1504,61,FALSE)=0/1/1900,"",VLOOKUP($A11,'8 Oct - LIVE LDS Data'!$A$3:$AAD$1504,61,FALSE)) | U11: =IF(VLOOKUP($A11,'8 Oct - LIVE LDS Data'!$A$3:$AAD$1504,64,FALSE)=0/1/1900,"",VLOOKUP($A11,'8 Oct - LIVE LDS Data'!$A$3:$AAD$1504,64,FALSE)) | V11: =IF(VLOOKUP($A11,'8 Oct - LIVE LDS Data'!$A$3:$AAD$1504,67,FALSE)=0/1/1900,"",VLOOKUP($A11,'8 Oct - LIVE LDS Data'!$A$3:$AAD$1504,67,FALSE)) | W11: =IF(VLOOKUP($A11,'8 Oct - LIVE LDS Data'!$A$3:$AAD$1504,80,FALSE)=0/1/1900,"",VLOOKUP($A11,'8 Oct - LIVE LDS Data'!$A$3:$AAD$1504,80,FALSE)) | X11: YES | Y11: =IF(VLOOKUP($A11,'8 Oct - LIVE LDS Data'!$A$3:$AAD$1504,73,FALSE)=0/1/1900,"",VLOOKUP($A11,'8 Oct - LIVE LDS Data'!$A$3:$AAD$1504,73,FALSE)) -> 45743 | Z11: =IF(VLOOKUP($A11,'8 Oct - LIVE LDS Data'!$A$3:$AAD$1504,74,FALSE)=0/1/1900,"",VLOOKUP($A11,'8 Oct - LIVE LDS Data'!$A$3:$AAD$1504,74,FALSE)) -> Shannon Franklin | AA11: =IF(VLOOKUP($A11,'8 Oct - LIVE LDS Data'!$A$3:$AAD$1504,76,FALSE)=0/1/1900,"",VLOOKUP($A11,'8 Oct - LIVE LDS Data'!$A$3:$AAD$1504,76,FALSE)) -> 45743 | AB11: =IF(VLOOKUP($A11,'8 Oct - LIVE LDS Data'!$A$3:$AAD$1504,77,FALSE)=0/1/1900,"",VLOOKUP($A11,'8 Oct - LIVE LDS Data'!$A$3:$AAD$1504,77,FALSE)) -> Shannon Franklin
A12: E06000022 | C12: Bath & North East Somerset | F12: =IF(VLOOKUP($A12,'8 Oct - LIVE LDS Data'!$A$3:$AAD$1504,4,FALSE)=0/1/1900,"",VLOOKUP($A12,'8 Oct - LIVE LDS Data'!$A$3:$AAD$1504,4,FALSE)) -> Bath and North East Somerset Council New Local Plan (2022-2042) | G12: =IF(VLOOKUP($A12,'8 Oct - LIVE LDS Data'!$A$3:$AAD$1504,6,FALSE)=0/1/1900,"",VLOOKUP($A12,'8 Oct - LIVE LDS Data'!$A$3:$AAD$1504,6,FALSE)) -> 2022 | H12: =IF(VLOOKUP($A12,'8 Oct - LIVE LDS Data'!$A$3:$AAD$1504,7,FALSE)=0/1/1900,"",VLOOKUP($A12,'8 Oct - LIVE LDS Data'!$A$3:$AAD$1504,7,FALSE)) -> 2042 | I12: =IF(VLOOKUP($A12,'8 Oct - LIVE LDS Data'!$A$3:$AAD$1504,8,FALSE)=0/1/1900,"",VLOOKUP($A12,'8 Oct - LIVE LDS Data'!$A$3:$AAD$1504,8,FALSE)) -> N | J12: =IF(VLOOKUP($A12,'8 Oct - LIVE LDS Data'!$A$3:$AAD$1504,9,FALSE)=0/1/1900,"",VLOOKUP($A12,'8 Oct - LIVE LDS Data'!$A$3:$AAD$1504,9,FALSE)) -> N | K12: =IF(VLOOKUP($A12,'8 Oct - LIVE LDS Data'!$A$3:$AAD$1504,10,FALSE)=0/1/1900,"",VLOOKUP($A12,'8 Oct - LIVE LDS Data'!$A$3:$AAD$1504,10,FALSE)) -> 10 July 2014 (as amended by partial update on 19 Jan 2023) | L12: =IF(VLOOKUP($A12,'8 Oct - LIVE LDS Data'!$A$3:$AAD$1504,34,FALSE)=0/1/1900,"",VLOOKUP($A12,'8 Oct - LIVE LDS Data'!$A$3:$AAD$1504,34,FALSE)) -> 44838 | M12: =IF(VLOOKUP($A12,'8 Oct - LIVE LDS Data'!$A$3:$AAD$1504,35,FALSE)=0/1/1900,"",VLOOKUP($A12,'8 Oct - LIVE LDS Data'!$A$3:$AAD$1504,35,FALSE)) -> 44880 | N12: =IF(VLOOKUP($A12,'8 Oct - LIVE LDS Data'!$A$3:$AAD$1504,41,FALSE)=0/1/1900,"",VLOOKUP($A12,'8 Oct - LIVE LDS Data'!$A$3:$AAD$1504,41,FALSE)) -> 45334 | O12: =IF(VLOOKUP($A12,'8 Oct - LIVE LDS Data'!$A$3:$AAD$1504,42,FALSE)=0/1/1900,"",VLOOKUP($A12,'8 Oct - LIVE LDS Data'!$A$3:$AAD$1504,42,FALSE)) -> 45390 | P12: =IF(VLOOKUP($A12,'8 Oct - LIVE LDS Data'!$A$3:$AAD$1504,48,FALSE)=0/1/1900,"",VLOOKUP($A12,'8 Oct - LIVE LDS Data'!$A$3:$AAD$1504,48,FALSE)) | Q12: =IF(VLOOKUP($A12,'8 Oct - LIVE LDS Data'!$A$3:$AAD$1504,49,FALSE)=0/1/1900,"",VLOOKUP($A12,'8 Oct - LIVE LDS Data'!$A$3:$AAD$1504,49,FALSE)) | R12: =IF(VLOOKUP($A12,'8 Oct - LIVE LDS Data'!$A$3:$AAD$1504,55,FALSE)=0/1/1900,"",VLOOKUP($A12,'8 Oct - LIVE LDS Data'!$A$3:$AAD$1504,55,FALSE)) | S12: =IF(VLOOKUP($A12,'8 Oct - LIVE LDS Data'!$A$3:$AAD$1504,56,FALSE)=0/1/1900,"",VLOOKUP($A12,'8 Oct - LIVE LDS Data'!$A$3:$AAD$1504,56,FALSE)) | T12: =IF(VLOOKUP($A12,'8 Oct - LIVE LDS Data'!$A$3:$AAD$1504,61,FALSE)=0/1/1900,"",VLOOKUP($A12,'8 Oct - LIVE LDS Data'!$A$3:$AAD$1504,61,FALSE)) | U12: =IF(VLOOKUP($A12,'8 Oct - LIVE LDS Data'!$A$3:$AAD$1504,64,FALSE)=0/1/1900,"",VLOOKUP($A12,'8 Oct - LIVE LDS Data'!$A$3:$AAD$1504,64,FALSE)) | V12: =IF(VLOOKUP($A12,'8 Oct - LIVE LDS Data'!$A$3:$AAD$1504,67,FALSE)=0/1/1900,"",VLOOKUP($A12,'8 Oct - LIVE LDS Data'!$A$3:$AAD$1504,67,FALSE)) | W12: =IF(VLOOKUP($A12,'8 Oct - LIVE LDS Data'!$A$3:$AAD$1504,80,FALSE)=0/1/1900,"",VLOOKUP($A12,'8 Oct - LIVE LDS Data'!$A$3:$AAD$1504,80,FALSE)) | X12: YES | Y12: =IF(VLOOKUP($A12,'8 Oct - LIVE LDS Data'!$A$3:$AAD$1504,73,FALSE)=0/1/1900,"",VLOOKUP($A12,'8 Oct - LIVE LDS Data'!$A$3:$AAD$1504,73,FALSE)) -> 45659 | Z12: =IF(VLOOKUP($A12,'8 Oct - LIVE LDS Data'!$A$3:$AAD$1504,74,FALSE)=0/1/1900,"",VLOOKUP($A12,'8 Oct - LIVE LDS Data'!$A$3:$AAD$1504,74,FALSE)) -> Robert Putnam | AA12: =IF(VLOOKUP($A12,'8 Oct - LIVE LDS Data'!$A$3:$AAD$1504,76,FALSE)=0/1/1900,"",VLOOKUP($A12,'8 Oct - LIVE LDS Data'!$A$3:$AAD$1504,76,FALSE)) -> 45659 | AB12: =IF(VLOOKUP($A12,'8 Oct - LIVE LDS Data'!$A$3:$AAD$1504,77,FALSE)=0/1/1900,"",VLOOKUP($A12,'8 Oct - LIVE LDS Data'!$A$3:$AAD$1504,77,FALSE)) -> Robert Putnam
A13: E08000025 | C13: Birmingham | F13: =IF(VLOOKUP($A13,'8 Oct - LIVE LDS Data'!$A$3:$AAD$1504,4,FALSE)=0/1/1900,"",VLOOKUP($A13,'8 Oct - LIVE LDS Data'!$A$3:$AAD$1504,4,FALSE)) -> Birmingham Local Plan 2042 | G13: =IF(VLOOKUP($A13,'8 Oct - LIVE LDS Data'!$A$3:$AAD$1504,6,FALSE)=0/1/1900,"",VLOOKUP($A13,'8 Oct - LIVE LDS Data'!$A$3:$AAD$1504,6,FALSE)) -> 2020 | H13: =IF(VLOOKUP($A13,'8 Oct - LIVE LDS Data'!$A$3:$AAD$1504,7,FALSE)=0/1/1900,"",VLOOKUP($A13,'8 Oct - LIVE LDS Data'!$A$3:$AAD$1504,7,FALSE)) -> 2042 | I13: =IF(VLOOKUP($A13,'8 Oct - LIVE LDS Data'!$A$3:$AAD$1504,8,FALSE)=0/1/1900,"",VLOOKUP($A13,'8 Oct - LIVE LDS Data'!$A$3:$AAD$1504,8,FALSE)) -> N | J13: =IF(VLOOKUP($A13,'8 Oct - LIVE LDS Data'!$A$3:$AAD$1504,9,FALSE)=0/1/1900,"",VLOOKUP($A13,'8 Oct - LIVE LDS Data'!$A$3:$AAD$1504,9,FALSE)) -> N | K13: =IF(VLOOKUP($A13,'8 Oct - LIVE LDS Data'!$A$3:$AAD$1504,10,FALSE)=0/1/1900,"",VLOOKUP($A13,'8 Oct - LIVE LDS Data'!$A$3:$AAD$1504,10,FALSE)) -> 42745 | L13: =IF(VLOOKUP($A13,'8 Oct - LIVE LDS Data'!$A$3:$AAD$1504,34,FALSE)=0/1/1900,"",VLOOKUP($A13,'8 Oct - LIVE LDS Data'!$A$3:$AAD$1504,34,FALSE)) -> 44858 | M13: =IF(VLOOKUP($A13,'8 Oct - LIVE LDS Data'!$A$3:$AAD$1504,35,FALSE)=0/1/1900,"",VLOOKUP($A13,'8 Oct - LIVE LDS Data'!$A$3:$AAD$1504,35,FALSE)) -> 44900 | N13: =IF(VLOOKUP($A13,'8 Oct - LIVE LDS Data'!$A$3:$AAD$1504,41,FALSE)=0/1/1900,"",VLOOKUP($A13,'8 Oct - LIVE LDS Data'!$A$3:$AAD$1504,41,FALSE)) -> 45474 | O13: =IF(VLOOKUP($A13,'8 Oct - LIVE LDS Data'!$A$3:$AAD$1504,42,FALSE)=0/1/1900,"",VLOOKUP($A13,'8 Oct - LIVE LDS Data'!$A$3:$AAD$1504,42,FALSE)) -> 45505 | P13: =IF(VLOOKUP($A13,'8 Oct - LIVE LDS Data'!$A$3:$AAD$1504,48,FALSE)=0/1/1900,"",VLOOKUP($A13,'8 Oct - LIVE LDS Data'!$A$3:$AAD$1504,48,FALSE)) | Q13: =IF(VLOOKUP($A13,'8 Oct - LIVE LDS Data'!$A$3:$AAD$1504,49,FALSE)=0/1/1900,"",VLOOKUP($A13,'8 Oct - LIVE LDS Data'!$A$3:$AAD$1504,49,FALSE)) | R13: =IF(VLOOKUP($A13,'8 Oct - LIVE LDS Data'!$A$3:$AAD$1504,55,FALSE)=0/1/1900,"",VLOOKUP($A13,'8 Oct - LIVE LDS Data'!$A$3:$AAD$1504,55,FALSE)) | S13: =IF(VLOOKUP($A13,'8 Oct - LIVE LDS Data'!$A$3:$AAD$1504,56,FALSE)=0/1/1900,"",VLOOKUP($A13,'8 Oct - LIVE LDS Data'!$A$3:$AAD$1504,56,FALSE)) | T13: =IF(VLOOKUP($A13,'8 Oct - LIVE LDS Data'!$A$3:$AAD$1504,61,FALSE)=0/1/1900,"",VLOOKUP($A13,'8 Oct - LIVE LDS Data'!$A$3:$AAD$1504,61,FALSE)) | U13: =IF(VLOOKUP($A13,'8 Oct - LIVE LDS Data'!$A$3:$AAD$1504,64,FALSE)=0/1/1900,"",VLOOKUP($A13,'8 Oct - LIVE LDS Data'!$A$3:$AAD$1504,64,FALSE)) | V13: =IF(VLOOKUP($A13,'8 Oct - LIVE LDS Data'!$A$3:$AAD$1504,67,FALSE)=0/1/1900,"",VLOOKUP($A13,'8 Oct - LIVE LDS Data'!$A$3:$AAD$1504,67,FALSE)) | W13: =IF(VLOOKUP($A13,'8 Oct - LIVE LDS Data'!$A$3:$AAD$1504,80,FALSE)=0/1/1900,"",VLOOKUP($A13,'8 Oct - LIVE LDS Data'!$A$3:$AAD$1504,80,FALSE)) | X13: YES | Y13: =IF(VLOOKUP($A13,'8 Oct - LIVE LDS Data'!$A$3:$AAD$1504,73,FALSE)=0/1/1900,"",VLOOKUP($A13,'8 Oct - LIVE LDS Data'!$A$3:$AAD$1504,73,FALSE)) -> 45686 | Z13: =IF(VLOOKUP($A13,'8 Oct - LIVE LDS Data'!$A$3:$AAD$1504,74,FALSE)=0/1/1900,"",VLOOKUP($A13,'8 Oct - LIVE LDS Data'!$A$3:$AAD$1504,74,FALSE)) -> Robert Putnam | AA13: =IF(VLOOKUP($A13,'8 Oct - LIVE LDS Data'!$A$3:$AAD$1504,76,FALSE)=0/1/1900,"",VLOOKUP($A13,'8 Oct - LIVE LDS Data'!$A$3:$AAD$1504,76,FALSE)) -> 45686 | AB13: =IF(VLOOKUP($A13,'8 Oct - LIVE LDS Data'!$A$3:$AAD$1504,77,FALSE)=0/1/1900,"",VLOOKUP($A13,'8 Oct - LIVE LDS Data'!$A$3:$AAD$1504,77,FALSE)) -> Robert Putnam
A14: E07000129 | C14: Blaby | F14: =IF(VLOOKUP($A14,'8 Oct - LIVE LDS Data'!$A$3:$AAD$1504,4,FALSE)=0/1/1900,"",VLOOKUP($A14,'8 Oct - LIVE LDS Data'!$A$3:$AAD$1504,4,FALSE)) -> Blaby District New Local Plan | G14: =IF(VLOOKUP($A14,'8 Oct - LIVE LDS Data'!$A$3:$AAD$1504,6,FALSE)=0/1/1900,"",VLOOKUP($A14,'8 Oct - LIVE LDS Data'!$A$3:$AAD$1504,6,FALSE)) -> 2022 | H14: =IF(VLOOKUP($A14,'8 Oct - LIVE LDS Data'!$A$3:$AAD$1504,7,FALSE)=0/1/1900,"",VLOOKUP($A14,'8 Oct - LIVE LDS Data'!$A$3:$AAD$1504,7,FALSE)) -> 2037 | I14: =IF(VLOOKUP($A14,'8 Oct - LIVE LDS Data'!$A$3:$AAD$1504,8,FALSE)=0/1/1900,"",VLOOKUP($A14,'8 Oct - LIVE LDS Data'!$A$3:$AAD$1504,8,FALSE)) -> N | J14: =IF(VLOOKUP($A14,'8 Oct - LIVE LDS Data'!$A$3:$AAD$1504,9,FALSE)=0/1/1900,"",VLOOKUP($A14,'8 Oct - LIVE LDS Data'!$A$3:$AAD$1504,9,FALSE)) -> N | K14: =IF(VLOOKUP($A14,'8 Oct - LIVE LDS Data'!$A$3:$AAD$1504,10,FALSE)=0/1/1900,"",VLOOKUP($A14,'8 Oct - LIVE LDS Data'!$A$3:$AAD$1504,10,FALSE)) -> 41326 | L14: =IF(VLOOKUP($A14,'8 Oct - LIVE LDS Data'!$A$3:$AAD$1504,34,FALSE)=0/1/1900,"",VLOOKUP($A14,'8 Oct - LIVE LDS Data'!$A$3:$AAD$1504,34,FALSE)) -> 43647 | M14: =IF(VLOOKUP($A14,'8 Oct - LIVE LDS Data'!$A$3:$AAD$1504,35,FALSE)=0/1/1900,"",VLOOKUP($A14,'8 Oct - LIVE LDS Data'!$A$3:$AAD$1504,35,FALSE)) -> 43738 | N14: =IF(VLOOKUP($A14,'8 Oct - LIVE LDS Data'!$A$3:$AAD$1504,41,FALSE)=0/1/1900,"",VLOOKUP($A14,'8 Oct - LIVE LDS Data'!$A$3:$AAD$1504,41,FALSE)) -> 44197 | O14: =IF(VLOOKUP($A14,'8 Oct - LIVE LDS Data'!$A$3:$AAD$1504,42,FALSE)=0/1/1900,"",VLOOKUP($A14,'8 Oct - LIVE LDS Data'!$A$3:$AAD$1504,42,FALSE)) -> 44256 | P14: =IF(VLOOKUP($A14,'8 Oct - LIVE LDS Data'!$A$3:$AAD$1504,48,FALSE)=0/1/1900,"",VLOOKUP($A14,'8 Oct - LIVE LDS Data'!$A$3:$AAD$1504,48,FALSE)) | Q14: =IF(VLOOKUP($A14,'8 Oct - LIVE LDS Data'!$A$3:$AAD$1504,49,FALSE)=0/1/1900,"",VLOOKUP($A14,'8 Oct - LIVE LDS Data'!$A$3:$AAD$1504,49,FALSE)) | R14: =IF(VLOOKUP($A14,'8 Oct - LIVE LDS Data'!$A$3:$AAD$1504,55,FALSE)=0/1/1900,"",VLOOKUP($A14,'8 Oct - LIVE LDS Data'!$A$3:$AAD$1504,55,FALSE)) | S14: =IF(VLOOKUP($A14,'8 Oct - LIVE LDS Data'!$A$3:$AAD$1504,56,FALSE)=0/1/1900,"",VLOOKUP($A14,'8 Oct - LIVE LDS Data'!$A$3:$AAD$1504,56,FALSE)) | T14: =IF(VLOOKUP($A14,'8 Oct - LIVE LDS Data'!$A$3:$AAD$1504,61,FALSE)=0/1/1900,"",VLOOKUP($A14,'8 Oct - LIVE LDS Data'!$A$3:$AAD$1504,61,FALSE)) | U14: =IF(VLOOKUP($A14,'8 Oct - LIVE LDS Data'!$A$3:$AAD$1504,64,FALSE)=0/1/1900,"",VLOOKUP($A14,'8 Oct - LIVE LDS Data'!$A$3:$AAD$1504,64,FALSE)) | V14: =IF(VLOOKUP($A14,'8 Oct - LIVE LDS Data'!$A$3:$AAD$1504,67,FALSE)=0/1/1900,"",VLOOKUP($A14,'8 Oct - LIVE LDS Data'!$A$3:$AAD$1504,67,FALSE)) | W14: =IF(VLOOKUP($A14,'8 Oct - LIVE LDS Data'!$A$3:$AAD$1504,80,FALSE)=0/1/1900,"",VLOOKUP($A14,'8 Oct - LIVE LDS Data'!$A$3:$AAD$1504,80,FALSE)) | X14: YES | Y14: =IF(VLOOKUP($A14,'8 Oct - LIVE LDS Data'!$A$3:$AAD$1504,73,FALSE)=0/1/1900,"",VLOOKUP($A14,'8 Oct - LIVE LDS Data'!$A$3:$AAD$1504,73,FALSE)) -> 45763 | Z14: =IF(VLOOKUP($A14,'8 Oct - LIVE LDS Data'!$A$3:$AAD$1504,74,FALSE)=0/1/1900,"",VLOOKUP($A14,'8 Oct - LIVE LDS Data'!$A$3:$AAD$1504,74,FALSE)) -> Greg Foster | AA14: =IF(VLOOKUP($A14,'8 Oct - LIVE LDS Data'!$A$3:$AAD$1504,76,FALSE)=0/1/1900,"",VLOOKUP($A14,'8 Oct - LIVE LDS Data'!$A$3:$AAD$1504,76,FALSE)) -> 45635 | AB14: =IF(VLOOKUP($A14,'8 Oct - LIVE LDS Data'!$A$3:$AAD$1504,77,FALSE)=0/1/1900,"",VLOOKUP($A14,'8 Oct - LIVE LDS Data'!$A$3:$AAD$1504,77,FALSE)) -> Robert Putnam
A15: E06000009 | C15: Blackpool | F15: =IF(VLOOKUP($A15,'8 Oct - LIVE LDS Data'!$A$3:$AAD$1504,4,FALSE)=0/1/1900,"",VLOOKUP($A15,'8 Oct - LIVE LDS Data'!$A$3:$AAD$1504,4,FALSE)) -> New Local Plan to 2042 | G15: =IF(VLOOKUP($A15,'8 Oct - LIVE LDS Data'!$A$3:$AAD$1504,6,FALSE)=0/1/1900,"",VLOOKUP($A15,'8 Oct - LIVE LDS Data'!$A$3:$AAD$1504,6,FALSE)) -> 2023 | H15: =IF(VLOOKUP($A15,'8 Oct - LIVE LDS Data'!$A$3:$AAD$1504,7,FALSE)=0/1/1900,"",VLOOKUP($A15,'8 Oct - LIVE LDS Data'!$A$3:$AAD$1504,7,FALSE)) -> 2042 | I15: =IF(VLOOKUP($A15,'8 Oct - LIVE LDS Data'!$A$3:$AAD$1504,8,FALSE)=0/1/1900,"",VLOOKUP($A15,'8 Oct - LIVE LDS Data'!$A$3:$AAD$1504,8,FALSE)) -> N | J15: =IF(VLOOKUP($A15,'8 Oct - LIVE LDS Data'!$A$3:$AAD$1504,9,FALSE)=0/1/1900,"",VLOOKUP($A15,'8 Oct - LIVE LDS Data'!$A$3:$AAD$1504,9,FALSE)) -> N | K15: =IF(VLOOKUP($A15,'8 Oct - LIVE LDS Data'!$A$3:$AAD$1504,10,FALSE)=0/1/1900,"",VLOOKUP($A15,'8 Oct - LIVE LDS Data'!$A$3:$AAD$1504,10,FALSE)) -> 42389 | L15: =IF(VLOOKUP($A15,'8 Oct - LIVE LDS Data'!$A$3:$AAD$1504,34,FALSE)=0/1/1900,"",VLOOKUP($A15,'8 Oct - LIVE LDS Data'!$A$3:$AAD$1504,34,FALSE)) | M15: =IF(VLOOKUP($A15,'8 Oct - LIVE LDS Data'!$A$3:$AAD$1504,35,FALSE)=0/1/1900,"",VLOOKUP($A15,'8 Oct - LIVE LDS Data'!$A$3:$AAD$1504,35,FALSE)) | N15: =IF(VLOOKUP($A15,'8 Oct - LIVE LDS Data'!$A$3:$AAD$1504,41,FALSE)=0/1/1900,"",VLOOKUP($A15,'8 Oct - LIVE LDS Data'!$A$3:$AAD$1504,41,FALSE)) | O15: =IF(VLOOKUP($A15,'8 Oct - LIVE LDS Data'!$A$3:$AAD$1504,42,FALSE)=0/1/1900,"",VLOOKUP($A15,'8 Oct - LIVE LDS Data'!$A$3:$AAD$1504,42,FALSE)) | P15: =IF(VLOOKUP($A15,'8 Oct - LIVE LDS Data'!$A$3:$AAD$1504,48,FALSE)=0/1/1900,"",VLOOKUP($A15,'8 Oct - LIVE LDS Data'!$A$3:$AAD$1504,48,FALSE)) | Q15: =IF(VLOOKUP($A15,'8 Oct - LIVE LDS Data'!$A$3:$AAD$1504,49,FALSE)=0/1/1900,"",VLOOKUP($A15,'8 Oct - LIVE LDS Data'!$A$3:$AAD$1504,49,FALSE)) | R15: =IF(VLOOKUP($A15,'8 Oct - LIVE LDS Data'!$A$3:$AAD$1504,55,FALSE)=0/1/1900,"",VLOOKUP($A15,'8 Oct - LIVE LDS Data'!$A$3:$AAD$1504,55,FALSE)) | S15: =IF(VLOOKUP($A15,'8 Oct - LIVE LDS Data'!$A$3:$AAD$1504,56,FALSE)=0/1/1900,"",VLOOKUP($A15,'8 Oct - LIVE LDS Data'!$A$3:$AAD$1504,56,FALSE)) | T15: =IF(VLOOKUP($A15,'8 Oct - LIVE LDS Data'!$A$3:$AAD$1504,61,FALSE)=0/1/1900,"",VLOOKUP($A15,'8 Oct - LIVE LDS Data'!$A$3:$AAD$1504,61,FALSE)) | U15: =IF(VLOOKUP($A15,'8 Oct - LIVE LDS Data'!$A$3:$AAD$1504,64,FALSE)=0/1/1900,"",VLOOKUP($A15,'8 Oct - LIVE LDS Data'!$A$3:$AAD$1504,64,FALSE)) | V15: =IF(VLOOKUP($A15,'8 Oct - LIVE LDS Data'!$A$3:$AAD$1504,67,FALSE)=0/1/1900,"",VLOOKUP($A15,'8 Oct - LIVE LDS Data'!$A$3:$AAD$1504,67,FALSE)) | W15: =IF(VLOOKUP($A15,'8 Oct - LIVE LDS Data'!$A$3:$AAD$1504,80,FALSE)=0/1/1900,"",VLOOKUP($A15,'8 Oct - LIVE LDS Data'!$A$3:$AAD$1504,80,FALSE)) | X15: YES | Y15: =IF(VLOOKUP($A15,'8 Oct - LIVE LDS Data'!$A$3:$AAD$1504,73,FALSE)=0/1/1900,"",VLOOKUP($A15,'8 Oct - LIVE LDS Data'!$A$3:$AAD$1504,73,FALSE)) -> 45763 | Z15: =IF(VLOOKUP($A15,'8 Oct - LIVE LDS Data'!$A$3:$AAD$1504,74,FALSE)=0/1/1900,"",VLOOKUP($A15,'8 Oct - LIVE LDS Data'!$A$3:$AAD$1504,74,FALSE)) -> Greg Foster | AA15: =IF(VLOOKUP($A15,'8 Oct - LIVE LDS Data'!$A$3:$AAD$1504,76,FALSE)=0/1/1900,"",VLOOKUP($A15,'8 Oct - LIVE LDS Data'!$A$3:$AAD$1504,76,FALSE)) -> 44855 | AB15: =IF(VLOOKUP($A15,'8 Oct - LIVE LDS Data'!$A$3:$AAD$1504,77,FALSE)=0/1/1900,"",VLOOKUP($A15,'8 Oct - LIVE LDS Data'!$A$3:$AAD$1504,77,FALSE)) -> Robert Putnam
A16: E07000033 | C16: Bolsover | F16: =IF(VLOOKUP($A16,'8 Oct - LIVE LDS Data'!$A$3:$AAD$1504,4,FALSE)=0/1/1900,"",VLOOKUP($A16,'8 Oct - LIVE LDS Data'!$A$3:$AAD$1504,4,FALSE)) -> Bolsover Local Plan | G16: =IF(VLOOKUP($A16,'8 Oct - LIVE LDS Data'!$A$3:$AAD$1504,6,FALSE)=0/1/1900,"",VLOOKUP($A16,'8 Oct - LIVE LDS Data'!$A$3:$AAD$1504,6,FALSE)) | H16: =IF(VLOOKUP($A16,'8 Oct - LIVE LDS Data'!$A$3:$AAD$1504,7,FALSE)=0/1/1900,"",VLOOKUP($A16,'8 Oct - LIVE LDS Data'!$A$3:$AAD$1504,7,FALSE)) | I16: =IF(VLOOKUP($A16,'8 Oct - LIVE LDS Data'!$A$3:$AAD$1504,8,FALSE)=0/1/1900,"",VLOOKUP($A16,'8 Oct - LIVE LDS Data'!$A$3:$AAD$1504,8,FALSE)) -> N | J16: =IF(VLOOKUP($A16,'8 Oct - LIVE LDS Data'!$A$3:$AAD$1504,9,FALSE)=0/1/1900,"",VLOOKUP($A16,'8 Oct - LIVE LDS Data'!$A$3:$AAD$1504,9,FALSE)) -> N | K16: =IF(VLOOKUP($A16,'8 Oct - LIVE LDS Data'!$A$3:$AAD$1504,10,FALSE)=0/1/1900,"",VLOOKUP($A16,'8 Oct - LIVE LDS Data'!$A$3:$AAD$1504,10,FALSE)) -> 43894 | L16: =IF(VLOOKUP($A16,'8 Oct - LIVE LDS Data'!$A$3:$AAD$1504,34,FALSE)=0/1/1900,"",VLOOKUP($A16,'8 Oct - LIVE LDS Data'!$A$3:$AAD$1504,34,FALSE)) | M16: =IF(VLOOKUP($A16,'8 Oct - LIVE LDS Data'!$A$3:$AAD$1504,35,FALSE)=0/1/1900,"",VLOOKUP($A16,'8 Oct - LIVE LDS Data'!$A$3:$AAD$1504,35,FALSE)) | N16: =IF(VLOOKUP($A16,'8 Oct - LIVE LDS Data'!$A$3:$AAD$1504,41,FALSE)=0/1/1900,"",VLOOKUP($A16,'8 Oct - LIVE LDS Data'!$A$3:$AAD$1504,41,FALSE)) | O16: =IF(VLOOKUP($A16,'8 Oct - LIVE LDS Data'!$A$3:$AAD$1504,42,FALSE)=0/1/1900,"",VLOOKUP($A16,'8 Oct - LIVE LDS Data'!$A$3:$AAD$1504,42,FALSE)) | P16: =IF(VLOOKUP($A16,'8 Oct - LIVE LDS Data'!$A$3:$AAD$1504,48,FALSE)=0/1/1900,"",VLOOKUP($A16,'8 Oct - LIVE LDS Data'!$A$3:$AAD$1504,48,FALSE)) | Q16: =IF(VLOOKUP($A16,'8 Oct - LIVE LDS Data'!$A$3:$AAD$1504,49,FALSE)=0/1/1900,"",VLOOKUP($A16,'8 Oct - LIVE LDS Data'!$A$3:$AAD$1504,49,FALSE)) | R16: =IF(VLOOKUP($A16,'8 Oct - LIVE LDS Data'!$A$3:$AAD$1504,55,FALSE)=0/1/1900,"",VLOOKUP($A16,'8 Oct - LIVE LDS Data'!$A$3:$AAD$1504,55,FALSE)) | S16: =IF(VLOOKUP($A16,'8 Oct - LIVE LDS Data'!$A$3:$AAD$1504,56,FALSE)=0/1/1900,"",VLOOKUP($A16,'8 Oct - LIVE LDS Data'!$A$3:$AAD$1504,56,FALSE)) | T16: =IF(VLOOKUP($A16,'8 Oct - LIVE LDS Data'!$A$3:$AAD$1504,61,FALSE)=0/1/1900,"",VLOOKUP($A16,'8 Oct - LIVE LDS Data'!$A$3:$AAD$1504,61,FALSE)) | U16: =IF(VLOOKUP($A16,'8 Oct - LIVE LDS Data'!$A$3:$AAD$1504,64,FALSE)=0/1/1900,"",VLOOKUP($A16,'8 Oct - LIVE LDS Data'!$A$3:$AAD$1504,64,FALSE)) | V16: =IF(VLOOKUP($A16,'8 Oct - LIVE LDS Data'!$A$3:$AAD$1504,67,FALSE)=0/1/1900,"",VLOOKUP($A16,'8 Oct - LIVE LDS Data'!$A$3:$AAD$1504,67,FALSE)) | W16: =IF(VLOOKUP($A16,'8 Oct - LIVE LDS Data'!$A$3:$AAD$1504,80,FALSE)=0/1/1900,"",VLOOKUP($A16,'8 Oct - LIVE LDS Data'!$A$3:$AAD$1504,80,FALSE)) | X16: YES | Y16: =IF(VLOOKUP($A16,'8 Oct - LIVE LDS Data'!$A$3:$AAD$1504,73,FALSE)=0/1/1900,"",VLOOKUP($A16,'8 Oct - LIVE LDS Data'!$A$3:$AAD$1504,73,FALSE)) -> 45763 | Z16: =IF(VLOOKUP($A16,'8 Oct - LIVE LDS Data'!$A$3:$AAD$1504,74,FALSE)=0/1/1900,"",VLOOKUP($A16,'8 Oct - LIVE LDS Data'!$A$3:$AAD$1504,74,FALSE)) -> Greg Foster | AA16: =IF(VLOOKUP($A16,'8 Oct - LIVE LDS Data'!$A$3:$AAD$1504,76,FALSE)=0/1/1900,"",VLOOKUP($A16,'8 Oct - LIVE LDS Data'!$A$3:$AAD$1504,76,FALSE)) -> 45686 | AB16: =IF(VLOOKUP($A16,'8 Oct - LIVE LDS Data'!$A$3:$AAD$1504,77,FALSE)=0/1/1900,"",VLOOKUP($A16,'8 Oct - LIVE LDS Data'!$A$3:$AAD$1504,77,FALSE)) -> Robert Putnam
A17: E07000136 | C17: Boston | F17: =IF(VLOOKUP($A17,'8 Oct - LIVE LDS Data'!$A$3:$AAD$1504,4,FALSE)=0/1/1900,"",VLOOKUP($A17,'8 Oct - LIVE LDS Data'!$A$3:$AAD$1504,4,FALSE)) -> South East Lincolnshire Local Plan Review | G17: =IF(VLOOKUP($A17,'8 Oct - LIVE LDS Data'!$A$3:$AAD$1504,6,FALSE)=0/1/1900,"",VLOOKUP($A17,'8 Oct - LIVE LDS Data'!$A$3:$AAD$1504,6,FALSE)) | H17: =IF(VLOOKUP($A17,'8 Oct - LIVE LDS Data'!$A$3:$AAD$1504,7,FALSE)=0/1/1900,"",VLOOKUP($A17,'8 Oct - LIVE LDS Data'!$A$3:$AAD$1504,7,FALSE)) | I17: =IF(VLOOKUP($A17,'8 Oct - LIVE LDS Data'!$A$3:$AAD$1504,8,FALSE)=0/1/1900,"",VLOOKUP($A17,'8 Oct - LIVE LDS Data'!$A$3:$AAD$1504,8,FALSE)) | J17: =IF(VLOOKUP($A17,'8 Oct - LIVE LDS Data'!$A$3:$AAD$1504,9,FALSE)=0/1/1900,"",VLOOKUP($A17,'8 Oct - LIVE LDS Data'!$A$3:$AAD$1504,9,FALSE)) | K17: =IF(VLOOKUP($A17,'8 Oct - LIVE LDS Data'!$A$3:$AAD$1504,10,FALSE)=0/1/1900,"",VLOOKUP($A17,'8 Oct - LIVE LDS Data'!$A$3:$AAD$1504,10,FALSE)) -> 43532 | L17: =IF(VLOOKUP($A17,'8 Oct - LIVE LDS Data'!$A$3:$AAD$1504,34,FALSE)=0/1/1900,"",VLOOKUP($A17,'8 Oct - LIVE LDS Data'!$A$3:$AAD$1504,34,FALSE)) | M17: =IF(VLOOKUP($A17,'8 Oct - LIVE LDS Data'!$A$3:$AAD$1504,35,FALSE)=0/1/1900,"",VLOOKUP($A17,'8 Oct - LIVE LDS Data'!$A$3:$AAD$1504,35,FALSE)) | N17: =IF(VLOOKUP($A17,'8 Oct - LIVE LDS Data'!$A$3:$AAD$1504,41,FALSE)=0/1/1900,"",VLOOKUP($A17,'8 Oct - LIVE LDS Data'!$A$3:$AAD$1504,41,FALSE)) | O17: =IF(VLOOKUP($A17,'8 Oct - LIVE LDS Data'!$A$3:$AAD$1504,42,FALSE)=0/1/1900,"",VLOOKUP($A17,'8 Oct - LIVE LDS Data'!$A$3:$AAD$1504,42,FALSE)) | P17: =IF(VLOOKUP($A17,'8 Oct - LIVE LDS Data'!$A$3:$AAD$1504,48,FALSE)=0/1/1900,"",VLOOKUP($A17,'8 Oct - LIVE LDS Data'!$A$3:$AAD$1504,48,FALSE)) | Q17: =IF(VLOOKUP($A17,'8 Oct - LIVE LDS Data'!$A$3:$AAD$1504,49,FALSE)=0/1/1900,"",VLOOKUP($A17,'8 Oct - LIVE LDS Data'!$A$3:$AAD$1504,49,FALSE)) | R17: =IF(VLOOKUP($A17,'8 Oct - LIVE LDS Data'!$A$3:$AAD$1504,55,FALSE)=0/1/1900,"",VLOOKUP($A17,'8 Oct - LIVE LDS Data'!$A$3:$AAD$1504,55,FALSE)) | S17: =IF(VLOOKUP($A17,'8 Oct - LIVE LDS Data'!$A$3:$AAD$1504,56,FALSE)=0/1/1900,"",VLOOKUP($A17,'8 Oct - LIVE LDS Data'!$A$3:$AAD$1504,56,FALSE)) | T17: =IF(VLOOKUP($A17,'8 Oct - LIVE LDS Data'!$A$3:$AAD$1504,61,FALSE)=0/1/1900,"",VLOOKUP($A17,'8 Oct - LIVE LDS Data'!$A$3:$AAD$1504,61,FALSE)) | U17: =IF(VLOOKUP($A17,'8 Oct - LIVE LDS Data'!$A$3:$AAD$1504,64,FALSE)=0/1/1900,"",VLOOKUP($A17,'8 Oct - LIVE LDS Data'!$A$3:$AAD$1504,64,FALSE)) | V17: =IF(VLOOKUP($A17,'8 Oct - LIVE LDS Data'!$A$3:$AAD$1504,67,FALSE)=0/1/1900,"",VLOOKUP($A17,'8 Oct - LIVE LDS Data'!$A$3:$AAD$1504,67,FALSE)) | W17: =IF(VLOOKUP($A17,'8 Oct - LIVE LDS Data'!$A$3:$AAD$1504,80,FALSE)=0/1/1900,"",VLOOKUP($A17,'8 Oct - LIVE LDS Data'!$A$3:$AAD$1504,80,FALSE)) | X17: YES | Y17: =IF(VLOOKUP($A17,'8 Oct - LIVE LDS Data'!$A$3:$AAD$1504,73,FALSE)=0/1/1900,"",VLOOKUP($A17,'8 Oct - LIVE LDS Data'!$A$3:$AAD$1504,73,FALSE)) | Z17: =IF(VLOOKUP($A17,'8 Oct - LIVE LDS Data'!$A$3:$AAD$1504,74,FALSE)=0/1/1900,"",VLOOKUP($A17,'8 Oct - LIVE LDS Data'!$A$3:$AAD$1504,74,FALSE)) -> Robert Putnam | AA17: =IF(VLOOKUP($A17,'8 Oct - LIVE LDS Data'!$A$3:$AAD$1504,76,FALSE)=0/1/1900,"",VLOOKUP($A17,'8 Oct - LIVE LDS Data'!$A$3:$AAD$1504,76,FALSE)) | AB17: =IF(VLOOKUP($A17,'8 Oct - LIVE LDS Data'!$A$3:$AAD$1504,77,FALSE)=0/1/1900,"",VLOOKUP($A17,'8 Oct - LIVE LDS Data'!$A$3:$AAD$1504,77,FALSE))
A18: E06000028 | C18: Bournemouth (defunct - now part of Bournemouth, Christchurch & Poole) | D18: YES [BCP] | G18: =IF(VLOOKUP($A18,'8 Oct - LIVE LDS Data'!$A$3:$AAD$1504,6,FALSE)=0/1/1900,"",VLOOKUP($A18,'8 Oct - LIVE LDS Data'!$A$3:$AAD$1504,6,FALSE)) | H18: =IF(VLOOKUP($A18,'8 Oct - LIVE LDS Data'!$A$3:$AAD$1504,7,FALSE)=0/1/1900,"",VLOOKUP($A18,'8 Oct - LIVE LDS Data'!$A$3:$AAD$1504,7,FALSE)) | I18: =IF(VLOOKUP($A18,'8 Oct - LIVE LDS Data'!$A$3:$AAD$1504,8,FALSE)=0/1/1900,"",VLOOKUP($A18,'8 Oct - LIVE LDS Data'!$A$3:$AAD$1504,8,FALSE)) | J18: =IF(VLOOKUP($A18,'8 Oct - LIVE LDS Data'!$A$3:$AAD$1504,9,FALSE)=0/1/1900,"",VLOOKUP($A18,'8 Oct - LIVE LDS Data'!$A$3:$AAD$1504,9,FALSE)) | K18: =IF(VLOOKUP($A18,'8 Oct - LIVE LDS Data'!$A$3:$AAD$1504,10,FALSE)=0/1/1900,"",VLOOKUP($A18,'8 Oct - LIVE LDS Data'!$A$3:$AAD$1504,10,FALSE)) -> 41212 | L18: =IF(VLOOKUP($A18,'8 Oct - LIVE LDS Data'!$A$3:$AAD$1504,34,FALSE)=0/1/1900,"",VLOOKUP($A18,'8 Oct - LIVE LDS Data'!$A$3:$AAD$1504,34,FALSE)) | M18: =IF(VLOOKUP($A18,'8 Oct - LIVE LDS Data'!$A$3:$AAD$1504,35,FALSE)=0/1/1900,"",VLOOKUP($A18,'8 Oct - LIVE LDS Data'!$A$3:$AAD$1504,35,FALSE)) | N18: =IF(VLOOKUP($A18,'8 Oct - LIVE LDS Data'!$A$3:$AAD$1504,41,FALSE)=0/1/1900,"",VLOOKUP($A18,'8 Oct - LIVE LDS Data'!$A$3:$AAD$1504,41,FALSE)) | O18: =IF(VLOOKUP($A18,'8 Oct - LIVE LDS Data'!$A$3:$AAD$1504,42,FALSE)=0/1/1900,"",VLOOKUP($A18,'8 Oct - LIVE LDS Data'!$A$3:$AAD$1504,42,FALSE)) | P18: =IF(VLOOKUP($A18,'8 Oct - LIVE LDS Data'!$A$3:$AAD$1504,48,FALSE)=0/1/1900,"",VLOOKUP($A18,'8 Oct - LIVE LDS Data'!$A$3:$AAD$1504,48,FALSE)) | Q18: =IF(VLOOKUP($A18,'8 Oct - LIVE LDS Data'!$A$3:$AAD$1504,49,FALSE)=0/1/1900,"",VLOOKUP($A18,'8 Oct - LIVE LDS Data'!$A$3:$AAD$1504,49,FALSE)) | R18: =IF(VLOOKUP($A18,'8 Oct - LIVE LDS Data'!$A$3:$AAD$1504,55,FALSE)=0/1/1900,"",VLOOKUP($A18,'8 Oct - LIVE LDS Data'!$A$3:$AAD$1504,55,FALSE)) | S18: =IF(VLOOKUP($A18,'8 Oct - LIVE LDS Data'!$A$3:$AAD$1504,56,FALSE)=0/1/1900,"",VLOOKUP($A18,'8 Oct - LIVE LDS Data'!$A$3:$AAD$1504,56,FALSE)) | T18: =IF(VLOOKUP($A18,'8 Oct - LIVE LDS Data'!$A$3:$AAD$1504,61,FALSE)=0/1/1900,"",VLOOKUP($A18,'8 Oct - LIVE LDS Data'!$A$3:$AAD$1504,61,FALSE)) | U18: =IF(VLOOKUP($A18,'8 Oct - LIVE LDS Data'!$A$3:$AAD$1504,64,FALSE)=0/1/1900,"",VLOOKUP($A18,'8 Oct - LIVE LDS Data'!$A$3:$AAD$1504,64,FALSE)) | V18: =IF(VLOOKUP($A18,'8 Oct - LIVE LDS Data'!$A$3:$AAD$1504,67,FALSE)=0/1/1900,"",VLOOKUP($A18,'8 Oct - LIVE LDS Data'!$A$3:$AAD$1504,67,FALSE)) | W18: =IF(VLOOKUP($A18,'8 Oct - LIVE LDS Data'!$A$3:$AAD$1504,80,FALSE)=0/1/1900,"",VLOOKUP($A18,'8 Oct - LIVE LDS Data'!$A$3:$AAD$1504,80,FALSE)) | X18: YES | Y18: =IF(VLOOKUP($A18,'8 Oct - LIVE LDS Data'!$A$3:$AAD$1504,73,FALSE)=0/1/1900,"",VLOOKUP($A18,'8 Oct - LIVE LDS Data'!$A$3:$AAD$1504,73,FALSE)) | Z18: =IF(VLOOKUP($A18,'8 Oct - LIVE LDS Data'!$A$3:$AAD$1504,74,FALSE)=0/1/1900,"",VLOOKUP($A18,'8 Oct - LIVE LDS Data'!$A$3:$AAD$1504,74,FALSE)) | AA18: =IF(VLOOKUP($A18,'8 Oct - LIVE LDS Data'!$A$3:$AAD$1504,76,FALSE)=0/1/1900,"",VLOOKUP($A18,'8 Oct - LIVE LDS Data'!$A$3:$AAD$1504,76,FALSE)) | AB18: =IF(VLOOKUP($A18,'8 Oct - LIVE LDS Data'!$A$3:$AAD$1504,77,FALSE)=0/1/1900,"",VLOOKUP($A18,'8 Oct - LIVE LDS Data'!$A$3:$AAD$1504,77,FALSE))
A19: E08000032 | C19: Bradford | F19: =IF(VLOOKUP($A19,'8 Oct - LIVE LDS Data'!$A$3:$AAD$1504,4,FALSE)=0/1/1900,"",VLOOKUP($A19,'8 Oct - LIVE LDS Data'!$A$3:$AAD$1504,4,FALSE)) -> Bradford District Local Plan | G19: =IF(VLOOKUP($A19,'8 Oct - LIVE LDS Data'!$A$3:$AAD$1504,6,FALSE)=0/1/1900,"",VLOOKUP($A19,'8 Oct - LIVE LDS Data'!$A$3:$AAD$1504,6,FALSE)) -> 2020 | H19: =IF(VLOOKUP($A19,'8 Oct - LIVE LDS Data'!$A$3:$AAD$1504,7,FALSE)=0/1/1900,"",VLOOKUP($A19,'8 Oct - LIVE LDS Data'!$A$3:$AAD$1504,7,FALSE)) -> 2038 | I19: =IF(VLOOKUP($A19,'8 Oct - LIVE LDS Data'!$A$3:$AAD$1504,8,FALSE)=0/1/1900,"",VLOOKUP($A19,'8 Oct - LIVE LDS Data'!$A$3:$AAD$1504,8,FALSE)) -> N | J19: =IF(VLOOKUP($A19,'8 Oct - LIVE LDS Data'!$A$3:$AAD$1504,9,FALSE)=0/1/1900,"",VLOOKUP($A19,'8 Oct - LIVE LDS Data'!$A$3:$AAD$1504,9,FALSE)) -> N | K19: =IF(VLOOKUP($A19,'8 Oct - LIVE LDS Data'!$A$3:$AAD$1504,10,FALSE)=0/1/1900,"",VLOOKUP($A19,'8 Oct - LIVE LDS Data'!$A$3:$AAD$1504,10,FALSE)) -> 42934 | L19: =IF(VLOOKUP($A19,'8 Oct - LIVE LDS Data'!$A$3:$AAD$1504,34,FALSE)=0/1/1900,"",VLOOKUP($A19,'8 Oct - LIVE LDS Data'!$A$3:$AAD$1504,34,FALSE)) -> 43476 | M19: =IF(VLOOKUP($A19,'8 Oct - LIVE LDS Data'!$A$3:$AAD$1504,35,FALSE)=0/1/1900,"",VLOOKUP($A19,'8 Oct - LIVE LDS Data'!$A$3:$AAD$1504,35,FALSE)) -> 43518 | N19: =IF(VLOOKUP($A19,'8 Oct - LIVE LDS Data'!$A$3:$AAD$1504,41,FALSE)=0/1/1900,"",VLOOKUP($A19,'8 Oct - LIVE LDS Data'!$A$3:$AAD$1504,41,FALSE)) -> 43676 | O19: =IF(VLOOKUP($A19,'8 Oct - LIVE LDS Data'!$A$3:$AAD$1504,42,FALSE)=0/1/1900,"",VLOOKUP($A19,'8 Oct - LIVE LDS Data'!$A$3:$AAD$1504,42,FALSE)) -> 43732 | P19: =IF(VLOOKUP($A19,'8 Oct - LIVE LDS Data'!$A$3:$AAD$1504,48,FALSE)=0/1/1900,"",VLOOKUP($A19,'8 Oct - LIVE LDS Data'!$A$3:$AAD$1504,48,FALSE)) -> 44235 | Q19: =IF(VLOOKUP($A19,'8 Oct - LIVE LDS Data'!$A$3:$AAD$1504,49,FALSE)=0/1/1900,"",VLOOKUP($A19,'8 Oct - LIVE LDS Data'!$A$3:$AAD$1504,49,FALSE)) -> 44279 | R19: =IF(VLOOKUP($A19,'8 Oct - LIVE LDS Data'!$A$3:$AAD$1504,55,FALSE)=0/1/1900,"",VLOOKUP($A19,'8 Oct - LIVE LDS Data'!$A$3:$AAD$1504,55,FALSE)) | S19: =IF(VLOOKUP($A19,'8 Oct - LIVE LDS Data'!$A$3:$AAD$1504,56,FALSE)=0/1/1900,"",VLOOKUP($A19,'8 Oct - LIVE LDS Data'!$A$3:$AAD$1504,56,FALSE)) | T19: =IF(VLOOKUP($A19,'8 Oct - LIVE LDS Data'!$A$3:$AAD$1504,61,FALSE)=0/1/1900,"",VLOOKUP($A19,'8 Oct - LIVE LDS Data'!$A$3:$AAD$1504,61,FALSE)) | U19: =IF(VLOOKUP($A19,'8 Oct - LIVE LDS Data'!$A$3:$AAD$1504,64,FALSE)=0/1/1900,"",VLOOKUP($A19,'8 Oct - LIVE LDS Data'!$A$3:$AAD$1504,64,FALSE)) | V19: =IF(VLOOKUP($A19,'8 Oct - LIVE LDS Data'!$A$3:$AAD$1504,67,FALSE)=0/1/1900,"",VLOOKUP($A19,'8 Oct - LIVE LDS Data'!$A$3:$AAD$1504,67,FALSE)) | W19: =IF(VLOOKUP($A19,'8 Oct - LIVE LDS Data'!$A$3:$AAD$1504,80,FALSE)=0/1/1900,"",VLOOKUP($A19,'8 Oct - LIVE LDS Data'!$A$3:$AAD$1504,80,FALSE)) | X19: YES | Y19: =IF(VLOOKUP($A19,'8 Oct - LIVE LDS Data'!$A$3:$AAD$1504,73,FALSE)=0/1/1900,"",VLOOKUP($A19,'8 Oct - LIVE LDS Data'!$A$3:$AAD$1504,73,FALSE)) -> 45763 | Z19: =IF(VLOOKUP($A19,'8 Oct - LIVE LDS Data'!$A$3:$AAD$1504,74,FALSE)=0/1/1900,"",VLOOKUP($A19,'8 Oct - LIVE LDS Data'!$A$3:$AAD$1504,74,FALSE)) -> Greg Foster | AA19: =IF(VLOOKUP($A19,'8 Oct - LIVE LDS Data'!$A$3:$AAD$1504,76,FALSE)=0/1/1900,"",VLOOKUP($A19,'8 Oct - LIVE LDS Data'!$A$3:$AAD$1504,76,FALSE)) -> 45440 | AB19: =IF(VLOOKUP($A19,'8 Oct - LIVE LDS Data'!$A$3:$AAD$1504,77,FALSE)=0/1/1900,"",VLOOKUP($A19,'8 Oct - LIVE LDS Data'!$A$3:$AAD$1504,77,FALSE)) -> Robert Putnam
A20: E07000067 | C20: Braintree | F20: =IF(VLOOKUP($A20,'8 Oct - LIVE LDS Data'!$A$3:$AAD$1504,4,FALSE)=0/1/1900,"",VLOOKUP($A20,'8 Oct - LIVE LDS Data'!$A$3:$AAD$1504,4,FALSE)) -> Braintree Local Plan (North Essex Garden Communities) Section 1 Review | G20: =IF(VLOOKUP($A20,'8 Oct - LIVE LDS Data'!$A$3:$AAD$1504,6,FALSE)=0/1/1900,"",VLOOKUP($A20,'8 Oct - LIVE LDS Data'!$A$3:$AAD$1504,6,FALSE)) | H20: =IF(VLOOKUP($A20,'8 Oct - LIVE LDS Data'!$A$3:$AAD$1504,7,FALSE)=0/1/1900,"",VLOOKUP($A20,'8 Oct - LIVE LDS Data'!$A$3:$AAD$1504,7,FALSE)) | I20: =IF(VLOOKUP($A20,'8 Oct - LIVE LDS Data'!$A$3:$AAD$1504,8,FALSE)=0/1/1900,"",VLOOKUP($A20,'8 Oct - LIVE LDS Data'!$A$3:$AAD$1504,8,FALSE)) -> Y | J20: =IF(VLOOKUP($A20,'8 Oct - LIVE LDS Data'!$A$3:$AAD$1504,9,FALSE)=0/1/1900,"",VLOOKUP($A20,'8 Oct - LIVE LDS Data'!$A$3:$AAD$1504,9,FALSE)) -> N | K20: =IF(VLOOKUP($A20,'8 Oct - LIVE LDS Data'!$A$3:$AAD$1504,10,FALSE)=0/1/1900,"",VLOOKUP($A20,'8 Oct - LIVE LDS Data'!$A$3:$AAD$1504,10,FALSE)) -> 44249 | L20: =IF(VLOOKUP($A20,'8 Oct - LIVE LDS Data'!$A$3:$AAD$1504,34,FALSE)=0/1/1900,"",VLOOKUP($A20,'8 Oct - LIVE LDS Data'!$A$3:$AAD$1504,34,FALSE)) -> 45677 | M20: =IF(VLOOKUP($A20,'8 Oct - LIVE LDS Data'!$A$3:$AAD$1504,35,FALSE)=0/1/1900,"",VLOOKUP($A20,'8 Oct - LIVE LDS Data'!$A$3:$AAD$1504,35,FALSE)) -> 45723 | N20: =IF(VLOOKUP($A20,'8 Oct - LIVE LDS Data'!$A$3:$AAD$1504,41,FALSE)=0/1/1900,"",VLOOKUP($A20,'8 Oct - LIVE LDS Data'!$A$3:$AAD$1504,41,FALSE)) | O20: =IF(VLOOKUP($A20,'8 Oct - LIVE LDS Data'!$A$3:$AAD$1504,42,FALSE)=0/1/1900,"",VLOOKUP($A20,'8 Oct - LIVE LDS Data'!$A$3:$AAD$1504,42,FALSE)) | P20: =IF(VLOOKUP($A20,'8 Oct - LIVE LDS Data'!$A$3:$AAD$1504,48,FALSE)=0/1/1900,"",VLOOKUP($A20,'8 Oct - LIVE LDS Data'!$A$3:$AAD$1504,48,FALSE)) | Q20: =IF(VLOOKUP($A20,'8 Oct - LIVE LDS Data'!$A$3:$AAD$1504,49,FALSE)=0/1/1900,"",VLOOKUP($A20,'8 Oct - LIVE LDS Data'!$A$3:$AAD$1504,49,FALSE)) | R20: =IF(VLOOKUP($A20,'8 Oct - LIVE LDS Data'!$A$3:$AAD$1504,55,FALSE)=0/1/1900,"",VLOOKUP($A20,'8 Oct - LIVE LDS Data'!$A$3:$AAD$1504,55,FALSE)) | S20: =IF(VLOOKUP($A20,'8 Oct - LIVE LDS Data'!$A$3:$AAD$1504,56,FALSE)=0/1/1900,"",VLOOKUP($A20,'8 Oct - LIVE LDS Data'!$A$3:$AAD$1504,56,FALSE)) | T20: =IF(VLOOKUP($A20,'8 Oct - LIVE LDS Data'!$A$3:$AAD$1504,61,FALSE)=0/1/1900,"",VLOOKUP($A20,'8 Oct - LIVE LDS Data'!$A$3:$AAD$1504,61,FALSE)) | U20: =IF(VLOOKUP($A20,'8 Oct - LIVE LDS Data'!$A$3:$AAD$1504,64,FALSE)=0/1/1900,"",VLOOKUP($A20,'8 Oct - LIVE LDS Data'!$A$3:$AAD$1504,64,FALSE)) | V20: =IF(VLOOKUP($A20,'8 Oct - LIVE LDS Data'!$A$3:$AAD$1504,67,FALSE)=0/1/1900,"",VLOOKUP($A20,'8 Oct - LIVE LDS Data'!$A$3:$AAD$1504,67,FALSE)) | W20: =IF(VLOOKUP($A20,'8 Oct - LIVE LDS Data'!$A$3:$AAD$1504,80,FALSE)=0/1/1900,"",VLOOKUP($A20,'8 Oct - LIVE LDS Data'!$A$3:$AAD$1504,80,FALSE)) | X20: YES | Y20: =IF(VLOOKUP($A20,'8 Oct - LIVE LDS Data'!$A$3:$AAD$1504,73,FALSE)=0/1/1900,"",VLOOKUP($A20,'8 Oct - LIVE LDS Data'!$A$3:$AAD$1504,73,FALSE)) -> 45932 | Z20: =IF(VLOOKUP($A20,'8 Oct - LIVE LDS Data'!$A$3:$AAD$1504,74,FALSE)=0/1/1900,"",VLOOKUP($A20,'8 Oct - LIVE LDS Data'!$A$3:$AAD$1504,74,FALSE)) -> Robert Putnam | AA20: =IF(VLOOKUP($A20,'8 Oct - LIVE LDS Data'!$A$3:$AAD$1504,76,FALSE)=0/1/1900,"",VLOOKUP($A20,'8 Oct - LIVE LDS Data'!$A$3:$AAD$1504,76,FALSE)) -> 45575 | AB20: =IF(VLOOKUP($A20,'8 Oct - LIVE LDS Data'!$A$3:$AAD$1504,77,FALSE)=0/1/1900,"",VLOOKUP($A20,'8 Oct - LIVE LDS Data'!$A$3:$AAD$1504,77,FALSE)) -> Robert Putnam
A21: E07000143 | C21: Breckland | F21: =IF(VLOOKUP($A21,'8 Oct - LIVE LDS Data'!$A$3:$AAD$1504,4,FALSE)=0/1/1900,"",VLOOKUP($A21,'8 Oct - LIVE LDS Data'!$A$3:$AAD$1504,4,FALSE)) -> Breckland Local Plan Full Update 2024-2041 | G21: =IF(VLOOKUP($A21,'8 Oct - LIVE LDS Data'!$A$3:$AAD$1504,6,FALSE)=0/1/1900,"",VLOOKUP($A21,'8 Oct - LIVE LDS Data'!$A$3:$AAD$1504,6,FALSE)) -> 2024 | H21: =IF(VLOOKUP($A21,'8 Oct - LIVE LDS Data'!$A$3:$AAD$1504,7,FALSE)=0/1/1900,"",VLOOKUP($A21,'8 Oct - LIVE LDS Data'!$A$3:$AAD$1504,7,FALSE)) -> 2041 | I21: =IF(VLOOKUP($A21,'8 Oct - LIVE LDS Data'!$A$3:$AAD$1504,8,FALSE)=0/1/1900,"",VLOOKUP($A21,'8 Oct - LIVE LDS Data'!$A$3:$AAD$1504,8,FALSE)) -> N | J21: =IF(VLOOKUP($A21,'8 Oct - LIVE LDS Data'!$A$3:$AAD$1504,9,FALSE)=0/1/1900,"",VLOOKUP($A21,'8 Oct - LIVE LDS Data'!$A$3:$AAD$1504,9,FALSE)) -> N | K21: =IF(VLOOKUP($A21,'8 Oct - LIVE LDS Data'!$A$3:$AAD$1504,10,FALSE)=0/1/1900,"",VLOOKUP($A21,'8 Oct - LIVE LDS Data'!$A$3:$AAD$1504,10,FALSE)) -> 28 November 2019 (as amended by the partial update of 21 Sept 2023) | L21: =IF(VLOOKUP($A21,'8 Oct - LIVE LDS Data'!$A$3:$AAD$1504,34,FALSE)=0/1/1900,"",VLOOKUP($A21,'8 Oct - LIVE LDS Data'!$A$3:$AAD$1504,34,FALSE)) -> 44995 | M21: =IF(VLOOKUP($A21,'8 Oct - LIVE LDS Data'!$A$3:$AAD$1504,35,FALSE)=0/1/1900,"",VLOOKUP($A21,'8 Oct - LIVE LDS Data'!$A$3:$AAD$1504,35,FALSE)) -> 45065 | N21: =IF(VLOOKUP($A21,'8 Oct - LIVE LDS Data'!$A$3:$AAD$1504,41,FALSE)=0/1/1900,"",VLOOKUP($A21,'8 Oct - LIVE LDS Data'!$A$3:$AAD$1504,41,FALSE)) -> 45299 | O21: =IF(VLOOKUP($A21,'8 Oct - LIVE LDS Data'!$A$3:$AAD$1504,42,FALSE)=0/1/1900,"",VLOOKUP($A21,'8 Oct - LIVE LDS Data'!$A$3:$AAD$1504,42,FALSE)) -> 45341 | P21: =IF(VLOOKUP($A21,'8 Oct - LIVE LDS Data'!$A$3:$AAD$1504,48,FALSE)=0/1/1900,"",VLOOKUP($A21,'8 Oct - LIVE LDS Data'!$A$3:$AAD$1504,48,FALSE)) -> 45446 | Q21: =IF(VLOOKUP($A21,'8 Oct - LIVE LDS Data'!$A$3:$AAD$1504,49,FALSE)=0/1/1900,"",VLOOKUP($A21,'8 Oct - LIVE LDS Data'!$A$3:$AAD$1504,49,FALSE)) -> 45488 | R21: =IF(VLOOKUP($A21,'8 Oct - LIVE LDS Data'!$A$3:$AAD$1504,55,FALSE)=0/1/1900,"",VLOOKUP($A21,'8 Oct - LIVE LDS Data'!$A$3:$AAD$1504,55,FALSE)) | S21: =IF(VLOOKUP($A21,'8 Oct - LIVE LDS Data'!$A$3:$AAD$1504,56,FALSE)=0/1/1900,"",VLOOKUP($A21,'8 Oct - LIVE LDS Data'!$A$3:$AAD$1504,56,FALSE)) | T21: =IF(VLOOKUP($A21,'8 Oct - LIVE LDS Data'!$A$3:$AAD$1504,61,FALSE)=0/1/1900,"",VLOOKUP($A21,'8 Oct - LIVE LDS Data'!$A$3:$AAD$1504,61,FALSE)) | U21: =IF(VLOOKUP($A21,'8 Oct - LIVE LDS Data'!$A$3:$AAD$1504,64,FALSE)=0/1/1900,"",VLOOKUP($A21,'8 Oct - LIVE LDS Data'!$A$3:$AAD$1504,64,FALSE)) | V21: =IF(VLOOKUP($A21,'8 Oct - LIVE LDS Data'!$A$3:$AAD$1504,67,FALSE)=0/1/1900,"",VLOOKUP($A21,'8 Oct - LIVE LDS Data'!$A$3:$AAD$1504,67,FALSE)) | W21: =IF(VLOOKUP($A21,'8 Oct - LIVE LDS Data'!$A$3:$AAD$1504,80,FALSE)=0/1/1900,"",VLOOKUP($A21,'8 Oct - LIVE LDS Data'!$A$3:$AAD$1504,80,FALSE)) | X21: YES | Y21: =IF(VLOOKUP($A21,'8 Oct - LIVE LDS Data'!$A$3:$AAD$1504,73,FALSE)=0/1/1900,"",VLOOKUP($A21,'8 Oct - LIVE LDS Data'!$A$3:$AAD$1504,73,FALSE)) -> 45950 | Z21: =IF(VLOOKUP($A21,'8 Oct - LIVE LDS Data'!$A$3:$AAD$1504,74,FALSE)=0/1/1900,"",VLOOKUP($A21,'8 Oct - LIVE LDS Data'!$A$3:$AAD$1504,74,FALSE)) -> Robert Putnam | AA21: =IF(VLOOKUP($A21,'8 Oct - LIVE LDS Data'!$A$3:$AAD$1504,76,FALSE)=0/1/1900,"",VLOOKUP($A21,'8 Oct - LIVE LDS Data'!$A$3:$AAD$1504,76,FALSE)) -> 45950 | AB21: =IF(VLOOKUP($A21,'8 Oct - LIVE LDS Data'!$A$3:$AAD$1504,77,FALSE)=0/1/1900,"",VLOOKUP($A21,'8 Oct - LIVE LDS Data'!$A$3:$AAD$1504,77,FALSE)) -> Robert Putnam
A22: E09000005 | C22: Brent | F22: =IF(VLOOKUP($A22,'8 Oct - LIVE LDS Data'!$A$3:$AAD$1504,4,FALSE)=0/1/1900,"",VLOOKUP($A22,'8 Oct - LIVE LDS Data'!$A$3:$AAD$1504,4,FALSE)) -> Brent Local Plan | G22: =IF(VLOOKUP($A22,'8 Oct - LIVE LDS Data'!$A$3:$AAD$1504,6,FALSE)=0/1/1900,"",VLOOKUP($A22,'8 Oct - LIVE LDS Data'!$A$3:$AAD$1504,6,FALSE)) | H22: =IF(VLOOKUP($A22,'8 Oct - LIVE LDS Data'!$A$3:$AAD$1504,7,FALSE)=0/1/1900,"",VLOOKUP($A22,'8 Oct - LIVE LDS Data'!$A$3:$AAD$1504,7,FALSE)) | I22: =IF(VLOOKUP($A22,'8 Oct - LIVE LDS Data'!$A$3:$AAD$1504,8,FALSE)=0/1/1900,"",VLOOKUP($A22,'8 Oct - LIVE LDS Data'!$A$3:$AAD$1504,8,FALSE)) -> N | J22: =IF(VLOOKUP($A22,'8 Oct - LIVE LDS Data'!$A$3:$AAD$1504,9,FALSE)=0/1/1900,"",VLOOKUP($A22,'8 Oct - LIVE LDS Data'!$A$3:$AAD$1504,9,FALSE)) -> N | K22: =IF(VLOOKUP($A22,'8 Oct - LIVE LDS Data'!$A$3:$AAD$1504,10,FALSE)=0/1/1900,"",VLOOKUP($A22,'8 Oct - LIVE LDS Data'!$A$3:$AAD$1504,10,FALSE)) -> 44616 | L22: =IF(VLOOKUP($A22,'8 Oct - LIVE LDS Data'!$A$3:$AAD$1504,34,FALSE)=0/1/1900,"",VLOOKUP($A22,'8 Oct - LIVE LDS Data'!$A$3:$AAD$1504,34,FALSE)) | M22: =IF(VLOOKUP($A22,'8 Oct - LIVE LDS Data'!$A$3:$AAD$1504,35,FALSE)=0/1/1900,"",VLOOKUP($A22,'8 Oct - LIVE LDS Data'!$A$3:$AAD$1504,35,FALSE)) | N22: =IF(VLOOKUP($A22,'8 Oct - LIVE LDS Data'!$A$3:$AAD$1504,41,FALSE)=0/1/1900,"",VLOOKUP($A22,'8 Oct - LIVE LDS Data'!$A$3:$AAD$1504,41,FALSE)) | O22: =IF(VLOOKUP($A22,'8 Oct - LIVE LDS Data'!$A$3:$AAD$1504,42,FALSE)=0/1/1900,"",VLOOKUP($A22,'8 Oct - LIVE LDS Data'!$A$3:$AAD$1504,42,FALSE)) | P22: =IF(VLOOKUP($A22,'8 Oct - LIVE LDS Data'!$A$3:$AAD$1504,48,FALSE)=0/1/1900,"",VLOOKUP($A22,'8 Oct - LIVE LDS Data'!$A$3:$AAD$1504,48,FALSE)) | Q22: =IF(VLOOKUP($A22,'8 Oct - LIVE LDS Data'!$A$3:$AAD$1504,49,FALSE)=0/1/1900,"",VLOOKUP($A22,'8 Oct - LIVE LDS Data'!$A$3:$AAD$1504,49,FALSE)) | R22: =IF(VLOOKUP($A22,'8 Oct - LIVE LDS Data'!$A$3:$AAD$1504,55,FALSE)=0/1/1900,"",VLOOKUP($A22,'8 Oct - LIVE LDS Data'!$A$3:$AAD$1504,55,FALSE)) | S22: =IF(VLOOKUP($A22,'8 Oct - LIVE LDS Data'!$A$3:$AAD$1504,56,FALSE)=0/1/1900,"",VLOOKUP($A22,'8 Oct - LIVE LDS Data'!$A$3:$AAD$1504,56,FALSE)) | T22: =IF(VLOOKUP($A22,'8 Oct - LIVE LDS Data'!$A$3:$AAD$1504,61,FALSE)=0/1/1900,"",VLOOKUP($A22,'8 Oct - LIVE LDS Data'!$A$3:$AAD$1504,61,FALSE)) | U22: =IF(VLOOKUP($A22,'8 Oct - LIVE LDS Data'!$A$3:$AAD$1504,64,FALSE)=0/1/1900,"",VLOOKUP($A22,'8 Oct - LIVE LDS Data'!$A$3:$AAD$1504,64,FALSE)) | V22: =IF(VLOOKUP($A22,'8 Oct - LIVE LDS Data'!$A$3:$AAD$1504,67,FALSE)=0/1/1900,"",VLOOKUP($A22,'8 Oct - LIVE LDS Data'!$A$3:$AAD$1504,67,FALSE)) | W22: =IF(VLOOKUP($A22,'8 Oct - LIVE LDS Data'!$A$3:$AAD$1504,80,FALSE)=0/1/1900,"",VLOOKUP($A22,'8 Oct - LIVE LDS Data'!$A$3:$AAD$1504,80,FALSE)) | X22: YES | Y22: =IF(VLOOKUP($A22,'8 Oct - LIVE LDS Data'!$A$3:$AAD$1504,73,FALSE)=0/1/1900,"",VLOOKUP($A22,'8 Oct - LIVE LDS Data'!$A$3:$AAD$1504,73,FALSE)) -> 45888 | Z22: =IF(VLOOKUP($A22,'8 Oct - LIVE LDS Data'!$A$3:$AAD$1504,74,FALSE)=0/1/1900,"",VLOOKUP($A22,'8 Oct - LIVE LDS Data'!$A$3:$AAD$1504,74,FALSE)) -> Robert Putnam | AA22: =IF(VLOOKUP($A22,'8 Oct - LIVE LDS Data'!$A$3:$AAD$1504,76,FALSE)=0/1/1900,"",VLOOKUP($A22,'8 Oct - LIVE LDS Data'!$A$3:$AAD$1504,76,FALSE)) -> 45888 | AB22: =IF(VLOOKUP($A22,'8 Oct - LIVE LDS Data'!$A$3:$AAD$1504,77,FALSE)=0/1/1900,"",VLOOKUP($A22,'8 Oct - LIVE LDS Data'!$A$3:$AAD$1504,77,FALSE)) -> Robert Putnam
A23: E07000068 | C23: Brentwood | F23: =IF(VLOOKUP($A23,'8 Oct - LIVE LDS Data'!$A$3:$AAD$1504,4,FALSE)=0/1/1900,"",VLOOKUP($A23,'8 Oct - LIVE LDS Data'!$A$3:$AAD$1504,4,FALSE)) -> Brentwood Local Plan | G23: =IF(VLOOKUP($A23,'8 Oct - LIVE LDS Data'!$A$3:$AAD$1504,6,FALSE)=0/1/1900,"",VLOOKUP($A23,'8 Oct - LIVE LDS Data'!$A$3:$AAD$1504,6,FALSE)) | H23: =IF(VLOOKUP($A23,'8 Oct - LIVE LDS Data'!$A$3:$AAD$1504,7,FALSE)=0/1/1900,"",VLOOKUP($A23,'8 Oct - LIVE LDS Data'!$A$3:$AAD$1504,7,FALSE)) | I23: =IF(VLOOKUP($A23,'8 Oct - LIVE LDS Data'!$A$3:$AAD$1504,8,FALSE)=0/1/1900,"",VLOOKUP($A23,'8 Oct - LIVE LDS Data'!$A$3:$AAD$1504,8,FALSE)) -> N | J23: =IF(VLOOKUP($A23,'8 Oct - LIVE LDS Data'!$A$3:$AAD$1504,9,FALSE)=0/1/1900,"",VLOOKUP($A23,'8 Oct - LIVE LDS Data'!$A$3:$AAD$1504,9,FALSE)) -> N | K23: =IF(VLOOKUP($A23,'8 Oct - LIVE LDS Data'!$A$3:$AAD$1504,10,FALSE)=0/1/1900,"",VLOOKUP($A23,'8 Oct - LIVE LDS Data'!$A$3:$AAD$1504,10,FALSE)) -> 44643 | L23: =IF(VLOOKUP($A23,'8 Oct - LIVE LDS Data'!$A$3:$AAD$1504,34,FALSE)=0/1/1900,"",VLOOKUP($A23,'8 Oct - LIVE LDS Data'!$A$3:$AAD$1504,34,FALSE)) | M23: =IF(VLOOKUP($A23,'8 Oct - LIVE LDS Data'!$A$3:$AAD$1504,35,FALSE)=0/1/1900,"",VLOOKUP($A23,'8 Oct - LIVE LDS Data'!$A$3:$AAD$1504,35,FALSE)) | N23: =IF(VLOOKUP($A23,'8 Oct - LIVE LDS Data'!$A$3:$AAD$1504,41,FALSE)=0/1/1900,"",VLOOKUP($A23,'8 Oct - LIVE LDS Data'!$A$3:$AAD$1504,41,FALSE)) | O23: =IF(VLOOKUP($A23,'8 Oct - LIVE LDS Data'!$A$3:$AAD$1504,42,FALSE)=0/1/1900,"",VLOOKUP($A23,'8 Oct - LIVE LDS Data'!$A$3:$AAD$1504,42,FALSE)) | P23: =IF(VLOOKUP($A23,'8 Oct - LIVE LDS Data'!$A$3:$AAD$1504,48,FALSE)=0/1/1900,"",VLOOKUP($A23,'8 Oct - LIVE LDS Data'!$A$3:$AAD$1504,48,FALSE)) | Q23: =IF(VLOOKUP($A23,'8 Oct - LIVE LDS Data'!$A$3:$AAD$1504,49,FALSE)=0/1/1900,"",VLOOKUP($A23,'8 Oct - LIVE LDS Data'!$A$3:$AAD$1504,49,FALSE)) | R23: =IF(VLOOKUP($A23,'8 Oct - LIVE LDS Data'!$A$3:$AAD$1504,55,FALSE)=0/1/1900,"",VLOOKUP($A23,'8 Oct - LIVE LDS Data'!$A$3:$AAD$1504,55,FALSE)) | S23: =IF(VLOOKUP($A23,'8 Oct - LIVE LDS Data'!$A$3:$AAD$1504,56,FALSE)=0/1/1900,"",VLOOKUP($A23,'8 Oct - LIVE LDS Data'!$A$3:$AAD$1504,56,FALSE)) | T23: =IF(VLOOKUP($A23,'8 Oct - LIVE LDS Data'!$A$3:$AAD$1504,61,FALSE)=0/1/1900,"",VLOOKUP($A23,'8 Oct - LIVE LDS Data'!$A$3:$AAD$1504,61,FALSE)) | U23: =IF(VLOOKUP($A23,'8 Oct - LIVE LDS Data'!$A$3:$AAD$1504,64,FALSE)=0/1/1900,"",VLOOKUP($A23,'8 Oct - LIVE LDS Data'!$A$3:$AAD$1504,64,FALSE)) | V23: =IF(VLOOKUP($A23,'8 Oct - LIVE LDS Data'!$A$3:$AAD$1504,67,FALSE)=0/1/1900,"",VLOOKUP($A23,'8 Oct - LIVE LDS Data'!$A$3:$AAD$1504,67,FALSE)) | W23: =IF(VLOOKUP($A23,'8 Oct - LIVE LDS Data'!$A$3:$AAD$1504,80,FALSE)=0/1/1900,"",VLOOKUP($A23,'8 Oct - LIVE LDS Data'!$A$3:$AAD$1504,80,FALSE)) | X23: YES | Y23: =IF(VLOOKUP($A23,'8 Oct - LIVE LDS Data'!$A$3:$AAD$1504,73,FALSE)=0/1/1900,"",VLOOKUP($A23,'8 Oct - LIVE LDS Data'!$A$3:$AAD$1504,73,FALSE)) -> 45902 | Z23: =IF(VLOOKUP($A23,'8 Oct - LIVE LDS Data'!$A$3:$AAD$1504,74,FALSE)=0/1/1900,"",VLOOKUP($A23,'8 Oct - LIVE LDS Data'!$A$3:$AAD$1504,74,FALSE)) -> Robert Putnam | AA23: =IF(VLOOKUP($A23,'8 Oct - LIVE LDS Data'!$A$3:$AAD$1504,76,FALSE)=0/1/1900,"",VLOOKUP($A23,'8 Oct - LIVE LDS Data'!$A$3:$AAD$1504,76,FALSE)) -> 45902 | AB23: =IF(VLOOKUP($A23,'8 Oct - LIVE LDS Data'!$A$3:$AAD$1504,77,FALSE)=0/1/1900,"",VLOOKUP($A23,'8 Oct - LIVE LDS Data'!$A$3:$AAD$1504,77,FALSE)) -> Robert Putnam
A24: E06000043 | C24: Brighton & Hove | F24: =IF(VLOOKUP($A24,'8 Oct - LIVE LDS Data'!$A$3:$AAD$1504,4,FALSE)=0/1/1900,"",VLOOKUP($A24,'8 Oct - LIVE LDS Data'!$A$3:$AAD$1504,4,FALSE)) -> City Plan Part 1 Review | G24: =IF(VLOOKUP($A24,'8 Oct - LIVE LDS Data'!$A$3:$AAD$1504,6,FALSE)=0/1/1900,"",VLOOKUP($A24,'8 Oct - LIVE LDS Data'!$A$3:$AAD$1504,6,FALSE)) | H24: =IF(VLOOKUP($A24,'8 Oct - LIVE LDS Data'!$A$3:$AAD$1504,7,FALSE)=0/1/1900,"",VLOOKUP($A24,'8 Oct - LIVE LDS Data'!$A$3:$AAD$1504,7,FALSE)) | I24: =IF(VLOOKUP($A24,'8 Oct - LIVE LDS Data'!$A$3:$AAD$1504,8,FALSE)=0/1/1900,"",VLOOKUP($A24,'8 Oct - LIVE LDS Data'!$A$3:$AAD$1504,8,FALSE)) -> N | J24: =IF(VLOOKUP($A24,'8 Oct - LIVE LDS Data'!$A$3:$AAD$1504,9,FALSE)=0/1/1900,"",VLOOKUP($A24,'8 Oct - LIVE LDS Data'!$A$3:$AAD$1504,9,FALSE)) -> N | K24: =IF(VLOOKUP($A24,'8 Oct - LIVE LDS Data'!$A$3:$AAD$1504,10,FALSE)=0/1/1900,"",VLOOKUP($A24,'8 Oct - LIVE LDS Data'!$A$3:$AAD$1504,10,FALSE)) -> 42453 | L24: =IF(VLOOKUP($A24,'8 Oct - LIVE LDS Data'!$A$3:$AAD$1504,34,FALSE)=0/1/1900,"",VLOOKUP($A24,'8 Oct - LIVE LDS Data'!$A$3:$AAD$1504,34,FALSE)) | M24: =IF(VLOOKUP($A24,'8 Oct - LIVE LDS Data'!$A$3:$AAD$1504,35,FALSE)=0/1/1900,"",VLOOKUP($A24,'8 Oct - LIVE LDS Data'!$A$3:$AAD$1504,35,FALSE)) -> 45677 | N24: =IF(VLOOKUP($A24,'8 Oct - LIVE LDS Data'!$A$3:$AAD$1504,41,FALSE)=0/1/1900,"",VLOOKUP($A24,'8 Oct - LIVE LDS Data'!$A$3:$AAD$1504,41,FALSE)) | O24: =IF(VLOOKUP($A24,'8 Oct - LIVE LDS Data'!$A$3:$AAD$1504,42,FALSE)=0/1/1900,"",VLOOKUP($A24,'8 Oct - LIVE LDS Data'!$A$3:$AAD$1504,42,FALSE)) | P24: =IF(VLOOKUP($A24,'8 Oct - LIVE LDS Data'!$A$3:$AAD$1504,48,FALSE)=0/1/1900,"",VLOOKUP($A24,'8 Oct - LIVE LDS Data'!$A$3:$AAD$1504,48,FALSE)) | Q24: =IF(VLOOKUP($A24,'8 Oct - LIVE LDS Data'!$A$3:$AAD$1504,49,FALSE)=0/1/1900,"",VLOOKUP($A24,'8 Oct - LIVE LDS Data'!$A$3:$AAD$1504,49,FALSE)) | R24: =IF(VLOOKUP($A24,'8 Oct - LIVE LDS Data'!$A$3:$AAD$1504,55,FALSE)=0/1/1900,"",VLOOKUP($A24,'8 Oct - LIVE LDS Data'!$A$3:$AAD$1504,55,FALSE)) | S24: =IF(VLOOKUP($A24,'8 Oct - LIVE LDS Data'!$A$3:$AAD$1504,56,FALSE)=0/1/1900,"",VLOOKUP($A24,'8 Oct - LIVE LDS Data'!$A$3:$AAD$1504,56,FALSE)) | T24: =IF(VLOOKUP($A24,'8 Oct - LIVE LDS Data'!$A$3:$AAD$1504,61,FALSE)=0/1/1900,"",VLOOKUP($A24,'8 Oct - LIVE LDS Data'!$A$3:$AAD$1504,61,FALSE)) | U24: =IF(VLOOKUP($A24,'8 Oct - LIVE LDS Data'!$A$3:$AAD$1504,64,FALSE)=0/1/1900,"",VLOOKUP($A24,'8 Oct - LIVE LDS Data'!$A$3:$AAD$1504,64,FALSE)) | V24: =IF(VLOOKUP($A24,'8 Oct - LIVE LDS Data'!$A$3:$AAD$1504,67,FALSE)=0/1/1900,"",VLOOKUP($A24,'8 Oct - LIVE LDS Data'!$A$3:$AAD$1504,67,FALSE)) | W24: =IF(VLOOKUP($A24,'8 Oct - LIVE LDS Data'!$A$3:$AAD$1504,80,FALSE)=0/1/1900,"",VLOOKUP($A24,'8 Oct - LIVE LDS Data'!$A$3:$AAD$1504,80,FALSE)) | X24: YES | Y24: =IF(VLOOKUP($A24,'8 Oct - LIVE LDS Data'!$A$3:$AAD$1504,73,FALSE)=0/1/1900,"",VLOOKUP($A24,'8 Oct - LIVE LDS Data'!$A$3:$AAD$1504,73,FALSE)) -> 45716 | Z24: =IF(VLOOKUP($A24,'8 Oct - LIVE LDS Data'!$A$3:$AAD$1504,74,FALSE)=0/1/1900,"",VLOOKUP($A24,'8 Oct - LIVE LDS Data'!$A$3:$AAD$1504,74,FALSE)) -> Robert Putnam | AA24: =IF(VLOOKUP($A24,'8 Oct - LIVE LDS Data'!$A$3:$AAD$1504,76,FALSE)=0/1/1900,"",VLOOKUP($A24,'8 Oct - LIVE LDS Data'!$A$3:$AAD$1504,76,FALSE)) -> 45716 | AB24: =IF(VLOOKUP($A24,'8 Oct - LIVE LDS Data'!$A$3:$AAD$1504,77,FALSE)=0/1/1900,"",VLOOKUP($A24,'8 Oct - LIVE LDS Data'!$A$3:$AAD$1504,77,FALSE)) -> Robert Putnam
A25: E26000007 | C25: Broads | F25: =IF(VLOOKUP($A25,'8 Oct - LIVE LDS Data'!$A$3:$AAD$1504,4,FALSE)=0/1/1900,"",VLOOKUP($A25,'8 Oct - LIVE LDS Data'!$A$3:$AAD$1504,4,FALSE)) -> Broads Local Plan Review | G25: =IF(VLOOKUP($A25,'8 Oct - LIVE LDS Data'!$A$3:$AAD$1504,6,FALSE)=0/1/1900,"",VLOOKUP($A25,'8 Oct - LIVE LDS Data'!$A$3:$AAD$1504,6,FALSE)) -> 2021 | H25: =IF(VLOOKUP($A25,'8 Oct - LIVE LDS Data'!$A$3:$AAD$1504,7,FALSE)=0/1/1900,"",VLOOKUP($A25,'8 Oct - LIVE LDS Data'!$A$3:$AAD$1504,7,FALSE)) -> 2041 | I25: =IF(VLOOKUP($A25,'8 Oct - LIVE LDS Data'!$A$3:$AAD$1504,8,FALSE)=0/1/1900,"",VLOOKUP($A25,'8 Oct - LIVE LDS Data'!$A$3:$AAD$1504,8,FALSE)) -> N | J25: =IF(VLOOKUP($A25,'8 Oct - LIVE LDS Data'!$A$3:$AAD$1504,9,FALSE)=0/1/1900,"",VLOOKUP($A25,'8 Oct - LIVE LDS Data'!$A$3:$AAD$1504,9,FALSE)) -> N | K25: =IF(VLOOKUP($A25,'8 Oct - LIVE LDS Data'!$A$3:$AAD$1504,10,FALSE)=0/1/1900,"",VLOOKUP($A25,'8 Oct - LIVE LDS Data'!$A$3:$AAD$1504,10,FALSE)) -> 43602 | L25: =IF(VLOOKUP($A25,'8 Oct - LIVE LDS Data'!$A$3:$AAD$1504,34,FALSE)=0/1/1900,"",VLOOKUP($A25,'8 Oct - LIVE LDS Data'!$A$3:$AAD$1504,34,FALSE)) -> 44837 | M25: =IF(VLOOKUP($A25,'8 Oct - LIVE LDS Data'!$A$3:$AAD$1504,35,FALSE)=0/1/1900,"",VLOOKUP($A25,'8 Oct - LIVE LDS Data'!$A$3:$AAD$1504,35,FALSE)) -> 44904 | N25: =IF(VLOOKUP($A25,'8 Oct - LIVE LDS Data'!$A$3:$AAD$1504,41,FALSE)=0/1/1900,"",VLOOKUP($A25,'8 Oct - LIVE LDS Data'!$A$3:$AAD$1504,41,FALSE)) | O25: =IF(VLOOKUP($A25,'8 Oct - LIVE LDS Data'!$A$3:$AAD$1504,42,FALSE)=0/1/1900,"",VLOOKUP($A25,'8 Oct - LIVE LDS Data'!$A$3:$AAD$1504,42,FALSE)) -> 45429 | P25: =IF(VLOOKUP($A25,'8 Oct - LIVE LDS Data'!$A$3:$AAD$1504,48,FALSE)=0/1/1900,"",VLOOKUP($A25,'8 Oct - LIVE LDS Data'!$A$3:$AAD$1504,48,FALSE)) | Q25: =IF(VLOOKUP($A25,'8 Oct - LIVE LDS Data'!$A$3:$AAD$1504,49,FALSE)=0/1/1900,"",VLOOKUP($A25,'8 Oct - LIVE LDS Data'!$A$3:$AAD$1504,49,FALSE)) | R25: =IF(VLOOKUP($A25,'8 Oct - LIVE LDS Data'!$A$3:$AAD$1504,55,FALSE)=0/1/1900,"",VLOOKUP($A25,'8 Oct - LIVE LDS Data'!$A$3:$AAD$1504,55,FALSE)) | S25: =IF(VLOOKUP($A25,'8 Oct - LIVE LDS Data'!$A$3:$AAD$1504,56,FALSE)=0/1/1900,"",VLOOKUP($A25,'8 Oct - LIVE LDS Data'!$A$3:$AAD$1504,56,FALSE)) | T25: =IF(VLOOKUP($A25,'8 Oct - LIVE LDS Data'!$A$3:$AAD$1504,61,FALSE)=0/1/1900,"",VLOOKUP($A25,'8 Oct - LIVE LDS Data'!$A$3:$AAD$1504,61,FALSE)) | U25: =IF(VLOOKUP($A25,'8 Oct - LIVE LDS Data'!$A$3:$AAD$1504,64,FALSE)=0/1/1900,"",VLOOKUP($A25,'8 Oct - LIVE LDS Data'!$A$3:$AAD$1504,64,FALSE)) | V25: =IF(VLOOKUP($A25,'8 Oct - LIVE LDS Data'!$A$3:$AAD$1504,67,FALSE)=0/1/1900,"",VLOOKUP($A25,'8 Oct - LIVE LDS Data'!$A$3:$AAD$1504,67,FALSE)) | W25: =IF(VLOOKUP($A25,'8 Oct - LIVE LDS Data'!$A$3:$AAD$1504,80,FALSE)=0/1/1900,"",VLOOKUP($A25,'8 Oct - LIVE LDS Data'!$A$3:$AAD$1504,80,FALSE)) | X25: YES | Y25: =IF(VLOOKUP($A25,'8 Oct - LIVE LDS Data'!$A$3:$AAD$1504,73,FALSE)=0/1/1900,"",VLOOKUP($A25,'8 Oct - LIVE LDS Data'!$A$3:$AAD$1504,73,FALSE)) -> 45700 | Z25: =IF(VLOOKUP($A25,'8 Oct - LIVE LDS Data'!$A$3:$AAD$1504,74,FALSE)=0/1/1900,"",VLOOKUP($A25,'8 Oct - LIVE LDS Data'!$A$3:$AAD$1504,74,FALSE)) -> Robert Putnam | AA25: =IF(VLOOKUP($A25,'8 Oct - LIVE LDS Data'!$A$3:$AAD$1504,76,FALSE)=0/1/1900,"",VLOOKUP($A25,'8 Oct - LIVE LDS Data'!$A$3:$AAD$1504,76,FALSE)) -> 45700 | AB25: =IF(VLOOKUP($A25,'8 Oct - LIVE LDS Data'!$A$3:$AAD$1504,77,FALSE)=0/1/1900,"",VLOOKUP($A25,'8 Oct - LIVE LDS Data'!$A$3:$AAD$1504,77,FALSE)) -> Robert Putnam
A26: E09000006 | C26: Bromley | F26: =IF(VLOOKUP($A26,'8 Oct - LIVE LDS Data'!$A$3:$AAD$1504,4,FALSE)=0/1/1900,"",VLOOKUP($A26,'8 Oct - LIVE LDS Data'!$A$3:$AAD$1504,4,FALSE)) -> Review of the Bromley Local Plan | G26: =IF(VLOOKUP($A26,'8 Oct - LIVE LDS Data'!$A$3:$AAD$1504,6,FALSE)=0/1/1900,"",VLOOKUP($A26,'8 Oct - LIVE LDS Data'!$A$3:$AAD$1504,6,FALSE)) -> 2023 | H26: =IF(VLOOKUP($A26,'8 Oct - LIVE LDS Data'!$A$3:$AAD$1504,7,FALSE)=0/1/1900,"",VLOOKUP($A26,'8 Oct - LIVE LDS Data'!$A$3:$AAD$1504,7,FALSE)) -> 2038 | I26: =IF(VLOOKUP($A26,'8 Oct - LIVE LDS Data'!$A$3:$AAD$1504,8,FALSE)=0/1/1900,"",VLOOKUP($A26,'8 Oct - LIVE LDS Data'!$A$3:$AAD$1504,8,FALSE)) -> N | J26: =IF(VLOOKUP($A26,'8 Oct - LIVE LDS Data'!$A$3:$AAD$1504,9,FALSE)=0/1/1900,"",VLOOKUP($A26,'8 Oct - LIVE LDS Data'!$A$3:$AAD$1504,9,FALSE)) -> N | K26: =IF(VLOOKUP($A26,'8 Oct - LIVE LDS Data'!$A$3:$AAD$1504,10,FALSE)=0/1/1900,"",VLOOKUP($A26,'8 Oct - LIVE LDS Data'!$A$3:$AAD$1504,10,FALSE)) -> 43481 | L26: =IF(VLOOKUP($A26,'8 Oct - LIVE LDS Data'!$A$3:$AAD$1504,34,FALSE)=0/1/1900,"",VLOOKUP($A26,'8 Oct - LIVE LDS Data'!$A$3:$AAD$1504,34,FALSE)) -> 45017 | M26: =IF(VLOOKUP($A26,'8 Oct - LIVE LDS Data'!$A$3:$AAD$1504,35,FALSE)=0/1/1900,"",VLOOKUP($A26,'8 Oct - LIVE LDS Data'!$A$3:$AAD$1504,35,FALSE)) -> 45078 | N26: =IF(VLOOKUP($A26,'8 Oct - LIVE LDS Data'!$A$3:$AAD$1504,41,FALSE)=0/1/1900,"",VLOOKUP($A26,'8 Oct - LIVE LDS Data'!$A$3:$AAD$1504,41,FALSE)) | O26: =IF(VLOOKUP($A26,'8 Oct - LIVE LDS Data'!$A$3:$AAD$1504,42,FALSE)=0/1/1900,"",VLOOKUP($A26,'8 Oct - LIVE LDS Data'!$A$3:$AAD$1504,42,FALSE)) | P26: =IF(VLOOKUP($A26,'8 Oct - LIVE LDS Data'!$A$3:$AAD$1504,48,FALSE)=0/1/1900,"",VLOOKUP($A26,'8 Oct - LIVE LDS Data'!$A$3:$AAD$1504,48,FALSE)) | Q26: =IF(VLOOKUP($A26,'8 Oct - LIVE LDS Data'!$A$3:$AAD$1504,49,FALSE)=0/1/1900,"",VLOOKUP($A26,'8 Oct - LIVE LDS Data'!$A$3:$AAD$1504,49,FALSE)) | R26: =IF(VLOOKUP($A26,'8 Oct - LIVE LDS Data'!$A$3:$AAD$1504,55,FALSE)=0/1/1900,"",VLOOKUP($A26,'8 Oct - LIVE LDS Data'!$A$3:$AAD$1504,55,FALSE)) | S26: =IF(VLOOKUP($A26,'8 Oct - LIVE LDS Data'!$A$3:$AAD$1504,56,FALSE)=0/1/1900,"",VLOOKUP($A26,'8 Oct - LIVE LDS Data'!$A$3:$AAD$1504,56,FALSE)) | T26: =IF(VLOOKUP($A26,'8 Oct - LIVE LDS Data'!$A$3:$AAD$1504,61,FALSE)=0/1/1900,"",VLOOKUP($A26,'8 Oct - LIVE LDS Data'!$A$3:$AAD$1504,61,FALSE)) | U26: =IF(VLOOKUP($A26,'8 Oct - LIVE LDS Data'!$A$3:$AAD$1504,64,FALSE)=0/1/1900,"",VLOOKUP($A26,'8 Oct - LIVE LDS Data'!$A$3:$AAD$1504,64,FALSE)) | V26: =IF(VLOOKUP($A26,'8 Oct - LIVE LDS Data'!$A$3:$AAD$1504,67,FALSE)=0/1/1900,"",VLOOKUP($A26,'8 Oct - LIVE LDS Data'!$A$3:$AAD$1504,67,FALSE)) | W26: =IF(VLOOKUP($A26,'8 Oct - LIVE LDS Data'!$A$3:$AAD$1504,80,FALSE)=0/1/1900,"",VLOOKUP($A26,'8 Oct - LIVE LDS Data'!$A$3:$AAD$1504,80,FALSE)) | X26: YES | Y26: =IF(VLOOKUP($A26,'8 Oct - LIVE LDS Data'!$A$3:$AAD$1504,73,FALSE)=0/1/1900,"",VLOOKUP($A26,'8 Oct - LIVE LDS Data'!$A$3:$AAD$1504,73,FALSE)) -> 45681 | Z26: =IF(VLOOKUP($A26,'8 Oct - LIVE LDS Data'!$A$3:$AAD$1504,74,FALSE)=0/1/1900,"",VLOOKUP($A26,'8 Oct - LIVE LDS Data'!$A$3:$AAD$1504,74,FALSE)) -> Robert Putnam | AA26: =IF(VLOOKUP($A26,'8 Oct - LIVE LDS Data'!$A$3:$AAD$1504,76,FALSE)=0/1/1900,"",VLOOKUP($A26,'8 Oct - LIVE LDS Data'!$A$3:$AAD$1504,76,FALSE)) -> 45681 | AB26: =IF(VLOOKUP($A26,'8 Oct - LIVE LDS Data'!$A$3:$AAD$1504,77,FALSE)=0/1/1900,"",VLOOKUP($A26,'8 Oct - LIVE LDS Data'!$A$3:$AAD$1504,77,FALSE))
A27: E07000234 | C27: Bromsgrove | F27: =IF(VLOOKUP($A27,'8 Oct - LIVE LDS Data'!$A$3:$AAD$1504,4,FALSE)=0/1/1900,"",VLOOKUP($A27,'8 Oct - LIVE LDS Data'!$A$3:$AAD$1504,4,FALSE)) -> Local Plan Review | G27: =IF(VLOOKUP($A27,'8 Oct - LIVE LDS Data'!$A$3:$AAD$1504,6,FALSE)=0/1/1900,"",VLOOKUP($A27,'8 Oct - LIVE LDS Data'!$A$3:$AAD$1504,6,FALSE)) | H27: =IF(VLOOKUP($A27,'8 Oct - LIVE LDS Data'!$A$3:$AAD$1504,7,FALSE)=0/1/1900,"",VLOOKUP($A27,'8 Oct - LIVE LDS Data'!$A$3:$AAD$1504,7,FALSE)) | I27: =IF(VLOOKUP($A27,'8 Oct - LIVE LDS Data'!$A$3:$AAD$1504,8,FALSE)=0/1/1900,"",VLOOKUP($A27,'8 Oct - LIVE LDS Data'!$A$3:$AAD$1504,8,FALSE)) -> N | J27: =IF(VLOOKUP($A27,'8 Oct - LIVE LDS Data'!$A$3:$AAD$1504,9,FALSE)=0/1/1900,"",VLOOKUP($A27,'8 Oct - LIVE LDS Data'!$A$3:$AAD$1504,9,FALSE)) -> N | K27: =IF(VLOOKUP($A27,'8 Oct - LIVE LDS Data'!$A$3:$AAD$1504,10,FALSE)=0/1/1900,"",VLOOKUP($A27,'8 Oct - LIVE LDS Data'!$A$3:$AAD$1504,10,FALSE)) -> 42760 | L27: =IF(VLOOKUP($A27,'8 Oct - LIVE LDS Data'!$A$3:$AAD$1504,34,FALSE)=0/1/1900,"",VLOOKUP($A27,'8 Oct - LIVE LDS Data'!$A$3:$AAD$1504,34,FALSE)) | M27: =IF(VLOOKUP($A27,'8 Oct - LIVE LDS Data'!$A$3:$AAD$1504,35,FALSE)=0/1/1900,"",VLOOKUP($A27,'8 Oct - LIVE LDS Data'!$A$3:$AAD$1504,35,FALSE)) | N27: =IF(VLOOKUP($A27,'8 Oct - LIVE LDS Data'!$A$3:$AAD$1504,41,FALSE)=0/1/1900,"",VLOOKUP($A27,'8 Oct - LIVE LDS Data'!$A$3:$AAD$1504,41,FALSE)) | O27: =IF(VLOOKUP($A27,'8 Oct - LIVE LDS Data'!$A$3:$AAD$1504,42,FALSE)=0/1/1900,"",VLOOKUP($A27,'8 Oct - LIVE LDS Data'!$A$3:$AAD$1504,42,FALSE)) | P27: =IF(VLOOKUP($A27,'8 Oct - LIVE LDS Data'!$A$3:$AAD$1504,48,FALSE)=0/1/1900,"",VLOOKUP($A27,'8 Oct - LIVE LDS Data'!$A$3:$AAD$1504,48,FALSE)) | Q27: =IF(VLOOKUP($A27,'8 Oct - LIVE LDS Data'!$A$3:$AAD$1504,49,FALSE)=0/1/1900,"",VLOOKUP($A27,'8 Oct - LIVE LDS Data'!$A$3:$AAD$1504,49,FALSE)) | R27: =IF(VLOOKUP($A27,'8 Oct - LIVE LDS Data'!$A$3:$AAD$1504,55,FALSE)=0/1/1900,"",VLOOKUP($A27,'8 Oct - LIVE LDS Data'!$A$3:$AAD$1504,55,FALSE)) | S27: =IF(VLOOKUP($A27,'8 Oct - LIVE LDS Data'!$A$3:$AAD$1504,56,FALSE)=0/1/1900,"",VLOOKUP($A27,'8 Oct - LIVE LDS Data'!$A$3:$AAD$1504,56,FALSE)) | T27: =IF(VLOOKUP($A27,'8 Oct - LIVE LDS Data'!$A$3:$AAD$1504,61,FALSE)=0/1/1900,"",VLOOKUP($A27,'8 Oct - LIVE LDS Data'!$A$3:$AAD$1504,61,FALSE)) | U27: =IF(VLOOKUP($A27,'8 Oct - LIVE LDS Data'!$A$3:$AAD$1504,64,FALSE)=0/1/1900,"",VLOOKUP($A27,'8 Oct - LIVE LDS Data'!$A$3:$AAD$1504,64,FALSE)) | V27: =IF(VLOOKUP($A27,'8 Oct - LIVE LDS Data'!$A$3:$AAD$1504,67,FALSE)=0/1/1900,"",VLOOKUP($A27,'8 Oct - LIVE LDS Data'!$A$3:$AAD$1504,67,FALSE)) | W27: =IF(VLOOKUP($A27,'8 Oct - LIVE LDS Data'!$A$3:$AAD$1504,80,FALSE)=0/1/1900,"",VLOOKUP($A27,'8 Oct - LIVE LDS Data'!$A$3:$AAD$1504,80,FALSE)) | X27: YES | Y27: =IF(VLOOKUP($A27,'8 Oct - LIVE LDS Data'!$A$3:$AAD$1504,73,FALSE)=0/1/1900,"",VLOOKUP($A27,'8 Oct - LIVE LDS Data'!$A$3:$AAD$1504,73,FALSE)) -> 45764 | Z27: =IF(VLOOKUP($A27,'8 Oct - LIVE LDS Data'!$A$3:$AAD$1504,74,FALSE)=0/1/1900,"",VLOOKUP($A27,'8 Oct - LIVE LDS Data'!$A$3:$AAD$1504,74,FALSE)) -> Greg Foster | AA27: =IF(VLOOKUP($A27,'8 Oct - LIVE LDS Data'!$A$3:$AAD$1504,76,FALSE)=0/1/1900,"",VLOOKUP($A27,'8 Oct - LIVE LDS Data'!$A$3:$AAD$1504,76,FALSE)) -> 45888 | AB27: =IF(VLOOKUP($A27,'8 Oct - LIVE LDS Data'!$A$3:$AAD$1504,77,FALSE)=0/1/1900,"",VLOOKUP($A27,'8 Oct - LIVE LDS Data'!$A$3:$AAD$1504,77,FALSE)) -> Robert Putnam
